16bit_adder_subtractor/Behavior/16bit_adder.v
// implement 16 bit adder by behavior (signed)
module Sub_adder_16bit(sum, overdetect, cout, a, b, mode);

input [15:0] a, b;
input mode; // mode = 1: subtractor, mode = 0: adder
output [15:0] sum;
output cout, overdetect; // overflow detect 


assign {cout, sum} = (mode) ? (a + {~b + 1'b1}) : (a + b);

// detect overflow (for unsigned number)
// assign overdetect = cout;


// detect overflow for signed integers 
assign overdetect = 
   (((mode == 1) && (A[15] == 1) && (B[15] == 0) && (SUM[15] == 0)) || ((mode == 1) && (A[15] == 0) && (B[15] == 1) && (SUM[15] == 1)) 
|| ((mode == 0) && (A[15] == 0) && (B[15] == 0) && (SUM[15] == 1)) || ((mode == 0) && (A[15] == 1) && (B[15] == 1) && (SUM[15] == 0)) ? 1 : 0 ;





endmodule

16bit_adder_subtractor/Behavior/testbench.v
`include "./16bit_adder.v"
`timescale 1ns/10ps
`define delay 20 
module testbench();

reg [15:0] A, B;
reg Mode;
wire [15:0] SUM;
wire Cout, Overflow;

reg [15:0] mem_A [9999:0];
reg [15:0] mem_B [9999:0];
reg mem_ctrl [9999:0];
reg [16:0] expect [9999:0];

reg [16:0] error = 0;

// read the testing data
initial begin
	$readmemh("A.txt", mem_A);
	$readmemh("B.txt", mem_B);
	$readmemh("ctrl.txt", mem_ctrl);
	$readmemh("result.txt", expect);
end


Sub_adder_16bit S1(
    .a(A),
    .b(B),
    .mode(Mode),
    .cout(Cout),
    .sum(SUM),
    .overdetect(Overflow)
);

integer i;
initial begin
    for (i =0 ; i <= 9999; i = i + 1 ) begin
        A = mem_A[i] ;
        B = mem_B[i] ;
        Mode = mem_ctrl[i] ;

        #(`delay);
        if (SUM !== expect[i][15:0]) begin
            $display ("ERROR at time=%d(pattern%d): SUM(%h)!= expect(%h)", $time, i+1, SUM, expect[i][15:0]);
            error = error + 1;
        end
		
        if (Cout !== expect[i][16]) begin
            $display ("ERROR at time=%d(pattern%d): C_out(%b)!= expect(%b)", $time,  i+1, Cout, expect[i][16]);
            error = error + 1;
        end
        
        if (Overflow !== expect[i][17]) begin
            $display ("ERROR at time=%d(pattern%d): Overflow(%b)!= expect(%b)", $time,  i+1, Overflow, expect[i][16]);
            error = error + 1;
        end

    end

    if(error == 17'b0) begin
        $display("        ***********************************************        ");
        $display("        **                                           **        ");
        $display("        **             Congratulations !!            **        ");
        $display("        **               Test PASS  !!               **        ");
        $display("        **                                           **        ");
        $display("        ***********************************************        ");
    end
    else begin
        $display ("=================================================");
        $display ("There're %d errors in your design", error); 
        $display ("=================================================");
    end

	$finish ;

end

initial begin
    $dumpfile("16bitsub_adder.vcd");
    $dumpvars;
end

endmodule

16bit_adder_subtractor/Behavior/16bitsub_adder.vcd
$date
	Tue Oct 20 15:18:44 2020
$end
$version
	Icarus Verilog
$end
$timescale
	10ps
$end
$scope module testbench $end
$var wire 16 ! SUM [15:0] $end
$var wire 1 " Overflow $end
$var wire 1 # Cout $end
$var reg 16 $ A [15:0] $end
$var reg 16 % B [15:0] $end
$var reg 1 & Mode $end
$var reg 17 ' error [16:0] $end
$var integer 32 ( i [31:0] $end
$scope module S1 $end
$var wire 16 ) a [15:0] $end
$var wire 16 * b [15:0] $end
$var wire 1 & mode $end
$var wire 1 " overdetect $end
$var wire 16 + sum [15:0] $end
$var wire 1 # cout $end
$upscope $end
$upscope $end
$enddefinitions $end
#0
$dumpvars
b1100011100010000 +
b1011101110111101 *
b101101010011 )
b0 (
b0 '
0&
b1011101110111101 %
b101101010011 $
0#
0"
b1100011100010000 !
$end
#2000
b1101101101100110 !
b1101101101100110 +
b1011111000001000 %
b1011111000001000 *
b1110101011110 $
b1110101011110 )
b1 (
#4000
b1110001011001010 !
b1110001011001010 +
1&
b11000111101011 %
b11000111101011 *
b1010010110101 $
b1010010110101 )
b10 (
#6000
b10001101111000 !
b10001101111000 +
1"
1#
b11001000010001 %
b11001000010001 *
b101010110001001 $
b101010110001001 )
b11 (
#8000
0"
0#
b1010100011000100 !
b1010100011000100 +
b1101111011110100 %
b1101111011110100 *
b1000011110111000 $
b1000011110111000 )
b100 (
#10000
b1111001100000001 !
b1111001100000001 +
b110110100101001 %
b110110100101001 *
b110000000101010 $
b110000000101010 )
b101 (
#12000
b10000010100010 !
b10000010100010 +
1"
1#
0&
b1001110000001001 %
b1001110000001001 *
b1000010010011001 $
b1000010010011001 )
b110 (
#14000
b101001011110110 !
b101001011110110 +
b110011101010111 %
b110011101010111 *
b1110101110011111 $
b1110101110011111 )
b111 (
#16000
b1001011110001010 !
b1001011110001010 +
0"
0#
b1000010011011101 %
b1000010011011101 *
b1001010101101 $
b1001010101101 )
b1000 (
#18000
b1011101111001011 !
b1011101111001011 +
1&
b100100100010101 %
b100100100010101 *
b10011100000 $
b10011100000 )
b1001 (
#20000
b1101000100111110 !
b1101000100111110 +
0"
0#
b1011110111111000 %
b1011110111111000 *
b1000111100110110 $
b1000111100110110 )
b1010 (
#22000
b1101011101101110 !
b1101011101101110 +
b1010110101100010 %
b1010110101100010 *
b1000010011010000 $
b1000010011010000 )
b1011 (
#24000
b1001100000100111 !
b1001100000100111 +
b1110111000110010 %
b1110111000110010 *
b1000011001011001 $
b1000011001011001 )
b1100 (
#26000
b1001011111010100 !
b1001011111010100 +
1"
1#
b110000100010101 %
b110000100010101 *
b1111100011101001 $
b1111100011101001 )
b1101 (
#28000
b111101001011000 !
b111101001011000 +
0&
b1111110001101001 %
b1111110001101001 *
b111110111101111 $
b111110111101111 )
b1110 (
#30000
b111111001010010 !
b111111001010010 +
0"
0#
1&
b1101001011010010 %
b1101001011010010 *
b101000100100100 $
b101000100100100 )
b1111 (
#32000
b10011010000100 !
b10011010000100 +
1"
1#
b1101011000000100 %
b1101011000000100 *
b1111110010001000 $
b1111110010001000 )
b10000 (
#34000
b10110110001000 !
b10110110001000 +
0"
0#
0&
b10010011101101 %
b10010011101101 *
b100010011011 $
b100010011011 )
b10001 (
#36000
b1011101111001111 !
b1011101111001111 +
0"
0#
1&
b1011000011101011 %
b1011000011101011 *
b110110010111010 $
b110110010111010 )
b10010 (
#38000
b1000110101101111 !
b1000110101101111 +
1"
1#
b11011101000110 %
b11011101000110 *
b1100010010110101 $
b1100010010110101 )
b10011 (
#40000
b10111101100 !
b10111101100 +
0&
b1111000000010000 %
b1111000000010000 *
b1010111011100 $
b1010111011100 )
b10100 (
#42000
b1110110101001000 !
b1110110101001000 +
0"
0#
b1010001110111101 %
b1010001110111101 *
b100100110001011 $
b100100110001011 )
b10101 (
#44000
b101111010 !
b101111010 +
1"
1#
b100011001011001 %
b100011001011001 *
b1011101100100001 $
b1011101100100001 )
b10110 (
#46000
b1100111111000001 !
b1100111111000001 +
0"
0#
b11010001011 %
b11010001011 *
b1100100100110110 $
b1100100100110110 )
b10111 (
#48000
b101001110111000 !
b101001110111000 +
1"
1#
1&
b1000111000111110 %
b1000111000111110 *
b1110000111110110 $
b1110000111110110 )
b11000 (
#50000
b1100110100111010 !
b1100110100111010 +
0"
0#
0&
b101100101000011 %
b101100101000011 *
b111001111110111 $
b111001111110111 )
b11001 (
#52000
b1011010101001100 !
b1011010101001100 +
b101001100011101 %
b101001100011101 *
b110001000101111 $
b110001000101111 )
b11010 (
#54000
b10110110111010 !
b10110110111010 +
1"
1#
1&
b101100000111110 %
b101100000111110 *
b1000010111111000 $
b1000010111111000 )
b11011 (
#56000
b1011101100001100 !
b1011101100001100 +
0"
0#
0&
b110010011001111 %
b110010011001111 *
b101011000111101 $
b101011000111101 )
b11100 (
#58000
b100100101010000 !
b100100101010000 +
1"
1#
b111000111001110 %
b111000111001110 *
b1101011110000010 $
b1101011110000010 )
b11101 (
#60000
b101000000111010 !
b101000000111010 +
0"
0#
b1100000001100 %
b1100000001100 *
b11100000101110 $
b11100000101110 )
b11110 (
#62000
b1000001000011101 !
b1000001000011101 +
b10000010001100 %
b10000010001100 *
b110000110010001 $
b110000110010001 )
b11111 (
#64000
b10010010110111 !
b10010010110111 +
1"
1#
b10111111010111 %
b10111111010111 *
b1111010011100000 $
b1111010011100000 )
b100000 (
#66000
b1011101101 !
b1011101101 +
1&
b100100111110111 %
b100100111110111 *
b100110011100100 $
b100110011100100 )
b100001 (
#68000
b100110111000 !
b100110111000 +
0&
b101001010011110 %
b101001010011110 *
b1011011100011010 $
b1011011100011010 )
b100010 (
#70000
b110110111001110 !
b110110111001110 +
1&
b111011001011 %
b111011001011 *
b111110010011001 $
b111110010011001 )
b100011 (
#72000
b110010000101111 !
b110010000101111 +
0&
b1011011100100001 %
b1011011100100001 *
b1010110100001110 $
b1010110100001110 )
b100100 (
#74000
b10101001011010 !
b10101001011010 +
b1110111010100111 %
b1110111010100111 *
b11101110110011 $
b11101110110011 )
b100101 (
#76000
b1111001000010101 !
b1111001000010101 +
0"
0#
1&
b111011000100011 %
b111011000100011 *
b110100000111000 $
b110100000111000 )
b100110 (
#78000
b1111101110111001 !
b1111101110111001 +
0&
b11101111111110 %
b11101111111110 *
b1011111110111011 $
b1011111110111011 )
b100111 (
#80000
b100011010111 !
b100011010111 +
1"
1#
1&
b11011110111100 %
b11011110111100 *
b100000010010011 $
b100000010010011 )
b101000 (
#82000
b10101110001001 !
b10101110001001 +
0&
b11010000011011 %
b11010000011011 *
b1111011101101110 $
b1111011101101110 )
b101001 (
#84000
0"
0#
b101101100101011 !
b101101100101011 +
1&
b1110100101100000 %
b1110100101100000 *
b100010010001011 $
b100010010001011 )
b101010 (
#86000
b1110110011011010 !
b1110110011011010 +
0&
b10010111101110 %
b10010111101110 *
b1100011011101100 $
b1100011011101100 )
b101011 (
#88000
b101101100100111 !
b101101100100111 +
1"
1#
1&
b1001010100110000 %
b1001010100110000 *
b1111000001010111 $
b1111000001010111 )
b101100 (
#90000
b1010100001000011 !
b1010100001000011 +
0&
b1110010111001001 %
b1110010111001001 *
b1100001001111010 $
b1100001001111010 )
b101101 (
#92000
b1111101010001 !
b1111101010001 +
0"
0#
1&
b1111100011000000 %
b1111100011000000 *
b1100000010001 $
b1100000010001 )
b101110 (
#94000
1"
1#
b1000000110101100 !
b1000000110101100 +
b110101100110100 %
b110101100110100 *
b1110110011100000 $
b1110110011100000 )
b101111 (
#96000
b1101010111001011 !
b1101010111001011 +
0"
0#
0&
b101010110110 %
b101010110110 *
b1100101100010101 $
b1100101100010101 )
b110000 (
#98000
b1101101100100000 !
b1101101100100000 +
0"
0#
1&
b1010100110101011 %
b1010100110101011 *
b1000010011001011 $
b1000010011001011 )
b110001 (
#100000
b101010000010000 !
b101010000010000 +
1"
1#
0&
b1010001001111011 %
b1010001001111011 *
b1011000110010101 $
b1011000110010101 )
b110010 (
#102000
b1101101110111000 !
b1101101110111000 +
b1111101011000110 %
b1111101011000110 *
b1110000011110010 $
b1110000011110010 )
b110011 (
#104000
b1000000011101101 !
b1000000011101101 +
1"
1#
1&
b100110101101001 %
b100110101101001 *
b1100111001010110 $
b1100111001010110 )
b110100 (
#106000
b101010110001010 !
b101010110001010 +
0&
b1110100011010100 %
b1110100011010100 *
b110110010110110 $
b110110010110110 )
b110101 (
#108000
b1010101101111001 !
b1010101101111001 +
0"
0#
b101010001 %
b101010001 *
b1010101000101000 $
b1010101000101000 )
b110110 (
#110000
b1000101111110011 !
b1000101111110011 +
1"
1#
b1101101110100111 %
b1101101110100111 *
b1011000001001100 $
b1011000001001100 )
b110111 (
#112000
b10001011000101 !
b10001011000101 +
b100001000011000 %
b100001000011000 *
b1110000010101101 $
b1110000010101101 )
b111000 (
#114000
b110000011000101 !
b110000011000101 +
0"
0#
b101010001101110 %
b101010001101110 *
b110001010111 $
b110001010111 )
b111001 (
#116000
b110101000101010 !
b110101000101010 +
b11001111100101 %
b11001111100101 *
b11011001000101 $
b11011001000101 )
b111010 (
#118000
b1001000000000100 !
b1001000000000100 +
0"
0#
1&
b1010011011100111 %
b1010011011100111 *
b11011011101011 $
b11011011101011 )
b111011 (
#120000
b1010101000010111 !
b1010101000010111 +
1"
1#
0&
b1100011000111101 %
b1100011000111101 *
b1110001111011010 $
b1110001111011010 )
b111100 (
#122000
b1011101001100101 !
b1011101001100101 +
0"
0#
b100101111110010 %
b100101111110010 *
b110111001110011 $
b110111001110011 )
b111101 (
#124000
b1101000100001000 !
b1101000100001000 +
0"
0#
1&
b1100011101110100 %
b1100011101110100 *
b1001100001111100 $
b1001100001111100 )
b111110 (
#126000
b1100111011001110 !
b1100111011001110 +
1"
1#
0&
b1111011000010100 %
b1111011000010100 *
b1101100010111010 $
b1101100010111010 )
b111111 (
#128000
b10010101101110 !
b10010101101110 +
1"
1#
1&
b1001010111101001 %
b1001010111101001 *
b1011101101010111 $
b1011101101010111 )
b1000000 (
#130000
b11010110000100 !
b11010110000100 +
1"
1#
b1101000010010 %
b1101000010010 *
b100111110010110 $
b100111110010110 )
b1000001 (
#132000
b101101000110010 !
b101101000110010 +
0"
0#
0&
b10011011111 %
b10011011111 *
b101010101010011 $
b101010101010011 )
b1000010 (
#134000
b1011010101101111 !
b1011010101101111 +
b100110100001010 %
b100110100001010 *
b110100001100101 $
b110100001100101 )
b1000011 (
#136000
b1000001010010001 !
b1000001010010001 +
1"
1#
1&
b100010111001 %
b100010111001 *
b1000101101001010 $
b1000101101001010 )
b1000100 (
#138000
b100001010001001 !
b100001010001001 +
b111101100000010 %
b111101100000010 *
b1011110110001011 $
b1011110110001011 )
b1000101 (
#140000
b1011000100101000 !
b1011000100101000 +
0"
0#
0&
b1000100100001000 %
b1000100100001000 *
b10100000100000 $
b10100000100000 )
b1000110 (
#142000
b110001010011 !
b110001010011 +
1"
1#
b100000001110110 %
b100000001110110 *
b1100101111011101 $
b1100101111011101 )
b1000111 (
#144000
b110010000010110 !
b110010000010110 +
b1010111100011101 %
b1010111100011101 *
b1011010011111001 $
b1011010011111001 )
b1001000 (
#146000
b1101111100010100 !
b1101111100010100 +
0"
0#
b111001001101001 %
b111001001101001 *
b110110010101011 $
b110110010101011 )
b1001001 (
#148000
b1111100100101110 !
b1111100100101110 +
b110011001100100 %
b110011001100100 *
b1001001011001010 $
b1001001011001010 )
b1001010 (
#150000
b110000100000100 !
b110000100000100 +
1"
1#
1&
b100010001001101 %
b100010001001101 *
b1010010101010001 $
b1010010101010001 )
b1001011 (
#152000
b1000011101010111 !
b1000011101010111 +
0"
0#
0&
b101100000110010 %
b101100000110010 *
b10111100100101 $
b10111100100101 )
b1001100 (
#154000
b101000000000 !
b101000000000 +
1"
1#
b101111100100101 %
b101111100100101 *
b1010101011011011 $
b1010101011011011 )
b1001101 (
#156000
b100000110110011 !
b100000110110011 +
b1010111110000010 %
b1010111110000010 *
b1001001000110001 $
b1001001000110001 )
b1001110 (
#158000
b101110100100100 !
b101110100100100 +
b110001011101001 %
b110001011101001 *
b1111101000111011 $
b1111101000111011 )
b1001111 (
#160000
b10011011010110 !
b10011011010110 +
1"
1#
1&
b100011010000 %
b100011010000 *
b10111110100110 $
b10111110100110 )
b1010000 (
#162000
0"
0#
b1111000111001001 !
b1111000111001001 +
b101000111111101 %
b101000111111101 *
b100001111000110 $
b100001111000110 )
b1010001 (
#164000
b11100011011100 !
b11100011011100 +
1"
1#
0&
b101110110101111 %
b101110110101111 *
b1101101100101101 $
b1101101100101101 )
b1010010 (
#166000
b101010000110101 !
b101010000110101 +
b101011000111001 %
b101011000111001 *
b1111110111111100 $
b1111110111111100 )
b1010011 (
#168000
b111010110101011 !
b111010110101011 +
1&
b11101011010001 %
b11101011010001 *
b1011000001111100 $
b1011000001111100 )
b1010100 (
#170000
b1110010001010110 !
b1110010001010110 +
0"
0#
0&
b101111100000001 %
b101111100000001 *
b1000010101010101 $
b1000010101010101 )
b1010101 (
#172000
b111110001101000 !
b111110001101000 +
1"
1#
1&
b11000111100001 %
b11000111100001 *
b1010111001001001 $
b1010111001001001 )
b1010110 (
#174000
b111000010011 !
b111000010011 +
0&
b111110011101001 %
b111110011101001 *
b1001000100101010 $
b1001000100101010 )
b1010111 (
#176000
0"
0#
b1101111000111110 !
b1101111000111110 +
1&
b1011001101101111 %
b1011001101101111 *
b1001000110101101 $
b1001000110101101 )
b1011000 (
#178000
b111111011001000 !
b111111011001000 +
1"
1#
b110010111000110 %
b110010111000110 *
b1110010010001110 $
b1110010010001110 )
b1011001 (
#180000
b1010010001000100 !
b1010010001000100 +
b10001111010001 %
b10001111010001 *
b1100100000010101 $
b1100100000010101 )
b1011010 (
#182000
0"
0#
b1111101111011011 !
b1111101111011011 +
b111100110101100 %
b111100110101100 *
b111010110000111 $
b111010110000111 )
b1011011 (
#184000
b1010000101001001 !
b1010000101001001 +
b1011000110111000 %
b1011000110111000 *
b101001100000001 $
b101001100000001 )
b1011100 (
#186000
b100101111010110 !
b100101111010110 +
1"
1#
0&
b1110101101000101 %
b1110101101000101 *
b110000010010001 $
b110000010010001 )
b1011101 (
#188000
b1011111000000001 !
b1011111000000001 +
0"
0#
b110111111000000 %
b110111111000000 *
b100111001000001 $
b100111001000001 )
b1011110 (
#190000
b101010111111011 !
b101010111111011 +
b100011110100010 %
b100011110100010 *
b111001011001 $
b111001011001 )
b1011111 (
#192000
b1011010101111110 !
b1011010101111110 +
b10101010111 %
b10101010111 *
b1011000000100111 $
b1011000000100111 )
b1100000 (
#194000
b1100000110101 !
b1100000110101 +
1"
1#
b111010010100000 %
b111010010100000 *
b1010001110010101 $
b1010001110010101 )
b1100001 (
#196000
b101101101010 !
b101101101010 +
b1001010010101100 %
b1001010010101100 *
b111011010111110 $
b111011010111110 )
b1100010 (
#198000
b10110101100001 !
b10110101100001 +
1"
1#
1&
b111000010000 %
b111000010000 *
b11101101110001 $
b11101101110001 )
b1100011 (
#200000
0"
0#
b111000101111110 !
b111000101111110 +
b1110111110100010 %
b1110111110100010 *
b110000100100000 $
b110000100100000 )
b1100100 (
#202000
1"
1#
b1000000100101010 !
b1000000100101010 +
b1110110110101 %
b1110110110101 *
b1001111011011111 $
b1001111011011111 )
b1100101 (
#204000
b101010111010101 !
b101010111010101 +
0"
0#
0&
b100111010000110 %
b100111010000110 *
b11101001111 $
b11101001111 )
b1100110 (
#206000
b111011101011010 !
b111011101011010 +
1&
b1001111011000000 %
b1001111011000000 *
b1011000011010 $
b1011000011010 )
b1100111 (
#208000
b111101101101100 !
b111101101101100 +
b1001000000011110 %
b1001000000011110 *
b101110001010 $
b101110001010 )
b1101000 (
#210000
b100111100000100 !
b100111100000100 +
1"
1#
0&
b1011010011101011 %
b1011010011101011 *
b1001101000011001 $
b1001101000011001 )
b1101001 (
#212000
0"
0#
b1101100001011110 !
b1101100001011110 +
1&
b1110001100001101 %
b1110001100001101 *
b1011101101101011 $
b1011101101101011 )
b1101010 (
#214000
b101001001100000 !
b101001001100000 +
b1110100001010000 %
b1110100001010000 *
b11101010110000 $
b11101010110000 )
b1101011 (
#216000
b101100100000100 !
b101100100000100 +
0&
b1010000010000 %
b1010000010000 *
b100010011110100 $
b100010011110100 )
b1101100 (
#218000
b1011101100001101 !
b1011101100001101 +
0"
0#
1&
b1001001010001111 %
b1001001010001111 *
b100110110011100 $
b100110110011100 )
b1101101 (
#220000
b1110100110110010 !
b1110100110110010 +
b100101100111001 %
b100101100111001 *
b11010011101011 $
b11010011101011 )
b1101110 (
#222000
b101011110111010 !
b101011110111010 +
1"
1#
b1110011100000 %
b1110011100000 *
b111010010011010 $
b111010010011010 )
b1101111 (
#224000
b111010111101110 !
b111010111101110 +
0&
b1110010010001100 %
b1110010010001100 *
b1001000101100010 $
b1001000101100010 )
b1110000 (
#226000
b110011100101111 !
b110011100101111 +
0"
0#
1&
b1010100011101001 %
b1010100011101001 *
b1000000011000 $
b1000000011000 )
b1110001 (
#228000
b1110010110110000 !
b1110010110110000 +
0&
b111001100011010 %
b111001100011010 *
b111001010010110 $
b111001010010110 )
b1110010 (
#230000
b110000100111100 !
b110000100111100 +
b1111101011110 %
b1111101011110 *
b100000111011110 $
b100000111011110 )
b1110011 (
#232000
b1000110110000011 !
b1000110110000011 +
1"
1#
1&
b11111101010 %
b11111101010 *
b1001010101101101 $
b1001010101101101 )
b1110100 (
#234000
0"
0#
b111101111100100 !
b111101111100100 +
b1010010011111011 %
b1010010011111011 *
b10000011011111 $
b10000011011111 )
b1110101 (
#236000
b110111101001111 !
b110111101001111 +
1"
1#
0&
b1001110001000111 %
b1001110001000111 *
b1101001100001000 $
b1101001100001000 )
b1110110 (
#238000
b1110001001110011 !
b1110001001110011 +
0"
0#
b1011101101011001 %
b1011101101011001 *
b10011100011010 $
b10011100011010 )
b1110111 (
#240000
b1000000101110 !
b1000000101110 +
b101011000001 %
b101011000001 *
b10101101101 $
b10101101101 )
b1111000 (
#242000
b1101101100000101 !
b1101101100000101 +
0"
0#
1&
b1100000000011000 %
b1100000000011000 *
b1001101100011101 $
b1001101100011101 )
b1111001 (
#244000
b1101000110100111 !
b1101000110100111 +
0&
b11010100000110 %
b11010100000110 *
b1001110010100001 $
b1001110010100001 )
b1111010 (
#246000
b1001101111110101 !
b1001101111110101 +
0"
0#
1&
b1011110001111010 %
b1011110001111010 *
b101100001101111 $
b101100001101111 )
b1111011 (
#248000
b101000001010001 !
b101000001010001 +
1"
1#
b1010101101011101 %
b1010101101011101 *
b1111101110101110 $
b1111101110101110 )
b1111100 (
#250000
b1000111110101001 !
b1000111110101001 +
0&
b1010010011000110 %
b1010010011000110 *
b1110101011100011 $
b1110101011100011 )
b1111101 (
#252000
b110001010101100 !
b110001010101100 +
1"
1#
1&
b10000011100 %
b10000011100 *
b110011011001000 $
b110011011001000 )
b1111110 (
#254000
0"
0#
b1111101100100010 !
b1111101100100010 +
b1011000010110100 %
b1011000010110100 *
b1010101111010110 $
b1010101111010110 )
b1111111 (
#256000
b1010011111011110 !
b1010011111011110 +
0&
b1100101100110 %
b1100101100110 *
b1000111001111000 $
b1000111001111000 )
b10000000 (
#258000
b111011001001110 !
b111011001001110 +
1"
1#
b1001100011001000 %
b1001100011001000 *
b1101110110000110 $
b1101110110000110 )
b10000001 (
#260000
b10100010000010 !
b10100010000010 +
1&
b1011111011000101 %
b1011111011000101 *
b1110011101000111 $
b1110011101000111 )
b10000010 (
#262000
b1110011010001111 !
b1110011010001111 +
b100100001001 %
b100100001001 *
b1110111110011000 $
b1110111110011000 )
b10000011 (
#264000
0"
0#
b1100010111101000 !
b1100010111101000 +
b1011011001111101 %
b1011011001111101 *
b111110001100101 $
b111110001100101 )
b10000100 (
#266000
b1110000101001011 !
b1110000101001011 +
1"
1#
b110101001011 %
b110101001011 *
b1110111010010110 $
b1110111010010110 )
b10000101 (
#268000
b101110111101001 !
b101110111101001 +
0"
0#
b1010011111001001 %
b1010011111001001 *
b10110110010 $
b10110110010 )
b10000110 (
#270000
b1100111010001011 !
b1100111010001011 +
0&
b100011010011011 %
b100011010011011 *
b1000011111110000 $
b1000011111110000 )
b10000111 (
#272000
b1100011001111001 !
b1100011001111001 +
0"
0#
1&
b1100001000110110 %
b1100001000110110 *
b1000100010101111 $
b1000100010101111 )
b10001000 (
#274000
b100101111110011 !
b100101111110011 +
1"
1#
0&
b1000101011010110 %
b1000101011010110 *
b1100000100011101 $
b1100000100011101 )
b10001001 (
#276000
b1001001110110100 !
b1001001110110100 +
1&
b10111011101100 %
b10111011101100 *
b1100001010100000 $
b1100001010100000 )
b10001010 (
#278000
b1010001111101001 !
b1010001111101001 +
0&
b1101011001000110 %
b1101011001000110 *
b1100110110100011 $
b1100110110100011 )
b10001011 (
#280000
b1111000101010011 !
b1111000101010011 +
0"
0#
1&
b1110101100110 %
b1110101100110 *
b111010111001 $
b111010111001 )
b10001100 (
#282000
b111000110110000 !
b111000110110000 +
1"
1#
0&
b111101000100101 %
b111101000100101 *
b1111011110001011 $
b1111011110001011 )
b10001101 (
#284000
b100111100010110 !
b100111100010110 +
0"
0#
1&
b1111001100100111 %
b1111001100100111 *
b100001000111101 $
b100001000111101 )
b10001110 (
#286000
b1010001000001101 !
b1010001000001101 +
0&
b111110010 %
b111110010 *
b1010000000011011 $
b1010000000011011 )
b10001111 (
#288000
b1110010010010101 !
b1110010010010101 +
0"
0#
1&
b10001100001110 %
b10001100001110 *
b11110100011 $
b11110100011 )
b10010000 (
#290000
b100111010010011 !
b100111010010011 +
1"
1#
b110011001000001 %
b110011001000001 *
b1011010011010100 $
b1011010011010100 )
b10010001 (
#292000
b1101001010 !
b1101001010 +
0&
b10000101010000 %
b10000101010000 *
b1110000111111010 $
b1110000111111010 )
b10010010 (
#294000
b1100100000001000 !
b1100100000001000 +
0"
0#
b10101011111000 %
b10101011111000 *
b1001110100010000 $
b1001110100010000 )
b10010011 (
#296000
b1110000011101111 !
b1110000011101111 +
b101100111100 %
b101100111100 *
b1101010110110011 $
b1101010110110011 )
b10010100 (
#298000
b111001010011010 !
b111001010011010 +
1"
1#
b1011110110011000 %
b1011110110011000 *
b1011010100000010 $
b1011010100000010 )
b10010101 (
#300000
0"
0#
b1101110111011001 !
b1101110111011001 +
1&
b1110011001010010 %
b1110011001010010 *
b1100010000101011 $
b1100010000101011 )
b10010110 (
#302000
b1111000100011110 !
b1111000100011110 +
0&
b1010111111101 %
b1010111111101 *
b1101101100100001 $
b1101101100100001 )
b10010111 (
#304000
b1101001001110000 !
b1101001001110000 +
0"
0#
1&
b111110110110000 %
b111110110110000 *
b101000000100000 $
b101000000100000 )
b10011000 (
#306000
1"
1#
b100010101110100 !
b100010101110100 +
b1101101011000 %
b1101101011000 *
b110000011001100 $
b110000011001100 )
b10011001 (
#308000
0"
0#
b110000100011001 !
b110000100011001 +
b1101001001110111 %
b1101001001110111 *
b11001110010000 $
b11001110010000 )
b10011010 (
#310000
b111010011011100 !
b111010011011100 +
0&
b10100100001110 %
b10100100001110 *
b100101111001110 $
b100101111001110 )
b10011011 (
#312000
b1000101110010001 !
b1000101110010001 +
0"
0#
1&
b1100000000011110 %
b1100000000011110 *
b100101110101111 $
b100101110101111 )
b10011100 (
#314000
b1100001111000101 !
b1100001111000101 +
b1101011010010011 %
b1101011010010011 *
b1001101001011000 $
b1001101001011000 )
b10011101 (
#316000
b1101000101100110 !
b1101000101100110 +
1"
1#
0&
b1101100111000010 %
b1101100111000010 *
b1111011110100100 $
b1111011110100100 )
b10011110 (
#318000
b10100010 !
b10100010 +
1&
b1101100110000101 %
b1101100110000101 *
b1101101000100111 $
b1101101000100111 )
b10011111 (
#320000
b100010000010 !
b100010000010 +
1"
1#
b110111101011100 %
b110111101011100 *
b111011111011110 $
b111011111011110 )
b10100000 (
#322000
b100011001100101 !
b100011001100101 +
b1001100010000111 %
b1001100010000111 *
b1101111011101100 $
b1101111011101100 )
b10100001 (
#324000
b1010110001001110 !
b1010110001001110 +
0&
b1110001010001110 %
b1110001010001110 *
b1100100111000000 $
b1100100111000000 )
b10100010 (
#326000
b1101000011101 !
b1101000011101 +
b10010111011001 %
b10010111011001 *
b1111010001000100 $
b1111010001000100 )
b10100011 (
#328000
b111001101010101 !
b111001101010101 +
b1010010111010011 %
b1010010111010011 *
b1100110110000010 $
b1100110110000010 )
b10100100 (
#330000
b100010100011011 !
b100010100011011 +
1&
b1000101001010111 %
b1000101001010111 *
b1100111101110010 $
b1100111101110010 )
b10100101 (
#332000
b1110100010101001 !
b1110100010101001 +
0"
0#
0&
b110110001110101 %
b110110001110101 *
b111110000110100 $
b111110000110100 )
b10100110 (
#334000
b1110111000101001 !
b1110111000101001 +
1&
b110100000001001 %
b110100000001001 *
b101011000110010 $
b101011000110010 )
b10100111 (
#336000
b111101101100011 !
b111101101100011 +
1"
1#
b1010100101101 %
b1010100101101 *
b1001000010010000 $
b1001000010010000 )
b10101000 (
#338000
0"
0#
b1010001101110011 !
b1010001101110011 +
b1001101101100001 %
b1001101101100001 *
b11111011010100 $
b11111011010100 )
b10101001 (
#340000
b1110010110000101 !
b1110010110000101 +
b11111001010000 %
b11111001010000 *
b10001111010101 $
b10001111010101 )
b10101010 (
#342000
b110110010110110 !
b110110010110110 +
1"
1#
b11001010010011 %
b11001010010011 *
b1001111101001001 $
b1001111101001001 )
b10101011 (
#344000
b10000011011001 !
b10000011011001 +
b1010110000110 %
b1010110000110 *
b11011001011111 $
b11011001011111 )
b10101100 (
#346000
b11010010011100 !
b11010010011100 +
b11000101110111 %
b11000101110111 *
b110011000010011 $
b110011000010011 )
b10101101 (
#348000
b101011011111 !
b101011011111 +
b11010010000110 %
b11010010000110 *
b11111101100101 $
b11111101100101 )
b10101110 (
#350000
b111011010010111 !
b111011010010111 +
0"
0#
0&
b11100010010101 %
b11100010010101 *
b11111000000010 $
b11111000000010 )
b10101111 (
#352000
b1011001010011111 !
b1011001010011111 +
b1001011110111000 %
b1001011110111000 *
b1101011100111 $
b1101011100111 )
b10110000 (
#354000
b1100101110001001 !
b1100101110001001 +
1&
b101010111010110 %
b101010111010110 *
b10000101011111 $
b10000101011111 )
b10110001 (
#356000
b11111010011111 !
b11111010011111 +
1"
1#
0&
b110001110001101 %
b110001110001101 *
b1101101100010010 $
b1101101100010010 )
b10110010 (
#358000
b100110110100110 !
b100110110100110 +
1&
b1010001011110100 %
b1010001011110100 *
b1111000010011010 $
b1111000010011010 )
b10110011 (
#360000
b1100001011110011 !
b1100001011110011 +
b1001101101110 %
b1001101101110 *
b1101011001100001 $
b1101011001100001 )
b10110100 (
#362000
b101010101011110 !
b101010101011110 +
b100100111011111 %
b100100111011111 *
b1001111100111101 $
b1001111100111101 )
b10110101 (
#364000
b1001011001010 !
b1001011001010 +
b1011100011110001 %
b1011100011110001 *
b1100101110111011 $
b1100101110111011 )
b10110110 (
#366000
b1011011110100000 !
b1011011110100000 +
0"
0#
0&
b1001000100011111 %
b1001000100011111 *
b10011010000001 $
b10011010000001 )
b10110111 (
