HW1/Behavior/test/16bit_adder.v
// implement 16 bit adder by behavior
module Sub_adder_16bit(sum, overdetect, cout, a, b, mode);

input [15:0] a, b;
input mode; // mode = 1: subtractor, mode = 0: adder
output [15:0] sum;
output cout, overdetect; // overflow detect 

//reg [16:0] result;

assign {cout, sum} = (mode) ? (a+{~b+1'b1}) : (a+b);
// assign overdetect = 
//    /*Positive Number OverFlow*/(((Add_ctrl==1)&&(A[15]==1)&&(B[15]==0)&&(SUM[15]==0)) || ((Add_ctrl==1)&&(A[15]==0)&&(B[15]==1)&&(SUM[15]==1)) 
// || /*Negative Number OverFlow*/ ((Add_ctrl==0)&&(A[15]==0)&&(B[15]==0)&&(SUM[15]==1)) || ((Add_ctrl==0)&&(A[15]==1)&&(B[15]==1)&&(SUM[15]==0)) )? 1:0;





endmodule

HW1/Behavior/test/testbench.v
`include "./16bit_adder.v"
`timescale 1ns/10ps
`define delay 20 
module testbench();

reg [15:0] A, B;
reg Mode;
wire [15:0] SUM;
wire Cout;

reg [15:0] mem_A [9999:0];
reg [15:0] mem_B [9999:0];
reg mem_ctrl [9999:0];
reg [16:0] expect [9999:0];

reg [16:0] error = 0;

// read the testing data
initial begin
	$readmemh("A.txt", mem_A);
	$readmemh("B.txt", mem_B);
	$readmemh("ctrl.txt", mem_ctrl);
	$readmemh("result.txt", expect);
end


Sub_adder_16bit S1(
    .a(A),
    .b(B),
    .mode(Mode),
    .cout(Cout),
    .sum(SUM)
);

integer i;
initial begin
    for (i =0 ; i <= 9999; i = i + 1 ) begin
        A = mem_A[i] ;
        B = mem_B[i] ;
        Mode = mem_ctrl[i] ;

        #(`delay);
        if (SUM !== expect[i][15:0]) begin
            $display ("ERROR at time=%d(pattern%d): SUM(%h)!= expect(%h)", $time, i+1, SUM, expect[i][15:0]);
            error = error + 1;
        end
		
        if (Cout !== expect[i][16]) begin
            $display ("ERROR at time=%d(pattern%d): C_out(%b)!= expect(%b)", $time,  i+1, Cout, expect[i][16]);
            error = error + 1;
        end

    end

    if(error == 17'b0) begin
        $display("        ***********************************************        ");
        $display("        **                                           **        ");
        $display("        **             Congratulations !!            **        ");
        $display("        **               Test PASS  !!               **        ");
        $display("        **                                           **        ");
        $display("        ***********************************************        ");
    end
    else begin
        $display ("=================================================");
        $display ("There're %d errors in your design", error); 
        $display ("=================================================");
    end

	$finish ;

end

initial begin
    $dumpfile("16bitsub_adder.vcd");
    $dumpvars;
end

endmodule

HW1/Behavior/test/16bitsub_adder.vcd
$date
	Sun Oct 18 23:20:22 2020
$end
$version
	Icarus Verilog
$end
$timescale
	10ps
$end
$scope module testbench $end
$var wire 16 ! SUM [15:0] $end
$var wire 1 " Cout $end
$var reg 16 # A [15:0] $end
$var reg 16 $ B [15:0] $end
$var reg 1 % Mode $end
$var reg 17 & error [16:0] $end
$var integer 32 ' i [31:0] $end
$scope module S1 $end
$var wire 16 ( a [15:0] $end
$var wire 16 ) b [15:0] $end
$var wire 1 % mode $end
$var wire 1 * overdetect $end
$var wire 16 + sum [15:0] $end
$var wire 1 " cout $end
$upscope $end
$upscope $end
$enddefinitions $end
#0
$dumpvars
b1101100111001100 +
z*
b1010001110111010 )
b11011000010010 (
b0 '
b0 &
0%
b1010001110111010 $
b11011000010010 #
0"
b1101100111001100 !
$end
#2000
b100010010000010 !
b100010010000010 +
1"
b1101101110010111 $
b1101101110010111 )
b110100011101011 #
b110100011101011 (
b1 '
#4000
b101011001011101 !
b101011001011101 +
b1101010010001101 $
b1101010010001101 )
b1000000111010000 #
b1000000111010000 (
b10 '
#6000
b1111011000000 !
b1111011000000 +
1"
1%
b1000100110011100 $
b1000100110011100 )
b1010100001011100 #
b1010100001011100 (
b11 '
#8000
b110000110010100 !
b110000110010100 +
0"
0%
b10011100000101 $
b10011100000101 )
b11101010001111 #
b11101010001111 (
b100 '
#10000
b11101110111011 !
b11101110111011 +
1"
b1000001101110010 $
b1000001101110010 )
b1011100001001001 #
b1011100001001001 (
b101 '
#12000
b11110011011111 !
b11110011011111 +
b1111110100111010 $
b1111110100111010 )
b11111110100101 #
b11111110100101 (
b110 '
#14000
b1000100001000000 !
b1000100001000000 +
b1000110010111010 $
b1000110010111010 )
b1111101110000110 #
b1111101110000110 (
b111 '
#16000
b11100011000 !
b11100011000 +
1%
b1000111110000011 $
b1000111110000011 )
b1001011010011011 #
b1001011010011011 (
b1000 '
#18000
b1011111010000011 !
b1011111010000011 +
b11100101110 $
b11100101110 )
b1100010110110001 #
b1100010110110001 (
b1001 '
#20000
b1110010011011100 !
b1110010011011100 +
0"
0%
b10000111000 $
b10000111000 )
b1110000010100100 #
b1110000010100100 (
b1010 '
#22000
b1100000010110111 !
b1100000010110111 +
b100110101101110 $
b100110101101110 )
b111001101001001 #
b111001101001001 (
b1011 '
#24000
b101001010111110 !
b101001010111110 +
1"
b101110110110011 $
b101110110110011 )
b1111010100001011 #
b1111010100001011 (
b1100 '
#26000
b1111100000001100 !
b1111100000001100 +
b1111110000010011 $
b1111110000010011 )
b1111101111111001 #
b1111101111111001 (
b1101 '
#28000
b1101110010100010 !
b1101110010100010 +
0"
b111100000011100 $
b111100000011100 )
b110010010000110 #
b110010010000110 (
b1110 '
#30000
b1110110100101111 !
b1110110100101111 +
0"
1%
b1111010000010011 $
b1111010000010011 )
b1110000101000010 #
b1110000101000010 (
b1111 '
#32000
b110100011101101 !
b110100011101101 +
0%
b1011001011110 $
b1011001011110 )
b101001010001111 #
b101001010001111 (
b10000 '
#34000
b1110001101100101 !
b1110001101100101 +
b100110111111 $
b100110111111 )
b1101100110100110 #
b1101100110100110 (
b10001 '
#36000
b110111001011101 !
b110111001011101 +
1"
b110111101000010 $
b110111101000010 )
b1111111100011011 #
b1111111100011011 (
b10010 '
#38000
b1000101001101001 !
b1000101001101001 +
0"
b1000000110001001 $
b1000000110001001 )
b100011100000 #
b100011100000 (
b10011 '
#40000
b10110100001011 !
b10110100001011 +
1"
b110001001101000 $
b110001001101000 )
b1100101010100011 #
b1100101010100011 (
b10100 '
#42000
b1111011101 !
b1111011101 +
b11101100100000 $
b11101100100000 )
b1100100010111101 #
b1100100010111101 (
b10101 '
#44000
b101100101111110 !
b101100101111110 +
0"
1%
b1010111101000100 $
b1010111101000100 )
b100011000010 #
b100011000010 (
b10110 '
#46000
b1100111101010100 !
b1100111101010100 +
0%
b10111111110101 $
b10111111110101 )
b1001111101011111 #
b1001111101011111 (
b10111 '
#48000
b1011110010000011 !
b1011110010000011 +
0"
1%
b1111101001011100 $
b1111101001011100 )
b1011011011011111 #
b1011011011011111 (
b11000 '
#50000
b1111010111010111 !
b1111010111010111 +
0%
b1011111010011001 $
b1011111010011001 )
b11011100111110 #
b11011100111110 (
b11001 '
#52000
b1011011010001001 !
b1011011010001001 +
b110110011101100 $
b110110011101100 )
b100100110011101 #
b100100110011101 (
b11010 '
#54000
b1011110111010011 !
b1011110111010011 +
b1011110011111000 $
b1011110011111000 )
b11011011 #
b11011011 (
b11011 '
#56000
b1110000110101110 !
b1110000110101110 +
1%
b101110001111001 $
b101110001111001 )
b11111000100111 #
b11111000100111 (
b11100 '
#58000
b1000010101001 !
b1000010101001 +
1"
b111100011101000 $
b111100011101000 )
b1000100110010001 #
b1000100110010001 (
b11101 '
#60000
b1111010111110011 !
b1111010111110011 +
0"
0%
b1001011000101 $
b1001011000101 )
b1110001100101110 #
b1110001100101110 (
b11110 '
#62000
b111010000000110 !
b111010000000110 +
1"
1%
b110011 $
b110011 )
b111010000111001 #
b111010000111001 (
b11111 '
#64000
b1001110111111101 !
b1001110111111101 +
b101010001111111 $
b101010001111111 )
b1111001001111100 #
b1111001001111100 (
b100000 '
#66000
0"
b111110110101011 !
b111110110101011 +
b1110011101010011 $
b1110011101010011 )
b110010011111110 #
b110010011111110 (
b100001 '
#68000
b1001001011000111 !
b1001001011000111 +
b1000100111001111 $
b1000100111001111 )
b1110010010110 #
b1110010010110 (
b100010 '
#70000
b1011000110000111 !
b1011000110000111 +
b111101110000101 $
b111101110000101 )
b10110100001100 #
b10110100001100 (
b100011 '
#72000
b1011001010000011 !
b1011001010000011 +
b110101011000101 $
b110101011000101 )
b1110101001000 #
b1110101001000 (
b100100 '
#74000
b1101010100110010 !
b1101010100110010 +
b1000011100001001 $
b1000011100001001 )
b101110000111011 #
b101110000111011 (
b100101 '
#76000
1"
b10000001010011 !
b10000001010011 +
b100000111111 $
b100000111111 )
b10100010010010 #
b10100010010010 (
b100110 '
#78000
b1010111000101011 !
b1010111000101011 +
0%
b1111101001001000 $
b1111101001001000 )
b1011001111100011 #
b1011001111100011 (
b100111 '
#80000
b1001001110110101 !
b1001001110110101 +
0"
1%
b1000111000111000 $
b1000111000111000 )
b10000111101101 #
b10000111101101 (
b101000 '
#82000
b1010110101110 !
b1010110101110 +
0%
b110001111000 $
b110001111000 )
b100100110110 #
b100100110110 (
b101001 '
#84000
b110111011100011 !
b110111011100011 +
b100011110110111 $
b100011110110111 )
b10011100101100 #
b10011100101100 (
b101010 '
#86000
b10101100001101 !
b10101100001101 +
1%
b1110101111101011 $
b1110101111101011 )
b1011011111000 #
b1011011111000 (
b101011 '
#88000
b110110111010 !
b110110111010 +
0%
b100010001011 $
b100010001011 )
b10100101111 #
b10100101111 (
b101100 '
#90000
b100101110000101 !
b100101110000101 +
1"
b1011111111010011 $
b1011111111010011 )
b1000101110110010 #
b1000101110110010 (
b101101 '
#92000
b1101100000111000 !
b1101100000111000 +
b1101111111111110 $
b1101111111111110 )
b1111100000111010 #
b1111100000111010 (
b101110 '
#94000
b111011010101000 !
b111011010101000 +
0"
b1111011101010 $
b1111011101010 )
b101011110111110 #
b101011110111110 (
b101111 '
#96000
b10111011101010 !
b10111011101010 +
1"
b1100100110010010 $
b1100100110010010 )
b110010101011000 #
b110010101011000 (
b110000 '
#98000
b100011010010101 !
b100011010010101 +
b100111101000000 $
b100111101000000 )
b1111011101010101 #
b1111011101010101 (
b110001 '
#100000
b100010001 !
b100010001 +
b1010000001110011 $
b1010000001110011 )
b110000010011110 #
b110000010011110 (
b110010 '
#102000
b101101111110110 !
b101101111110110 +
0"
b10101111111010 $
b10101111111010 )
b10111111111100 #
b10111111111100 (
b110011 '
#104000
b100101001110011 !
b100101001110011 +
1"
b1000101001100001 $
b1000101001100001 )
b1100000000010010 #
b1100000000010010 (
b110100 '
#106000
b1011100100011000 !
b1011100100011000 +
0"
b100111110110111 $
b100111110110111 )
b110100101100001 #
b110100101100001 (
b110101 '
#108000
b111001101101100 !
b111001101101100 +
1"
1%
b101101111101111 $
b101101111101111 )
b1100111101011011 #
b1100111101011011 (
b110110 '
#110000
b1111101110101110 !
b1111101110101110 +
0"
0%
b1000010010111101 $
b1000010010111101 )
b111011011110001 #
b111011011110001 (
b110111 '
#112000
b1010111011110000 !
b1010111011110000 +
b111001010001 $
b111001010001 )
b1010000010011111 #
b1010000010011111 (
b111000 '
#114000
b101000000011100 !
b101000000011100 +
0"
1%
b1100100011011100 $
b1100100011011100 )
b1100011111000 #
b1100011111000 (
b111001 '
#116000
b1011100110000001 !
b1011100110000001 +
0%
b100000110110101 $
b100000110110101 )
b111011111001100 #
b111011111001100 (
b111010 '
#118000
b111001111111101 !
b111001111111101 +
1"
1%
b110101011001010 $
b110101011001010 )
b1101111011000111 #
b1101111011000111 (
b111011 '
#120000
b1110010001001101 !
b1110010001001101 +
0"
0%
b100000111000100 $
b100000111000100 )
b1010001010001001 #
b1010001010001001 (
b111100 '
#122000
b11010000000 !
b11010000000 +
1"
1%
b101010001111011 $
b101010001111011 )
b101101011111011 #
b101101011111011 (
b111101 '
#124000
b1110100000000011 !
b1110100000000011 +
0"
b110101011111101 $
b110101011111101 )
b101001100000000 #
b101001100000000 (
b111110 '
#126000
b1111111011000010 !
b1111111011000010 +
0"
b1001011001000100 $
b1001011001000100 )
b1001010100000110 #
b1001010100000110 (
b111111 '
#128000
b1111101111000111 !
b1111101111000111 +
0%
b11101111001110 $
b11101111001110 )
b1011111111111001 #
b1011111111111001 (
b1000000 '
#130000
b110010001100011 !
b110010001100011 +
1"
b1111010011001101 $
b1111010011001101 )
b110111110010110 #
b110111110010110 (
b1000001 '
#132000
b1101001111011011 !
b1101001111011011 +
0"
b1000111001001 $
b1000111001001 )
b1100001000010010 #
b1100001000010010 (
b1000010 '
#134000
b11011010101110 !
b11011010101110 +
1"
1%
b1010011010010011 $
b1010011010010011 )
b1101110101000001 #
b1101110101000001 (
b1000011 '
#136000
b100111111111100 !
b100111111111100 +
b111101111010110 $
b111101111010110 )
b1100101111010010 #
b1100101111010010 (
b1000100 '
#138000
b10010101100 !
b10010101100 +
0%
b1101000001000 $
b1101000001000 )
b1110101010100100 #
b1110101010100100 (
b1000101 '
#140000
0"
b1111000001001001 !
b1111000001001001 +
1%
b1010000011011011 $
b1010000011011011 )
b1001000100100100 #
b1001000100100100 (
b1000110 '
#142000
b1111011111001101 !
b1111011111001101 +
0%
b101000001110 $
b101000001110 )
b1110110110111111 #
b1110110110111111 (
b1000111 '
#144000
b1101001011011 !
b1101001011011 +
1"
b10011010000000 $
b10011010000000 )
b1111001111011011 #
b1111001111011011 (
b1001000 '
#146000
0"
b1100111110111110 !
b1100111110111110 +
1%
b1110100010010010 $
b1110100010010010 )
b1011100001010000 #
b1011100001010000 (
b1001001 '
#148000
b111010111110 !
b111010111110 +
b1111010111111001 $
b1111010111111001 )
b10010110111 #
b10010110111 (
b1001010 '
#150000
b10100000010110 !
b10100000010110 +
1"
0%
b10111100001100 $
b10111100001100 )
b1111100100001010 #
b1111100100001010 (
b1001011 '
#152000
0"
b1001101110011101 !
b1001101110011101 +
1%
b1010100001100110 $
b1010100001100110 )
b100010000000011 #
b100010000000011 (
b1001100 '
#154000
b1101001011101000 !
b1101001011101000 +
1"
0%
b1101010111110111 $
b1101010111110111 )
b1111110011110001 #
b1111110011110001 (
b1001101 '
#156000
b1001111010111111 !
b1001111010111111 +
0"
b100110111110110 $
b100110111110110 )
b101000011001001 #
b101000011001001 (
b1001110 '
#158000
b11011101100011 !
b11011101100011 +
1"
1%
b111000111111000 $
b111000111111000 )
b1010100101011011 #
b1010100101011011 (
b1001111 '
#160000
b1100101111111 !
b1100101111111 +
0%
b10010100111000 $
b10010100111000 )
b1111010001000111 #
b1111010001000111 (
b1010000 '
#162000
0"
b1100001011111110 !
b1100001011111110 +
1%
b1110111001101001 $
b1110111001101001 )
b1011000101100111 #
b1011000101100111 (
b1010001 '
#164000
b111011101001010 !
b111011101001010 +
1"
0%
b1001110111110011 $
b1001110111110011 )
b1101100101010111 #
b1101100101010111 (
b1010010 '
#166000
b10011000000 !
b10011000000 +
1%
b1010111110011001 $
b1010111110011001 )
b1011010001011001 #
b1011010001011001 (
b1010011 '
#168000
b1101110010101000 !
b1101110010101000 +
0"
b11111000100000 $
b11111000100000 )
b1101011001000 #
b1101011001000 (
b1010100 '
#170000
b1010111011010000 !
b1010111011010000 +
0"
b1111100111100010 $
b1111100111100010 )
b1010100010110010 #
b1010100010110010 (
b1010101 '
#172000
b1111011011110101 !
b1111011011110101 +
b11010001010110 $
b11010001010110 )
b10101101001011 #
b10101101001011 (
b1010110 '
#174000
b110111011110111 !
b110111011110111 +
1"
b100110001110001 $
b100110001110001 )
b1011101101101000 #
b1011101101101000 (
b1010111 '
#176000
b1000010001101001 !
b1000010001101001 +
0%
b1100001010111110 $
b1100001010111110 )
b1100000110101011 #
b1100000110101011 (
b1011000 '
#178000
b10110100001100 !
b10110100001100 +
1"
1%
b111011000001011 $
b111011000001011 )
b1010001100010111 #
b1010001100010111 (
b1011001 '
#180000
0"
b1110001011110100 !
b1110001011110100 +
b1011011100111011 $
b1011011100111011 )
b1001101000101111 #
b1001101000101111 (
b1011010 '
#182000
b110100010110111 !
b110100010110111 +
0%
b10010000011 $
b10010000011 )
b110010000110100 #
b110010000110100 (
b1011011 '
#184000
b1100100010011000 !
b1100100010011000 +
1"
b1100101010000110 $
b1100101010000110 )
b1111111000010010 #
b1111111000010010 (
b1011100 '
#186000
b111101101000 !
b111101101000 +
b10001000111001 $
b10001000111001 )
b1110110100101111 #
b1110110100101111 (
b1011101 '
#188000
b101111001110011 !
b101111001110011 +
1%
b1001101011000111 $
b1001101011000111 )
b1111100100111010 #
b1111100100111010 (
b1011110 '
#190000
b1100010001100000 !
b1100010001100000 +
0"
0%
b11001010100 $
b11001010100 )
b1011111000001100 #
b1011111000001100 (
b1011111 '
#192000
b111001111001100 !
b111001111001100 +
b1011100000110 $
b1011100000110 )
b101110011000110 #
b101110011000110 (
b1100000 '
#194000
b111010111100 !
b111010111100 +
1"
1%
b1010110010010000 $
b1010110010010000 )
b1011101101001100 #
b1011101101001100 (
b1100001 '
#196000
b1110111001100110 !
b1110111001100110 +
0"
b1010110011100111 $
b1010110011100111 )
b1001101101001101 #
b1001101101001101 (
b1100010 '
#198000
b1001010110111100 !
b1001010110111100 +
b1001001011011100 $
b1001001011011100 )
b10100010011000 #
b10100010011000 (
b1100011 '
#200000
b1101111101011001 !
b1101111101011001 +
0"
b1100011010011000 $
b1100011010011000 )
b1010010111110001 #
b1010010111110001 (
b1100100 '
#202000
b111101000110101 !
b111101000110101 +
0%
b100110111000011 $
b100110111000011 )
b10110001110010 #
b10110001110010 (
b1100101 '
#204000
b1011001101000010 !
b1011001101000010 +
b1001110011101011 $
b1001110011101011 )
b1011001010111 #
b1011001010111 (
b1100110 '
#206000
b1010110010110011 !
b1010110010110011 +
1%
b1110110100011001 $
b1110110100011001 )
b1001100111001100 #
b1001100111001100 (
b1100111 '
#208000
1"
b1010111001101101 !
b1010111001101101 +
b11011001010101 $
b11011001010101 )
b1110010011000010 #
b1110010011000010 (
b1101000 '
#210000
b1000100000101010 !
b1000100000101010 +
0"
b1001001011100100 $
b1001001011100100 )
b1101100001110 #
b1101100001110 (
b1101001 '
#212000
1"
b111011010110001 !
b111011010110001 +
b1110000100101 $
b1110000100101 )
b1001001011010110 #
b1001001011010110 (
b1101010 '
#214000
b11110000000 !
b11110000000 +
0%
b1101111010111011 $
b1101111010111011 )
b10100011000101 #
b10100011000101 (
b1101011 '
#216000
b1010111100100011 !
b1010111100100011 +
0"
1%
b110100011011100 $
b110100011011100 )
b1011111111111 #
b1011111111111 (
b1101100 '
#218000
b100110110111010 !
b100110110111010 +
1"
0%
b110101000011011 $
b110101000011011 )
b1110001110011111 #
b1110001110011111 (
b1101101 '
#220000
b10001011010101 !
b10001011010101 +
b101000010110100 $
b101000010110100 )
b1101001000100001 #
b1101001000100001 (
b1101110 '
#222000
b1001101001011010 !
b1001101001011010 +
0"
b1000111000010100 $
b1000111000010100 )
b110001000110 #
b110001000110 (
b1101111 '
#224000
b11110010000011 !
b11110010000011 +
1"
1%
b101100010000100 $
b101100010000100 )
b1001010100000111 #
b1001010100000111 (
b1110000 '
#226000
b1001101000011111 !
b1001101000011111 +
0%
b1110111010100111 $
b1110111010100111 )
b1010101101111000 #
b1010101101111000 (
b1110001 '
#228000
b1000001011110011 !
b1000001011110011 +
1"
1%
b11110110101101 $
b11110110101101 )
b1100000010100000 #
b1100000010100000 (
b1110010 '
#230000
b100011001110011 !
b100011001110011 +
0%
b1001011010100100 $
b1001011010100100 )
b1010111111001111 #
b1010111111001111 (
b1110011 '
#232000
b110101110100010 !
b110101110100010 +
0"
1%
b1110100010001001 $
b1110100010001001 )
b101010000101011 #
b101010000101011 (
b1110100 '
#234000
b101110111101110 !
b101110111101110 +
1"
0%
b111001000000011 $
b111001000000011 )
b1110101111101011 #
b1110101111101011 (
b1110101 '
#236000
b1000100000100001 !
b1000100000100001 +
0"
1%
b1110001100010110 $
b1110001100010110 )
b110101100110111 #
b110101100110111 (
b1110110 '
#238000
b110101010001110 !
b110101010001110 +
b1010101101001000 $
b1010101101001000 )
b1010111010110 #
b1010111010110 (
b1110111 '
#240000
b1010011011110100 !
b1010011011110100 +
b1110100000001110 $
b1110100000001110 )
b1000111100000010 #
b1000111100000010 (
b1111000 '
#242000
b1001111110110111 !
b1001111110110111 +
0%
b1001101001010001 $
b1001101001010001 )
b10101100110 #
b10101100110 (
b1111001 '
#244000
b1100101000111111 !
b1100101000111111 +
1%
b1010111111001011 $
b1010111111001011 )
b111101000001010 #
b111101000001010 (
b1111010 '
#246000
b11111110101010 !
b11111110101010 +
1"
0%
b1011001010010101 $
b1011001010010101 )
b1000110100010101 #
b1000110100010101 (
b1111011 '
#248000
b1010111100100000 !
b1010111100100000 +
b1011110010001010 $
b1011110010001010 )
b1111001010010110 #
b1111001010010110 (
b1111100 '
#250000
b1011110111010111 !
b1011110111010111 +
0"
b100101010010010 $
b100101010010010 )
b111001101000101 #
b111001101000101 (
b1111101 '
#252000
b10000001010 !
b10000001010 +
1"
b1011100011101001 $
b1011100011101001 )
b100101100100001 #
b100101100100001 (
b1111110 '
#254000
b10001011101100 !
b10001011101100 +
b1101001110010000 $
b1101001110010000 )
b100111101011100 #
b100111101011100 (
b1111111 '
#256000
b11011101101111 !
b11011101101111 +
0"
1%
b1111011100100010 $
b1111011100100010 )
b10111010010001 #
b10111010010001 (
b10000000 '
#258000
b100110000111111 !
b100110000111111 +
1"
0%
b110010111010001 $
b110010111010001 )
b1110011001101110 #
b1110011001101110 (
b10000001 '
#260000
b1101111001100001 !
b1101111001100001 +
0"
b110011001101101 $
b110011001101101 )
b111011111110100 #
b111011111110100 (
b10000010 '
#262000
b1011011001000 !
b1011011001000 +
1"
1%
b1011110110111010 $
b1011110110111010 )
b1101010010000010 #
b1101010010000010 (
b10000011 '
#264000
b1100011001110100 !
b1100011001110100 +
0"
0%
b1011001110010100 $
b1011001110010100 )
b1001011100000 #
b1001011100000 (
b10000100 '
#266000
b1001000110100011 !
b1001000110100011 +
b1101011000 $
b1101011000 )
b1000111001001011 #
b1000111001001011 (
b10000101 '
#268000
b1100100100001 !
b1100100100001 +
1"
b1010101011010011 $
b1010101011010011 )
b110111001001110 #
b110111001001110 (
b10000110 '
#270000
b1110000110001100 !
b1110000110001100 +
b1110100111101001 $
b1110100111101001 )
b1111011110100011 #
b1111011110100011 (
b10000111 '
#272000
b1001100011101 !
b1001100011101 +
1"
1%
b1001011000111100 $
b1001011000111100 )
b1010100101011001 #
b1010100101011001 (
b10001000 '
#274000
b1100100000011101 !
b1100100000011101 +
0"
0%
b1100011011111000 $
b1100011011111000 )
b100100101 #
b100100101 (
b10001001 '
#276000
b1110100100001101 !
b1110100100001101 +
b1100100010100101 $
b1100100010100101 )
b10000001101000 #
b10000001101000 (
b10001010 '
#278000
b1100001001000000 !
b1100001001000000 +
1%
b1111111100011000 $
b1111111100011000 )
b1100000101011000 #
b1100000101011000 (
b10001011 '
#280000
b1010111010111 !
b1010111010111 +
1"
0%
b11000100010011 $
b11000100010011 )
b1110010011000100 #
b1110010011000100 (
b10001100 '
#282000
b101111100010 !
b101111100010 +
b1100101011001 $
b1100101011001 )
b1111001010001001 #
b1111001010001001 (
b10001101 '
#284000
b100000001110011 !
b100000001110011 +
1%
b1000110100101100 $
b1000110100101100 )
b1100110110011111 #
b1100110110011111 (
b10001110 '
#286000
b1111000000110100 !
b1111000000110100 +
0"
b1000100110010111 $
b1000100110010111 )
b111100111001011 #
b111100111001011 (
b10001111 '
#288000
b1010011000000010 !
b1010011000000010 +
0%
b100000000000 $
b100000000000 )
b1001111000000010 #
b1001111000000010 (
b10010000 '
#290000
b101100100011000 !
b101100100011000 +
1"
b1100101011011001 $
b1100101011011001 )
b1000111000111111 #
b1000111000111111 (
b10010001 '
#292000
b100101011111 !
b100101011111 +
1"
1%
b10000000111100 $
b10000000111100 )
b10100110011011 #
b10100110011011 (
b10010010 '
#294000
b110100100 !
b110100100 +
b1111000010001001 $
b1111000010001001 )
b1111001000101101 #
b1111001000101101 (
b10010011 '
#296000
b1011011100000110 !
b1011011100000110 +
0"
0%
b11110011011100 $
b11110011011100 )
b111101000101010 #
b111101000101010 (
b10010100 '
#298000
b1001100000100100 !
b1001100000100100 +
b1101010010 $
b1101010010 )
b1001010011010010 #
b1001010011010010 (
b10010101 '
#300000
b1010001111010100 !
b1010001111010100 +
b1001101111010001 $
b1001101111010001 )
b100000000011 #
b100000000011 (
b10010110 '
#302000
b1110010001000001 !
b1110010001000001 +
1%
b10010011101011 $
b10010011101011 )
b100100101100 #
b100100101100 (
b10010111 '
#304000
b1111110010010110 !
b1111110010010110 +
0"
b1001110110100011 $
b1001110110100011 )
b1001101000111001 #
b1001101000111001 (
b10011000 '
#306000
1"
b11011001110001 !
b11011001110001 +
b100101110011100 $
b100101110011100 )
b1000001000001101 #
b1000001000001101 (
b10011001 '
#308000
0"
b1011111011000001 !
b1011111011000001 +
b1101011110000000 $
b1101011110000000 )
b1001011001000001 #
b1001011001000001 (
b10011010 '
#310000
1"
b11001010100001 !
b11001010100001 +
b101101000101110 $
b101101000101110 )
b1000110011001111 #
b1000110011001111 (
b10011011 '
#312000
b101111100100100 !
b101111100100100 +
b1001011000101110 $
b1001011000101110 )
b1111010101010010 #
b1111010101010010 (
b10011100 '
#314000
b111000111001011 !
b111000111001011 +
0%
b1001000001101001 $
b1001000001101001 )
b1110000101100010 #
b1110000101100010 (
b10011101 '
#316000
b100111101001 !
b100111101001 +
b10110110111110 $
b10110110111110 )
b1101110000101011 #
b1101110000101011 (
b10011110 '
#318000
b1001011010010100 !
b1001011010010100 +
0"
1%
b1000110101010000 $
b1000110101010000 )
b10001111100100 #
b10001111100100 (
b10011111 '
#320000
b1011111000001011 !
b1011111000001011 +
1"
0%
b1111011000111010 $
b1111011000111010 )
b1100011111010001 #
b1100011111010001 (
b10100000 '
#322000
b1110100001001010 !
b1110100001001010 +
0"
b1001010000101011 $
b1001010000101011 )
b101010000011111 #
b101010000011111 (
b10100001 '
#324000
b100001101110001 !
b100001101110001 +
1"
b100101100001011 $
b100101100001011 )
b1111100001100110 #
b1111100001100110 (
b10100010 '
#326000
b1000010001111111 !
b1000010001111111 +
b1010100111001110 $
b1010100111001110 )
b1101101010110001 #
b1101101010110001 (
b10100011 '
#328000
b111100111101101 !
b111100111101101 +
b1001011110000011 $
b1001011110000011 )
b1110001001101010 #
b1110001001101010 (
b10100100 '
#330000
b101110010010011 !
b101110010010011 +
b1111010111011110 $
b1111010111011110 )
b110011010110101 #
b110011010110101 (
b10100101 '
#332000
b110011000001100 !
b110011000001100 +
b1001001110111000 $
b1001001110111000 )
b1101001001010100 #
b1101001001010100 (
b10100110 '
#334000
b101111000000011 !
b101111000000011 +
1"
1%
b10110111000000 $
b10110111000000 )
b1000101111000011 #
b1000101111000011 (
b10100111 '
#336000
b10010010110001 !
b10010010110001 +
0%
b1011110011010111 $
b1011110011010111 )
b110011111011010 #
b110011111011010 (
b10101000 '
#338000
b1001011001100000 !
b1001011001100000 +
1%
b101110001011101 $
b101110001011101 )
b1111001010111101 #
b1111001010111101 (
b10101001 '
#340000
b111100111110011 !
b111100111110011 +
0"
0%
b10110011011000 $
b10110011011000 )
b100110100011011 #
b100110100011011 (
b10101010 '
#342000
b11101010001000 !
b11101010001000 +
1"
b1110110111101010 $
b1110110111101010 )
b100110010011110 #
b100110010011110 (
b10101011 '
#344000
b110111110010000 !
b110111110010000 +
1"
1%
b111010110110110 $
b111010110110110 )
b1110010101000110 #
b1110010101000110 (
b10101100 '
#346000
b110000010110101 !
b110000010110101 +
0"
b1011101000000101 $
b1011101000000101 )
b1101010111010 #
b1101010111010 (
b10101101 '
#348000
b100111011101000 !
b100111011101000 +
1"
b111011110000010 $
b111011110000010 )
b1100011001101010 #
b1100011001101010 (
b10101110 '
#350000
b11111110 !
b11111110 +
0%
b111110110110110 $
b111110110110110 )
b1000001101001000 #
b1000001101001000 (
b10101111 '
#352000
b10010000011011 !
b10010000011011 +
1%
b1000010011011110 $
b1000010011011110 )
b1010100011111001 #
b1010100011111001 (
b10110000 '
#354000
b1000011111000011 !
b1000011111000011 +
0%
b1001011110111110 $
b1001011110111110 )
b1111000000000101 #
b1111000000000101 (
b10110001 '
#356000
b11100110110 !
b11100110110 +
1"
1%
b110111000111111 $
b110111000111111 )
b111010101110101 #
b111010101110101 (
b10110010 '
#358000
b110000101101000 !
b110000101101000 +
0"
b1100000110111011 $
b1100000110111011 )
b10001100100011 #
b10001100100011 (
b10110011 '
#360000
b1110100111000111 !
b1110100111000111 +
b1001101100010000 $
b1001101100010000 )
b1000010011010111 #
b1000010011010111 (
b10110100 '
#362000
b1000011110001001 !
b1000011110001001 +
0%
b101000010001 $
b101000010001 )
b111110101111000 #
b111110101111000 (
b10110101 '
#364000
b100010110101010 !
b100010110101010 +
0"
1%
b1110011010100110 $
b1110011010100110 )
b10110001010000 #
b10110001010000 (
b10110110 '
#366000
b101011111000011 !
b101011111000011 +
0%
b11100010110011 $
b11100010110011 )
b1111100010000 #
b1111100010000 (
b10110111 '
#368000
b1010100111011001 !
b1010100111011001 +
1"
1%
b101010110101101 $
b101010110101101 )
b1111111110000110 #
b1111111110000110 (
b10111000 '
#370000
b1000000010110111 !
b1000000010110111 +
0%
b1011111000100110 $
b1011111000100110 )
b1100001010010001 #
b1100001010010001 (
b10111001 '
#372000
b1100011111110 !
b1100011111110 +
1"
1%
b1001001011100001 $
b1001001011100001 )
b1010101111011111 #
b1010101111011111 (
b10111010 '
#374000
b100011111100 !
b100011111100 +
b1110101111011100 $
b1110101111011100 )
b1111010011011000 #
b1111010011011000 (
b10111011 '
#376000
b1111001010000011 !
b1111001010000011 +
0"
0%
b100111010001111 $
b100111010001111 )
b1010001111110100 #
b1010001111110100 (
b10111100 '
#378000
b1100011101101010 !
b1100011101101010 +
0"
1%
b1100000010100000 $
b1100000010100000 )
b1000100000001010 #
b1000100000001010 (
b10111101 '
