counter/Behavior/counter.v
`timescale 1ns/10ps
module Syncounter(mode, clk, rst, counter);

input mode, clk, rst; // mode = 1: count 0 -> 30, mode = 0: count 30 -> 0
output reg [4:0] counter;
always @(posedge clk or posedge rst) begin
    if (rst) begin
        counter <= 0;
    end
    else begin    
        if (mode && counter == 5'd30)
            counter <= 5'b0;
        else if (!mode && counter == 0)
            counter <= 5'd30;
        else if (mode)
            counter <= counter + 1'b1;
        else 
            counter <= counter - 1'b1;
    end
end

endmodule

counter/Behavior/testbench.v
`timescale 1ns/10ps
`include "./counter.v"
`define delay 10
`define clkPeriod 20

module testbench();
reg clk, rst, mode;
wire [4:0] counter;

Syncounter S1(
    .mode(mode),
    .clk(clk),
    .rst(rst),
    .counter(counter)
);

// clock generator
always #(`clkPeriod/2) clk = ~clk;

integer i;
initial begin
    rst = 1;
    clk = 0;
    mode = 1;
    # 5   rst = 0;
    # 107 rst = 1; // check asynchronous reset
    # 23  rst = 0;
    # 660 mode = 0; // check counter in mode 1
    # 702 rst = 1; // check counter in mode 0
    # 28  rst = 0; mode = 1; // check asynchronous reset
    # 600 mode = 0;
    # 600;
    $finish;


end

// generate waveform
initial begin
    $dumpfile("counter.vcd");
    $dumpvars;
end

// initial begin
//     $fsdbDumpfile("counter.fsdb");
//     $fsdbDumpvars;
// end


endmodule

counter/Behavior/counter.vcd
$date
	Tue Oct 20 22:45:00 2020
$end
$version
	Icarus Verilog
$end
$timescale
	10ps
$end
$scope module testbench $end
$var wire 5 ! counter [4:0] $end
$var reg 1 " clk $end
$var reg 1 # mode $end
$var reg 1 $ rst $end
$scope module S1 $end
$var wire 1 " clk $end
$var wire 1 # mode $end
$var wire 1 $ rst $end
$var reg 5 % counter [4:0] $end
$upscope $end
$upscope $end
$enddefinitions $end
#0
$dumpvars
b0 %
1$
1#
0"
b0 !
$end
#500
0$
#1000
b1 !
b1 %
1"
#2000
0"
#3000
b10 !
b10 %
1"
#4000
0"
#5000
b11 !
b11 %
1"
#6000
0"
#7000
b100 !
b100 %
1"
#8000
0"
#9000
b101 !
b101 %
1"
#10000
0"
#11000
b110 !
b110 %
1"
#11200
b0 !
b0 %
1$
#12000
0"
#13000
1"
#13500
0$
#14000
0"
#15000
b1 !
b1 %
1"
#16000
0"
#17000
b10 !
b10 %
1"
#18000
0"
#19000
b11 !
b11 %
1"
#20000
0"
#21000
b100 !
b100 %
1"
#22000
0"
#23000
b101 !
b101 %
1"
#24000
0"
#25000
b110 !
b110 %
1"
#26000
0"
#27000
b111 !
b111 %
1"
#28000
0"
#29000
b1000 !
b1000 %
1"
#30000
0"
#31000
b1001 !
b1001 %
1"
#32000
0"
#33000
b1010 !
b1010 %
1"
#34000
0"
#35000
b1011 !
b1011 %
1"
#36000
0"
#37000
b1100 !
b1100 %
1"
#38000
0"
#39000
b1101 !
b1101 %
1"
#40000
0"
#41000
b1110 !
b1110 %
1"
#42000
0"
#43000
b1111 !
b1111 %
1"
#44000
0"
#45000
b10000 !
b10000 %
1"
#46000
0"
#47000
b10001 !
b10001 %
1"
#48000
0"
#49000
b10010 !
b10010 %
1"
#50000
0"
#51000
b10011 !
b10011 %
1"
#52000
0"
#53000
b10100 !
b10100 %
1"
#54000
0"
#55000
b10101 !
b10101 %
1"
#56000
0"
#57000
b10110 !
b10110 %
1"
#58000
0"
#59000
b10111 !
b10111 %
1"
#60000
0"
#61000
b11000 !
b11000 %
1"
#62000
0"
#63000
b11001 !
b11001 %
1"
#64000
0"
#65000
b11010 !
b11010 %
1"
#66000
0"
#67000
b11011 !
b11011 %
1"
#68000
0"
#69000
b11100 !
b11100 %
1"
#70000
0"
#71000
b11101 !
b11101 %
1"
#72000
0"
#73000
b11110 !
b11110 %
1"
#74000
0"
#75000
b0 !
b0 %
1"
#76000
0"
#77000
b1 !
b1 %
1"
#78000
0"
#79000
b10 !
b10 %
1"
#79500
0#
#80000
0"
#81000
b1 !
b1 %
1"
#82000
0"
#83000
b0 !
b0 %
1"
#84000
0"
#85000
b11110 !
b11110 %
1"
#86000
0"
#87000
b11101 !
b11101 %
1"
#88000
0"
#89000
b11100 !
b11100 %
1"
#90000
0"
#91000
b11011 !
b11011 %
1"
#92000
0"
#93000
b11010 !
b11010 %
1"
#94000
0"
#95000
b11001 !
b11001 %
1"
#96000
0"
#97000
b11000 !
b11000 %
1"
#98000
0"
#99000
b10111 !
b10111 %
1"
#100000
0"
#101000
b10110 !
b10110 %
1"
#102000
0"
#103000
b10101 !
b10101 %
1"
#104000
0"
#105000
b10100 !
b10100 %
1"
#106000
0"
#107000
b10011 !
b10011 %
1"
#108000
0"
#109000
b10010 !
b10010 %
1"
#110000
0"
#111000
b10001 !
b10001 %
1"
#112000
0"
#113000
b10000 !
b10000 %
1"
#114000
0"
#115000
b1111 !
b1111 %
1"
#116000
0"
#117000
b1110 !
b1110 %
1"
#118000
0"
#119000
b1101 !
b1101 %
1"
#120000
0"
#121000
b1100 !
b1100 %
1"
#122000
0"
#123000
b1011 !
b1011 %
1"
#124000
0"
#125000
b1010 !
b1010 %
1"
#126000
0"
#127000
b1001 !
b1001 %
1"
#128000
0"
#129000
b1000 !
b1000 %
1"
#130000
0"
#131000
b111 !
b111 %
1"
#132000
0"
#133000
b110 !
b110 %
1"
#134000
0"
#135000
b101 !
b101 %
1"
#136000
0"
#137000
b100 !
b100 %
1"
#138000
0"
#139000
b11 !
b11 %
1"
#140000
0"
#141000
b10 !
b10 %
1"
#142000
0"
#143000
b1 !
b1 %
1"
#144000
0"
#145000
b0 !
b0 %
1"
#146000
0"
#147000
b11110 !
b11110 %
1"
#148000
0"
#149000
b11101 !
b11101 %
1"
#149700
b0 !
b0 %
1$
#150000
0"
#151000
1"
#152000
0"
#152500
1#
0$
#153000
b1 !
b1 %
1"
#154000
0"
#155000
b10 !
b10 %
1"
#156000
0"
#157000
b11 !
b11 %
1"
#158000
0"
#159000
b100 !
b100 %
1"
#160000
0"
#161000
b101 !
b101 %
1"
#162000
0"
#163000
b110 !
b110 %
1"
#164000
0"
#165000
b111 !
b111 %
1"
#166000
0"
#167000
b1000 !
b1000 %
1"
#168000
0"
#169000
b1001 !
b1001 %
1"
#170000
0"
#171000
b1010 !
b1010 %
1"
#172000
0"
#173000
b1011 !
b1011 %
1"
#174000
0"
#175000
b1100 !
b1100 %
1"
#176000
0"
#177000
b1101 !
b1101 %
1"
#178000
0"
#179000
b1110 !
b1110 %
1"
#180000
0"
#181000
b1111 !
b1111 %
1"
#182000
0"
#183000
b10000 !
b10000 %
1"
#184000
0"
#185000
b10001 !
b10001 %
1"
#186000
0"
#187000
b10010 !
b10010 %
1"
#188000
0"
#189000
b10011 !
b10011 %
1"
#190000
0"
#191000
b10100 !
b10100 %
1"
#192000
0"
#193000
b10101 !
b10101 %
1"
#194000
0"
#195000
b10110 !
b10110 %
1"
#196000
0"
#197000
b10111 !
b10111 %
1"
#198000
0"
#199000
b11000 !
b11000 %
1"
#200000
0"
#201000
b11001 !
b11001 %
1"
#202000
0"
#203000
b11010 !
b11010 %
1"
#204000
0"
#205000
b11011 !
b11011 %
1"
#206000
0"
#207000
b11100 !
b11100 %
1"
#208000
0"
#209000
b11101 !
b11101 %
1"
#210000
0"
#211000
b11110 !
b11110 %
1"
#212000
0"
#212500
0#
#213000
b11101 !
b11101 %
1"
#214000
0"
#215000
b11100 !
b11100 %
1"
#216000
0"
#217000
b11011 !
b11011 %
1"
#218000
0"
#219000
b11010 !
b11010 %
1"
#220000
0"
#221000
b11001 !
b11001 %
1"
#222000
0"
#223000
b11000 !
b11000 %
1"
#224000
0"
#225000
b10111 !
b10111 %
1"
#226000
0"
#227000
b10110 !
b10110 %
1"
#228000
0"
#229000
b10101 !
b10101 %
1"
#230000
0"
#231000
b10100 !
b10100 %
1"
#232000
0"
#233000
b10011 !
b10011 %
1"
#234000
0"
#235000
b10010 !
b10010 %
1"
#236000
0"
#237000
b10001 !
b10001 %
1"
#238000
0"
#239000
b10000 !
b10000 %
1"
#240000
0"
#241000
b1111 !
b1111 %
1"
#242000
0"
#243000
b1110 !
b1110 %
1"
#244000
0"
#245000
b1101 !
b1101 %
1"
#246000
0"
#247000
b1100 !
b1100 %
1"
#248000
0"
#249000
b1011 !
b1011 %
1"
#250000
0"
#251000
b1010 !
b1010 %
1"
#252000
0"
#253000
b1001 !
b1001 %
1"
#254000
0"
#255000
b1000 !
b1000 %
1"
#256000
0"
#257000
b111 !
b111 %
1"
#258000
0"
#259000
b110 !
b110 %
1"
#260000
0"
#261000
b101 !
b101 %
1"
#262000
0"
#263000
b100 !
b100 %
1"
#264000
0"
#265000
b11 !
b11 %
1"
#266000
0"
#267000
b10 !
b10 %
1"
#268000
0"
#269000
b1 !
b1 %
1"
#270000
0"
#271000
b0 !
b0 %
1"
