HW1/Behavior/test/16bit_adder.v
// implement 16 bit adder by behavior
module Sub_adder_16bit(sum, overdetect, cout, a, b, mode);

input [15:0] a, b;
input mode; // mode = 1: subtractor, mode = 0: adder
output [15:0] sum;
output cout, overdetect; // overflow detect 

//reg [16:0] result;

assign {cout, sum} = (mode) ? (a+{~b+1'b1}) : (a+b);
// assign overdetect = 
//    /*Positive Number OverFlow*/(((Add_ctrl==1)&&(A[15]==1)&&(B[15]==0)&&(SUM[15]==0)) || ((Add_ctrl==1)&&(A[15]==0)&&(B[15]==1)&&(SUM[15]==1)) 
// || /*Negative Number OverFlow*/ ((Add_ctrl==0)&&(A[15]==0)&&(B[15]==0)&&(SUM[15]==1)) || ((Add_ctrl==0)&&(A[15]==1)&&(B[15]==1)&&(SUM[15]==0)) )? 1:0;





endmodule

HW1/Behavior/test/testbench.v
`include "./16bit_adder.v"
`timescale 1ns/10ps
`define delay 20 
module testbench();

reg [15:0] A, B;
reg Mode;
wire [15:0] SUM;
wire Cout;

reg [15:0] mem_A [9999:0];
reg [15:0] mem_B [9999:0];
reg mem_ctrl [9999:0];
reg [16:0] expect [9999:0];

reg [16:0] error = 0;

// read the testing data
initial begin
	$readmemh("A.txt", mem_A);
	$readmemh("B.txt", mem_B);
	$readmemh("ctrl.txt", mem_ctrl);
	$readmemh("result.txt", expect);
end


Sub_adder_16bit S1(
    .a(A),
    .b(B),
    .mode(Mode),
    .cout(Cout),
    .sum(SUM)
);

integer i;
initial begin
    for (i =0 ; i <= 9999; i = i + 1 ) begin
        A = mem_A[i] ;
        B = mem_B[i] ;
        Mode = mem_ctrl[i] ;

        #(`delay);
        if (SUM !== expect[i][15:0]) begin
            $display ("ERROR at time=%d(pattern%d): SUM(%h)!= expect(%h)", $time, i+1, SUM, expect[i][15:0]);
            error = error + 1;
        end
		
        if (Cout !== expect[i][16]) begin
            $display ("ERROR at time=%d(pattern%d): C_out(%b)!= expect(%b)", $time,  i+1, Cout, expect[i][16]);
            error = error + 1;
        end

    end

    if(error == 17'b0) begin
        $display("        ***********************************************        ");
        $display("        **                                           **        ");
        $display("        **             Congratulations !!            **        ");
        $display("        **               Test PASS  !!               **        ");
        $display("        **                                           **        ");
        $display("        ***********************************************        ");
    end
    else begin
        $display ("=================================================");
        $display ("There're %d errors in your design", error); 
        $display ("=================================================");
    end

	$finish ;

end

initial begin
    $dumpfile("16bitsub_adder.vcd");
    $dumpvars;
end

endmodule

HW1/Behavior/16bitsub_adder.vcd
$date
	Sun Oct 18 17:53:50 2020
$end
$version
	Icarus Verilog
$end
$timescale
	10ps
$end
$scope module testbench $end
$var wire 16 ! SUM [15:0] $end
$var wire 1 " Cout $end
$var reg 16 # A [15:0] $end
$var reg 16 $ B [15:0] $end
$var reg 1 % Mode $end
$var reg 17 & error [16:0] $end
$var integer 32 ' i [31:0] $end
$scope module S1 $end
$var wire 16 ( a [15:0] $end
$var wire 16 ) b [15:0] $end
$var wire 1 % mode $end
$var wire 1 * overdetect $end
$var wire 16 + sum [15:0] $end
$var wire 1 " cout $end
$upscope $end
$upscope $end
$enddefinitions $end
#0
$dumpvars
b10100101001110 +
z*
b1111111010010100 )
b10011111100010 (
b0 '
b0 &
1%
b1111111010010100 $
b10011111100010 #
0"
b10100101001110 !
$end
#2000
b1110101110011011 !
b1110101110011011 +
0%
b11010010001011 $
b11010010001011 )
b1011011100010000 #
b1011011100010000 (
b1 '
#4000
b100000100011110 !
b100000100011110 +
1"
b1111101101110011 $
b1111101101110011 )
b100010110101011 #
b100010110101011 (
b10 '
#6000
b110101110011110 !
b110101110011110 +
b1011011101111101 $
b1011011101111101 )
b1011010000100001 #
b1011010000100001 (
b11 '
#8000
b1111000111101010 !
b1111000111101010 +
0"
1%
b101110111010111 $
b101110111010111 )
b100111111000001 #
b100111111000001 (
b100 '
#10000
b1000100100000111 !
b1000100100000111 +
0"
b1101011100011011 $
b1101011100011011 )
b110000000100010 #
b110000000100010 (
b101 '
#12000
b1101100101111110 !
b1101100101111110 +
b111011110001010 $
b111011110001010 )
b101000100001000 #
b101000100001000 (
b110 '
#14000
b1011000111100111 !
b1011000111100111 +
0%
b1010001111111111 $
b1010001111111111 )
b110111101000 #
b110111101000 (
b111 '
#16000
b1111111100110 !
b1111111100110 +
1"
b101101100001111 $
b101101100001111 )
b1100010011010111 #
b1100010011010111 (
b1000 '
#18000
b100110111001 !
b100110111001 +
b1111101000101000 $
b1111101000101000 )
b111110010001 #
b111110010001 (
b1001 '
#20000
b1000000010110 !
b1000000010110 +
1"
1%
b110000101101100 $
b110000101101100 )
b111000110000010 #
b111000110000010 (
b1010 '
#22000
b10000110101101 !
b10000110101101 +
b1011011100111001 $
b1011011100111001 )
b1101100011100110 #
b1101100011100110 (
b1011 '
#24000
b10100010100100 !
b10100010100100 +
1"
b100001010010001 $
b100001010010001 )
b110101100110101 #
b110101100110101 (
b1100 '
#26000
b11011101011000 !
b11011101011000 +
0"
b1111111110001000 $
b1111111110001000 )
b11011011100000 #
b11011011100000 (
b1101 '
#28000
b1010101111011101 !
b1010101111011101 +
0%
b100100001010010 $
b100100001010010 )
b110001110001011 #
b110001110001011 (
b1110 '
#30000
b1000010111011000 !
b1000010111011000 +
1"
b1101110011110111 $
b1101110011110111 )
b1010100011100001 #
b1010100011100001 (
b1111 '
#32000
b1100001001111011 !
b1100001001111011 +
0"
1%
b1100010000111011 $
b1100010000111011 )
b1000011010110110 #
b1000011010110110 (
b10000 '
#34000
b1000111001000010 !
b1000111001000010 +
1"
b101101011111010 $
b101101011111010 )
b1110100100111100 #
b1110100100111100 (
b10001 '
#36000
b1100110001010010 !
b1100110001010010 +
0"
0%
b11010101000110 $
b11010101000110 )
b1001011100001100 #
b1001011100001100 (
b10010 '
#38000
b10101011101001 !
b10101011101001 +
1"
b1010000001010111 $
b1010000001010111 )
b1000101010010010 #
b1000101010010010 (
b10011 '
#40000
b100011011101110 !
b100011011101110 +
0"
b1001110100000 $
b1001110100000 )
b11001101001110 #
b11001101001110 (
b10100 '
#42000
b1001111011110110 !
b1001111011110110 +
1"
1%
b10011111000010 $
b10011111000010 )
b1100011010111000 #
b1100011010111000 (
b10101 '
#44000
b101001110000000 !
b101001110000000 +
0%
b101110001001111 $
b101110001001111 )
b1111011100110001 #
b1111011100110001 (
b10110 '
#46000
b11001111110010 !
b11001111110010 +
0"
1%
b1101100100000011 $
b1101100100000011 )
b110011110101 #
b110011110101 (
b10111 '
#48000
b1000010011001000 !
b1000010011001000 +
b1000111110000110 $
b1000111110000110 )
b1010001001110 #
b1010001001110 (
b11000 '
#50000
b101111111100111 !
b101111111100111 +
b1110111100111011 $
b1110111100111011 )
b100111100100010 #
b100111100100010 (
b11001 '
#52000
b1100001001111111 !
b1100001001111111 +
b1100111111010001 $
b1100111111010001 )
b1001001001010000 #
b1001001001010000 (
b11010 '
#54000
b1110010101011101 !
b1110010101011101 +
0%
b11010010110100 $
b11010010110100 )
b1011000010101001 #
b1011000010101001 (
b11011 '
#56000
b10011010010000 !
b10011010010000 +
1"
1%
b1000101000110111 $
b1000101000110111 )
b1011000011000111 #
b1011000011000111 (
b11100 '
#58000
b100111000011110 !
b100111000011110 +
b111100111101010 $
b111100111101010 )
b1100100000001000 #
b1100100000001000 (
b11101 '
#60000
b1011101110010001 !
b1011101110010001 +
0%
b1100100111000010 $
b1100100111000010 )
b1111000111001111 #
b1111000111001111 (
b11110 '
#62000
b110000101110110 !
b110000101110110 +
b1000100011001100 $
b1000100011001100 )
b1101100010101010 #
b1101100010101010 (
b11111 '
#64000
b1101000010100011 !
b1101000010100011 +
0"
1%
b1010111001110101 $
b1010111001110101 )
b111111100011000 #
b111111100011000 (
b100000 '
#66000
b1111110010110000 !
b1111110010110000 +
0%
b1100010100110101 $
b1100010100110101 )
b11011101111011 #
b11011101111011 (
b100001 '
#68000
b1100110100010100 !
b1100110100010100 +
b100000001001001 $
b100000001001001 )
b1000110011001011 #
b1000110011001011 (
b100010 '
#70000
b1101101100100101 !
b1101101100100101 +
b110001001100 $
b110001001100 )
b1100111011011001 #
b1100111011011001 (
b100011 '
#72000
b1111101101001101 !
b1111101101001101 +
0"
1%
b1001110001010000 $
b1001110001010000 )
b1001011110011101 #
b1001011110011101 (
b100100 '
#74000
b10010111111111 !
b10010111111111 +
1"
b1011011111010100 $
b1011011111010100 )
b1101110111010011 #
b1101110111010011 (
b100101 '
#76000
b1000110100001100 !
b1000110100001100 +
0%
b1011000001001011 $
b1011000001001011 )
b1101110011000001 #
b1101110011000001 (
b100110 '
#78000
b110010100010100 !
b110010100010100 +
0"
1%
b1111011101100000 $
b1111011101100000 )
b101110001110100 #
b101110001110100 (
b100111 '
#80000
1"
b11101101101000 !
b11101101101000 +
b1011000111111100 $
b1011000111111100 )
b1110110101100100 #
b1110110101100100 (
b101000 '
#82000
b101111111111010 !
b101111111111010 +
0"
0%
b1000110110111 $
b1000110110111 )
b100111001000011 #
b100111001000011 (
b101001 '
#84000
b1000011011000001 !
b1000011011000001 +
0"
1%
b1010111010011001 $
b1010111010011001 )
b11010101011010 #
b11010101011010 (
b101010 '
#86000
b100110100100110 !
b100110100100110 +
1"
0%
b1111010010001101 $
b1111010010001101 )
b101100010011001 #
b101100010011001 (
b101011 '
#88000
b111001111100100 !
b111001111100100 +
1"
1%
b1000100111111 $
b1000100111111 )
b1000010100100011 #
b1000010100100011 (
b101100 '
#90000
0"
b1010000111111010 !
b1010000111111010 +
b1111011011101011 $
b1111011011101011 )
b1001100011100101 #
b1001100011100101 (
b101101 '
#92000
b10111111110101 !
b10111111110101 +
b1101000110000101 $
b1101000110000101 )
b101111010 #
b101111010 (
b101110 '
#94000
b1110000101010101 !
b1110000101010101 +
0%
b1101010101111011 $
b1101010101111011 )
b101111011010 #
b101111011010 (
b101111 '
#96000
b1101010000000110 !
b1101010000000110 +
b101000111100101 $
b101000111100101 )
b1000001000100001 #
b1000001000100001 (
b110000 '
#98000
b1001000110111011 !
b1001000110111011 +
1"
1%
b11011001011 $
b11011001011 )
b1001100010000110 #
b1001100010000110 (
b110001 '
#100000
b110000111110 !
b110000111110 +
0%
b111010111010010 $
b111010111010010 )
b1001011001101100 #
b1001011001101100 (
b110010 '
#102000
b100111111101011 !
b100111111101011 +
1%
b110010110000101 $
b110010110000101 )
b1011010101110000 #
b1011010101110000 (
b110011 '
#104000
b1000110111001011 !
b1000110111001011 +
0"
0%
b10111010001101 $
b10111010001101 )
b101111100111110 #
b101111100111110 (
b110100 '
#106000
b101111110111110 !
b101111110111110 +
1"
b1101001000100001 $
b1101001000100001 )
b1000110110011101 #
b1000110110011101 (
b110101 '
#108000
b11101110 !
b11101110 +
b11111010001001 $
b11111010001001 )
b1100001001100101 #
b1100001001100101 (
b110110 '
#110000
0"
b1011010101111010 !
b1011010101111010 +
1%
b1011111000010011 $
b1011111000010011 )
b111001110001101 #
b111001110001101 (
b110111 '
#112000
b1101101100011 !
b1101101100011 +
1"
b1100000101011100 $
b1100000101011100 )
b1101110010111111 #
b1101110010111111 (
b111000 '
#114000
b100011001011011 !
b100011001011011 +
1"
b111001011010 $
b111001011010 )
b101010010110101 #
b101010010110101 (
b111001 '
#116000
b1011011111110 !
b1011011111110 +
0%
b1111001011001000 $
b1111001011001000 )
b10010000110110 #
b10010000110110 (
b111010 '
#118000
b1101100100011010 !
b1101100100011010 +
0"
b100101110010100 $
b100101110010100 )
b1000110110000110 #
b1000110110000110 (
b111011 '
#120000
b1010010100000001 !
b1010010100000001 +
b1000100001000100 $
b1000100001000100 )
b1110010111101 #
b1110010111101 (
b111100 '
#122000
b1101001010010000 !
b1101001010010000 +
b1011110010001010 $
b1011110010001010 )
b1011000000110 #
b1011000000110 (
b111101 '
#124000
b11101010010000 !
b11101010010000 +
1"
b1101010001100000 $
b1101010001100000 )
b110011000110000 #
b110011000110000 (
b111110 '
#126000
b110010100011101 !
b110010100011101 +
1"
1%
b11011010111001 $
b11011010111001 )
b1001101111010110 #
b1001101111010110 (
b111111 '
#128000
b1100111101000001 !
b1100111101000001 +
0"
0%
b1000000111000000 $
b1000000111000000 )
b100110110000001 #
b100110110000001 (
b1000000 '
#130000
b1101111001010010 !
b1101111001010010 +
1"
1%
b1010010101001 $
b1010010101001 )
b1111001011111011 #
b1111001011111011 (
b1000001 '
#132000
b10011110101010 !
b10011110101010 +
b100001100000101 $
b100001100000101 )
b110101010101111 #
b110101010101111 (
b1000010 '
#134000
b1100011100001110 !
b1100011100001110 +
b1111000010000 $
b1111000010000 )
b1110010100011110 #
b1110010100011110 (
b1000011 '
#136000
b1001110101001011 !
b1001110101001011 +
0%
b1100110001111101 $
b1100110001111101 )
b1101000011001110 #
b1101000011001110 (
b1000100 '
#138000
b11101011000001 !
b11101011000001 +
b1111001101010000 $
b1111001101010000 )
b100011101110001 #
b100011101110001 (
b1000101 '
#140000
b10110000100011 !
b10110000100011 +
1"
1%
b1010101110000 $
b1010101110000 )
b100000110010011 #
b100000110010011 (
b1000110 '
#142000
b11110010101100 !
b11110010101100 +
0%
b111111001111010 $
b111111001111010 )
b1011111000110010 #
b1011111000110010 (
b1000111 '
#144000
b1001101010111011 !
b1001101010111011 +
0"
b10100000111 $
b10100000111 )
b1001010110110100 #
b1001010110110100 (
b1001000 '
#146000
b11101011110110 !
b11101011110110 +
1"
b1100010000001001 $
b1100010000001001 )
b111011011101101 #
b111011011101101 (
b1001001 '
#148000
b1000100111010011 !
b1000100111010011 +
0"
b111001100000111 $
b111001100000111 )
b1011011001100 #
b1011011001100 (
b1001010 '
#150000
1"
b10010010001 !
b10010010001 +
1%
b1011001000111 $
b1011001000111 )
b1101011011000 #
b1101011011000 (
b1001011 '
#152000
b101010011011110 !
b101010011011110 +
0"
b1011101011110101 $
b1011101011110101 )
b111111010011 #
b111111010011 (
b1001100 '
#154000
b1101001110111010 !
b1101001110111010 +
b100010010001100 $
b100010010001100 )
b1100001000110 #
b1100001000110 (
b1001101 '
#156000
b11101011110000 !
b11101011110000 +
b1110101111000010 $
b1110101111000010 )
b10011010110010 #
b10011010110010 (
b1001110 '
#158000
b1001111011001110 !
b1001111011001110 +
0%
b110011011010 $
b110011011010 )
b1001000111110100 #
b1001000111110100 (
b1001111 '
#160000
b110010101110101 !
b110010101110101 +
1"
1%
b100101101011000 $
b100101101011000 )
b1011000011001101 #
b1011000011001101 (
b1010000 '
#162000
b101101110001010 !
b101101110001010 +
b110000110010100 $
b110000110010100 )
b1011110100011110 #
b1011110100011110 (
b1010001 '
#164000
b1101010100000100 !
b1101010100000100 +
0"
b111001001100000 $
b111001001100000 )
b100011101100100 #
b100011101100100 (
b1010010 '
#166000
b1001011000100110 !
b1001011000100110 +
b111100111100101 $
b111100111100101 )
b1000000001011 #
b1000000001011 (
b1010011 '
#168000
b111111001110000 !
b111111001110000 +
0%
b11001110110101 $
b11001110110101 )
b100101010111011 #
b100101010111011 (
b1010100 '
#170000
b101100011100000 !
b101100011100000 +
1%
b1011000011101001 $
b1011000011101001 )
b100111001001 #
b100111001001 (
b1010101 '
#172000
1"
b100101110011111 !
b100101110011111 +
b11011111111001 $
b11011111111001 )
b1000001110011000 #
b1000001110011000 (
b1010110 '
#174000
b11001001101001 !
b11001001101001 +
0"
b1111010100010001 $
b1111010100010001 )
b10011101111010 #
b10011101111010 (
b1010111 '
#176000
b1110111000010 !
b1110111000010 +
1"
0%
b1011111101000011 $
b1011111101000011 )
b101111001111111 #
b101111001111111 (
b1011000 '
#178000
b111110100001110 !
b111110100001110 +
1"
1%
b10101011000001 $
b10101011000001 )
b1010011111001111 #
b1010011111001111 (
b1011001 '
#180000
b1111010110100101 !
b1111010110100101 +
0"
0%
b100000010100101 $
b100000010100101 )
b1011010100000000 #
b1011010100000000 (
b1011010 '
#182000
b1100001011000100 !
b1100001011000100 +
b100011110001000 $
b100011110001000 )
b111101100111100 #
b111101100111100 (
b1011011 '
#184000
b1101011010001010 !
b1101011010001010 +
0"
1%
b1110011101001011 $
b1110011101001011 )
b1011110111010101 #
b1011110111010101 (
b1011100 '
#186000
b11000000110110 !
b11000000110110 +
0%
b1010100000101 $
b1010100000101 )
b1101100110001 #
b1101100110001 (
b1011101 '
#188000
b1001100011010001 !
b1001100011010001 +
0"
1%
b111111001000001 $
b111111001000001 )
b1011100010010 #
b1011100010010 (
b1011110 '
#190000
b1010001001001011 !
b1010001001001011 +
b110100100001011 $
b110100100001011 )
b101101010110 #
b101101010110 (
b1011111 '
#192000
b1110010001111101 !
b1110010001111101 +
b10100110101111 $
b10100110101111 )
b111000101100 #
b111000101100 (
b1100000 '
#194000
b100001100001001 !
b100001100001001 +
1"
0%
b1100000101000111 $
b1100000101000111 )
b1000000111000010 #
b1000000111000010 (
b1100001 '
#196000
b111011110010000 !
b111011110010000 +
b1000011100011100 $
b1000011100011100 )
b1111000001110100 #
b1111000001110100 (
b1100010 '
#198000
b1101010100100111 !
b1101010100100111 +
b1111011000101100 $
b1111011000101100 )
b1101111011111011 #
b1101111011111011 (
b1100011 '
#200000
b111110111001010 !
b111110111001010 +
b1011010010010111 $
b1011010010010111 )
b1100100100110011 #
b1100100100110011 (
b1100100 '
#202000
b1001010101111011 !
b1001010101111011 +
0"
1%
b1001110010001100 $
b1001110010001100 )
b11001000000111 #
b11001000000111 (
b1100101 '
#204000
b1000111010011 !
b1000111010011 +
1"
0%
b111010010100110 $
b111010010100110 )
b1001110100101101 #
b1001110100101101 (
b1100110 '
#206000
b1100010000110 !
b1100010000110 +
b1011100110011111 $
b1011100110011111 )
b101111011100111 #
b101111011100111 (
b1100111 '
#208000
b100100001011111 !
b100100001011111 +
1"
1%
b110000010010110 $
b110000010010110 )
b1010100011110101 #
b1010100011110101 (
b1101000 '
#210000
b1001101110100111 !
b1001101110100111 +
0%
b1110011110101110 $
b1110011110101110 )
b1011001111111001 #
b1011001111111001 (
b1101001 '
#212000
b1010100111011001 !
b1010100111011001 +
0"
1%
b1100111111100110 $
b1100111111100110 )
b111100110111111 #
b111100110111111 (
b1101010 '
#214000
1"
b1001110100111101 !
b1001110100111101 +
b1101110001011 $
b1101110001011 )
b1011100011001000 #
b1011100011001000 (
b1101011 '
#216000
b1111100001111010 !
b1111100001111010 +
0"
0%
b10110000111010 $
b10110000111010 )
b1100110001000000 #
b1100110001000000 (
b1101100 '
#218000
b101110000011001 !
b101110000011001 +
1"
b1011101110101000 $
b1011101110101000 )
b1010000001110001 #
b1010000001110001 (
b1101101 '
#220000
b10001001010111 !
b10001001010111 +
1"
1%
b10100001100101 $
b10100001100101 )
b100101010111100 #
b100101010111100 (
b1101110 '
#222000
b10101111011 !
b10101111011 +
b111011110010010 $
b111011110010010 )
b111110100001101 #
b111110100001101 (
b1101111 '
#224000
b111101011001011 !
b111101011001011 +
0"
0%
b1110100111100 $
b1110100111100 )
b101110110001111 #
b101110110001111 (
b1110000 '
#226000
b10110011100110 !
b10110011100110 +
1"
b1001101011000101 $
b1001101011000101 )
b1001001000100001 #
b1001001000100001 (
b1110001 '
#228000
b111111010010000 !
b111111010010000 +
b1111000101111000 $
b1111000101111000 )
b1000110100011000 #
b1000110100011000 (
b1110010 '
#230000
b1111100100111011 !
b1111100100111011 +
0"
b101000011110001 $
b101000011110001 )
b1010100001001010 #
b1010100001001010 (
b1110011 '
#232000
b101000000111100 !
b101000000111100 +
1"
1%
b100101110101110 $
b100101110101110 )
b1001101111101010 #
b1001101111101010 (
b1110100 '
#234000
b1110011101000000 !
b1110011101000000 +
0"
b10100101110001 $
b10100101110001 )
b1000010110001 #
b1000010110001 (
b1110101 '
#236000
b1000100111000010 !
b1000100111000010 +
1"
b100011000000010 $
b100011000000010 )
b1100111111000100 #
b1100111111000100 (
b1110110 '
#238000
b1110111101110111 !
b1110111101110111 +
b101011110010 $
b101011110010 )
b1111101001101001 #
b1111101001101001 (
b1110111 '
#240000
b110010110010 !
b110010110010 +
0%
b101010000110010 $
b101010000110010 )
b1011100010000000 #
b1011100010000000 (
b1111000 '
#242000
0"
b1111111000011101 !
b1111111000011101 +
1%
b1000011010101000 $
b1000011010101000 )
b1000010011000101 #
b1000010011000101 (
b1111001 '
#244000
1"
b10001100101100 !
b10001100101100 +
b101001001111010 $
b101001001111010 )
b111010110100110 #
b111010110100110 (
b1111010 '
#246000
b11101011011000 !
b11101011011000 +
b11101101111101 $
b11101101111101 )
b111011001010101 #
b111011001010101 (
b1111011 '
#248000
b11101110100011 !
b11101110100011 +
0%
b1001101110101101 $
b1001101110101101 )
b1001111111110110 #
b1001111111110110 (
b1111100 '
#250000
b101110101110011 !
b101110101110011 +
b1101000010111011 $
b1101000010111011 )
b1000110010111000 #
b1000110010111000 (
b1111101 '
#252000
b10011000110100 !
b10011000110100 +
b1010010010001001 $
b1010010010001001 )
b1000000110101011 #
b1000000110101011 (
b1111110 '
#254000
0"
b1110100011000110 !
b1110100011000110 +
1%
b1100010101011100 $
b1100010101011100 )
b1010111000100010 #
b1010111000100010 (
b1111111 '
#256000
b1010000001111100 !
b1010000001111100 +
0%
b1001001000000010 $
b1001001000000010 )
b111001111010 #
b111001111010 (
b10000000 '
#258000
1"
b100011001111010 !
b100011001111010 +
1%
b10101110100101 $
b10101110100101 )
b111001000011111 #
b111001000011111 (
b10000001 '
#260000
0"
b1101000110010100 !
b1101000110010100 +
b1011101110001001 $
b1011101110001001 )
b1000110100011101 #
b1000110100011101 (
b10000010 '
#262000
b1001000100010011 !
b1001000100010011 +
1"
b100011010011010 $
b100011010011010 )
b1101011110101101 #
b1101011110101101 (
b10000011 '
#264000
b110110001011000 !
b110110001011000 +
0%
b1100100000110001 $
b1100100000110001 )
b1010010000100111 #
b1010010000100111 (
b10000100 '
#266000
b1111101000011100 !
b1111101000011100 +
0"
1%
b11000000101111 $
b11000000101111 )
b10101001001011 #
b10101001001011 (
b10000101 '
#268000
b11011001011100 !
b11011001011100 +
1"
b111001 $
b111001 )
b11011010010101 #
b11011010010101 (
b10000110 '
#270000
b111010111100011 !
b111010111100011 +
0"
0%
b10100011000111 $
b10100011000111 )
b100110100011100 #
b100110100011100 (
b10000111 '
#272000
b1111011000100001 !
b1111011000100001 +
b1011111011101 $
b1011111011101 )
b1101111001000100 #
b1101111001000100 (
b10001000 '
#274000
b1110000000110101 !
b1110000000110101 +
0"
1%
b1101000000011111 $
b1101000000011111 )
b1011000001010100 #
b1011000001010100 (
b10001001 '
#276000
b1100000110010010 !
b1100000110010010 +
b100010001010010 $
b100010001010010 )
b10111100100 #
b10111100100 (
b10001010 '
#278000
b1110111010011100 !
b1110111010011100 +
0%
b100010000011000 $
b100010000011000 )
b1010101010000100 #
b1010101010000100 (
b10001011 '
#280000
b1100010011111111 !
b1100010011111111 +
0"
1%
b1000101111000111 $
b1000101111000111 )
b101000011000110 #
b101000011000110 (
b10001100 '
#282000
b1011110101011000 !
b1011110101011000 +
0%
b110110010111000 $
b110110010111000 )
b101000010100000 #
b101000010100000 (
b10001101 '
#284000
b110101111100111 !
b110101111100111 +
1%
b1011101110101010 $
b1011101110101010 )
b10011110010001 #
b10011110010001 (
b10001110 '
#286000
1"
b10101010010 !
b10101010010 +
b1010100100000011 $
b1010100100000011 )
b1010111001010101 #
b1010111001010101 (
b10001111 '
#288000
b1110101000111110 !
b1110101000111110 +
0"
0%
b11101111101 $
b11101111101 )
b1110001011000001 #
b1110001011000001 (
b10010000 '
#290000
b11110001000 !
b11110001000 +
1"
1%
b1010110100100010 $
b1010110100100010 )
b1011010010101010 #
b1011010010101010 (
b10010001 '
#292000
b101110010101100 !
b101110010101100 +
0"
b1111100111110100 $
b1111100111110100 )
b101011010100000 #
b101011010100000 (
b10010010 '
#294000
1"
b10101110000000 !
b10101110000000 +
b101001100101100 $
b101001100101100 )
b111111010101100 #
b111111010101100 (
b10010011 '
#296000
0"
b1110111011001000 !
b1110111011001000 +
b1101011010010011 $
b1101011010010011 )
b1100010101011011 #
b1100010101011011 (
b10010100 '
#298000
b1110011001101110 !
b1110011001101110 +
b11111111110110 $
b11111111110110 )
b10011001100100 #
b10011001100100 (
b10010101 '
#300000
b1101011100110011 !
b1101011100110011 +
0%
b101111000011110 $
b101111000011110 )
b111100100010101 #
b111100100010101 (
b10010110 '
#302000
b101001100010110 !
b101001100010110 +
1"
1%
b10101011000101 $
b10101011000101 )
b111110111011011 #
b111110111011011 (
b10010111 '
#304000
b111000111000111 !
b111000111000111 +
0%
b1100011010011110 $
b1100011010011110 )
b1010101100101001 #
b1010101100101001 (
b10011000 '
#306000
b11111000100011 !
b11111000100011 +
1%
b1011000010011000 $
b1011000010011000 )
b1110111010111011 #
b1110111010111011 (
b10011001 '
#308000
b1000110111101101 !
b1000110111101101 +
b110011001000011 $
b110011001000011 )
b1111010000110000 #
b1111010000110000 (
b10011010 '
#310000
b1010110101101011 !
b1010110101101011 +
0"
0%
b110001001001100 $
b110001001001100 )
b100101100011111 #
b100101100011111 (
b10011011 '
#312000
b1111101000100001 !
b1111101000100001 +
0"
1%
b1000000101010011 $
b1000000101010011 )
b111101101110100 #
b111101101110100 (
b10011100 '
#314000
1"
b110101100001111 !
b110101100001111 +
b101011001100 $
b101011001100 )
b111010111011011 #
b111010111011011 (
b10011101 '
#316000
b10000011101010 !
b10000011101010 +
0%
b10011110101000 $
b10011110101000 )
b1111100101000010 #
b1111100101000010 (
b10011110 '
#318000
b111011010011000 !
b111011010011000 +
1%
b1001101010110 $
b1001101010110 )
b1000100111101110 #
b1000100111101110 (
b10011111 '
#320000
b1111001101011 !
b1111001101011 +
0%
b11011001110001 $
b11011001110001 )
b1110011111111010 #
b1110011111111010 (
b10100000 '
#322000
0"
b1010001100101110 !
b1010001100101110 +
1%
b1110001100110001 $
b1110001100110001 )
b1000011001011111 #
b1000011001011111 (
b10100001 '
#324000
b1011101110001100 !
b1011101110001100 +
0%
b101100111110000 $
b101100111110000 )
b110000110011100 #
b110000110011100 (
b10100010 '
#326000
b1000110101111111 !
b1000110101111111 +
0"
1%
b1111111010100010 $
b1111111010100010 )
b1000110000100001 #
b1000110000100001 (
b10100011 '
#328000
1"
b1001110101001001 !
b1001110101001001 +
b1001101100001 $
b1001101100001 )
b1011000010101010 #
b1011000010101010 (
b10100100 '
#330000
b1111001001011010 !
b1111001001011010 +
0"
0%
b101101000101001 $
b101101000101001 )
b1001100000110001 #
b1001100000110001 (
b10100101 '
#332000
b1011000111010011 !
b1011000111010011 +
1"
1%
b10011101101010 $
b10011101101010 )
b1101100100111101 #
b1101100100111101 (
b10100110 '
#334000
b110001110110001 !
b110001110110001 +
b10101100111110 $
b10101100111110 )
b1000111011101111 #
b1000111011101111 (
b10100111 '
#336000
b1111000111101 !
b1111000111101 +
b10101001001000 $
b10101001001000 )
b100100010000101 #
b100100010000101 (
b10101000 '
#338000
b100101011011101 !
b100101011011101 +
0%
b110101110111100 $
b110101110111100 )
b1101111100100001 #
b1101111100100001 (
b10101001 '
#340000
b1100101000011101 !
b1100101000011101 +
0"
1%
b110111101010110 $
b110111101010110 )
b11100101110011 #
b11100101110011 (
b10101010 '
#342000
b100111101011010 !
b100111101011010 +
1"
0%
b1011011000001111 $
b1011011000001111 )
b1001100101001011 #
b1001100101001011 (
b10101011 '
#344000
b100000110110 !
b100000110110 +
b1101100001110100 $
b1101100001110100 )
b10111111000010 #
b10111111000010 (
b10101100 '
#346000
b1000110000000110 !
b1000110000000110 +
0"
b10101100000001 $
b10101100000001 )
b110000100000101 #
b110000100000101 (
b10101101 '
#348000
b1010011010110011 !
b1010011010110011 +
b101111100010010 $
b101111100010010 )
b100011110100001 #
b100011110100001 (
b10101110 '
#350000
b1111001001110101 !
b1111001001110101 +
b1101111111110010 $
b1101111111110010 )
b1001010000011 #
b1001010000011 (
b10101111 '
#352000
b11110110001100 !
b11110110001100 +
1%
b1101100000100011 $
b1101100000100011 )
b1010110101111 #
b1010110101111 (
b10110000 '
#354000
1"
b100010100111011 !
b100010100111011 +
b101100100000110 $
b101100100000110 )
b1001111001000001 #
b1001111001000001 (
b10110001 '
#356000
b101111000010001 !
b101111000010001 +
b11001100011110 $
b11001100011110 )
b1001000100101111 #
b1001000100101111 (
b10110010 '
#358000
b1000100111000001 !
b1000100111000001 +
0%
b1010111010110111 $
b1010111010110111 )
b1101101100001010 #
b1101101100001010 (
b10110011 '
#360000
b101110110100001 !
b101110110100001 +
b1001100011111100 $
b1001100011111100 )
b1100010010100101 #
b1100010010100101 (
b10110100 '
#362000
b111100100001001 !
b111100100001001 +
0"
1%
b1001000100111100 $
b1001000100111100 )
b101001000101 #
b101001000101 (
b10110101 '
#364000
b11001001100001 !
b11001001100001 +
1"
0%
b1101100101111100 $
b1101100101111100 )
b101100011100101 #
b101100011100101 (
b10110110 '
#366000
b1000000110100 !
b1000000110100 +
1"
1%
b101111110011011 $
b101111110011011 )
b110111111001111 #
b110111111001111 (
b10110111 '
#368000
b11101011010100 !
b11101011010100 +
0%
b100000111010100 $
b100000111010100 )
b1111100100000000 #
b1111100100000000 (
b10111000 '
#370000
b110101010110 !
b110101010110 +
1%
b11111110111111 $
b11111110111111 )
b100110100010101 #
b100110100010101 (
b10111001 '
#372000
0"
b1111100100000111 !
b1111100100000111 +
b1100000111100111 $
b1100000111100111 )
b1011101011101110 #
b1011101011101110 (
b10111010 '
#374000
b1011000101001101 !
b1011000101001101 +
b1100001100100111 $
b1100001100100111 )
b111010001110100 #
b111010001110100 (
b10111011 '
#376000
b110101111011 !
b110101111011 +
1"
0%
b100101010001011 $
b100101010001011 )
b1100001011110000 #
b1100001011110000 (
b10111100 '
#378000
0"
b1100101010100001 !
b1100101010100001 +
1%
b1110100110001111 $
b1110100110001111 )
b1011010000110000 #
b1011010000110000 (
b10111101 '
