FSM(traffic light)/traffic_light.v
// FSM+counter 10/29 finished
`timescale 1ns/10ps
module Traffic_light(R1G, R1Y, R1R, R2G, R2Y, R2R, FG, FY, FR, clk, rst_n, c);

input clk, rst_n, c;
output R1G, R1Y, R1R, R2G, R2Y, R2R, FG, FY, FR;
wire tg1, tg2, ty; // the signal of the
reg ST_o, ST; // start timer(counter)
reg [2:0] state, next_state;
parameter S0 = 3'b000,
          S1 = 3'b001,
          S2 = 3'b010,
          S3 = 3'b011,
          S4 = 3'b100,
          S5 = 3'b101;
reg [4:0] counter;
// output logic (combinational)
// R1: road 1, R2: road 2, F: farmroad
// G: green light, Y: yellow light, R: red light
assign R1G = (state == S0);
assign R1Y = (state == S1);
assign R1R = (state == S2) || (state == S3) || (state == S4) || (state == S5);
assign R2G = (state == S2);
assign R2Y = (state == S3);
assign R2R = (state == S0) || (state == S1) || (state == S4) || (state == S5);
assign FG  = (state == S4);
assign FY  = (state == S5);
assign FR  = (state == S0) || (state == S1) || (state == S2) || (state == S3);

// define the time of each light
assign tg1 = (counter == 5'd30) ? 1 : 0; // green light of road1/road2
assign tg2 = (counter == 5'd15) ? 1 : 0; // green light of farmload
assign ty  = (counter == 5'd5)  ? 1 : 0; // yellow light of all roads
// assign tf  = (counter == 5'd15) ? 1 : 0; // green light of farmroad

always@(posedge clk or negedge rst_n) begin // state register (sequential) + counter
    if(!rst_n) begin
        state <= S0;
        ST_o <= 0;
        counter <= 1;
    end 
    else begin
        state <= next_state;
        ST_o <= ST;    
        // if((state == S0) || (state == S1) || (state == S2) || (state == S3) || (state == S4) || (state == S5)) begin
        if(tg1 && (state == S0 || state == S2)) begin   
            counter <= 1;
            //counter <= counter + 1;
        end
        else if(tg2 && state == S4) begin
            counter <= 1;
        end
        else if(ty && (state == S1 || state == S3 || state == S5)) begin
            counter <= 1;
        end
        else begin
            counter <= counter + 1;
        end
    end // end else
end // end always



always@(*) begin // next state logic (combinational)
    case(state)
        S0: begin
            if(tg1) begin
                next_state = S1;
                ST = 1;
            end
            else begin
                next_state = S0;
                ST = 0;
            end
        end
        S1: begin
            if(ty & !c) begin
                next_state = S2;
                ST = 1;
            end
            else if(ty & c) begin
                next_state = S4;
                ST = 1;
            end
            else begin
                next_state = S1;
                ST = 0;
            end
        end
        S2: begin
            if(tg1) begin
                next_state = S3;
                ST = 1;
            end
            else begin
                next_state = S2;
                ST = 0;
            end
        end
        S3: begin
            if(ty & !c) begin
                next_state = S0;
                ST = 1;
            end
            else if(ty & c) begin
                next_state = S4;
                ST = 1;
            end
            else begin
                next_state = S3;
                ST = 0;
            end
        end
        S4: begin
            if(tg2 | !c) begin
                next_state = S5;
                ST = 1;
            end
            else begin
                next_state = S4;
                ST = 0;
            end
        end
        S5: begin
            if(ty) begin
                next_state = S0;
                ST = 1;
            end
            else begin
                next_state = S5;
                ST = 0;
            end
        end
        default: begin
            next_state = S0;
        end
    endcase
end // end always

endmodule

// always @(posedge clk or negedge rst_n) begin // counter
//     if (!rst_n) begin 
//         counter <= 5'b0;
//         TL <= 1'b0;
//         Ty <= 1'b0;
//     end
//     else begin    
//         if (counter == 5'd30) begin// long time interval: 30s
//             counter <= 5'd0;
//             TL <= 1'b1;
//         end
//         else if (counter == 5'd10) begin// short time interval: 10s
//             counter <= 5'd0;
//             Ty <= 1'b1;
//         end
//         else 
//             counter <= counter + 1'b1;
//     end
// end

FSM(traffic light)/testbench.v
`include "./traffic_light.v"
`timescale 1ns/10ps
`define INTERVAL 10
module testbench();

reg clk, rst_n, c;
wire R1G, R1Y, R1R, R2G, R2Y, R2R, FG, FY, FR;

Traffic_light T1(
    .c(c),
    .clk(clk),
    .rst_n(rst_n),
    .R1G(R1G),
    .R1Y(R1Y),
    .R1R(R1R),
    .R2G(R2G),
    .R2Y(R2Y),
    .R2R(R2R),
    .FG(FG),
    .FY(FY),
    .FR(FR)
);

// clock generator
always #(`INTERVAL/2) clk = ~clk;

initial begin
    clk = 0;
    rst_n = 1'b0;
    c = 0;
    #`INTERVAL rst_n = 1;
    // #`INTERVAL
    // #`INTERVAL
    // #`INTERVAL
    // #`INTERVAL
    // #`INTERVAL
    // #`INTERVAL
    // #`INTERVAL
    # 1000 c = 1;
    # 200  c = 0;
    # 1000 c = 1;
    # 100 $finish;
end

// initial begin
//     $fsdbDumpfile("counter.fsdb");
//     $fsdbDumpvars;
// end

initial begin
    $dumpfile("FSM.vcd");
    $dumpvars;
end

endmodule

FSM(traffic light)/FSM.vcd
$date
	Thu Oct 29 22:15:49 2020
$end
$version
	Icarus Verilog
$end
$timescale
	10ps
$end
$scope module testbench $end
$var wire 1 ! R2Y $end
$var wire 1 " R2R $end
$var wire 1 # R2G $end
$var wire 1 $ R1Y $end
$var wire 1 % R1R $end
$var wire 1 & R1G $end
$var wire 1 ' FY $end
$var wire 1 ( FR $end
$var wire 1 ) FG $end
$var reg 1 * c $end
$var reg 1 + clk $end
$var reg 1 , rst_n $end
$scope module T1 $end
$var wire 1 ( FR $end
$var wire 1 % R1R $end
$var wire 1 " R2R $end
$var wire 1 * c $end
$var wire 1 + clk $end
$var wire 1 , rst_n $end
$var wire 1 - ty $end
$var wire 1 . tg2 $end
$var wire 1 / tg1 $end
$var wire 1 ! R2Y $end
$var wire 1 # R2G $end
$var wire 1 $ R1Y $end
$var wire 1 & R1G $end
$var wire 1 ' FY $end
$var wire 1 ) FG $end
$var reg 1 0 ST $end
$var reg 1 1 ST_o $end
$var reg 5 2 counter [4:0] $end
$var reg 3 3 next_state [2:0] $end
$var reg 3 4 state [2:0] $end
$upscope $end
$upscope $end
$enddefinitions $end
#0
$dumpvars
b0 4
b0 3
b1 2
01
00
0/
0.
0-
0,
0+
0*
0)
1(
0'
1&
0%
0$
0#
1"
0!
$end
#500
1+
#1000
0+
1,
#1500
b10 2
1+
#2000
0+
#2500
b11 2
1+
#3000
0+
#3500
b100 2
1+
#4000
0+
#4500
1-
b101 2
1+
#5000
0+
#5500
0-
b110 2
1+
#6000
0+
#6500
b111 2
1+
#7000
0+
#7500
b1000 2
1+
#8000
0+
#8500
b1001 2
1+
#9000
0+
#9500
b1010 2
1+
#10000
0+
#10500
b1011 2
1+
#11000
0+
#11500
b1100 2
1+
#12000
0+
#12500
b1101 2
1+
#13000
0+
#13500
b1110 2
1+
#14000
0+
#14500
1.
b1111 2
1+
#15000
0+
#15500
0.
b10000 2
1+
#16000
0+
#16500
b10001 2
1+
#17000
0+
#17500
b10010 2
1+
#18000
0+
#18500
b10011 2
1+
#19000
0+
#19500
b10100 2
1+
#20000
0+
#20500
b10101 2
1+
#21000
0+
#21500
b10110 2
1+
#22000
0+
#22500
b10111 2
1+
#23000
0+
#23500
b11000 2
1+
#24000
0+
#24500
b11001 2
1+
#25000
0+
#25500
b11010 2
1+
#26000
0+
#26500
b11011 2
1+
#27000
0+
#27500
b11100 2
1+
#28000
0+
#28500
b11101 2
1+
#29000
0+
#29500
10
b1 3
1/
b11110 2
1+
#30000
0+
#30500
0/
00
b1 2
11
0&
1$
b1 4
1+
#31000
0+
#31500
b10 2
01
1+
#32000
0+
#32500
b11 2
1+
#33000
0+
#33500
b100 2
1+
#34000
0+
#34500
10
b10 3
1-
b101 2
1+
#35000
0+
#35500
1%
0"
0-
00
b1 2
11
0$
1#
b10 4
1+
#36000
0+
#36500
b10 2
01
1+
#37000
0+
#37500
b11 2
1+
#38000
0+
#38500
b100 2
1+
#39000
0+
#39500
1-
b101 2
1+
#40000
0+
#40500
0-
b110 2
1+
#41000
0+
#41500
b111 2
1+
#42000
0+
#42500
b1000 2
1+
#43000
0+
#43500
b1001 2
1+
#44000
0+
#44500
b1010 2
1+
#45000
0+
#45500
b1011 2
1+
#46000
0+
#46500
b1100 2
1+
#47000
0+
#47500
b1101 2
1+
#48000
0+
#48500
b1110 2
1+
#49000
0+
#49500
1.
b1111 2
1+
#50000
0+
#50500
0.
b10000 2
1+
#51000
0+
#51500
b10001 2
1+
#52000
0+
#52500
b10010 2
1+
#53000
0+
#53500
b10011 2
1+
#54000
0+
#54500
b10100 2
1+
#55000
0+
#55500
b10101 2
1+
#56000
0+
#56500
b10110 2
1+
#57000
0+
#57500
b10111 2
1+
#58000
0+
#58500
b11000 2
1+
#59000
0+
#59500
b11001 2
1+
#60000
0+
#60500
b11010 2
1+
#61000
0+
#61500
b11011 2
1+
#62000
0+
#62500
b11100 2
1+
#63000
0+
#63500
b11101 2
1+
#64000
0+
#64500
10
b11 3
1/
b11110 2
1+
#65000
0+
#65500
0/
00
b1 2
11
0#
1!
b11 4
1+
#66000
0+
#66500
b10 2
01
1+
#67000
0+
#67500
b11 2
1+
#68000
0+
#68500
b100 2
1+
#69000
0+
#69500
10
b0 3
1-
b101 2
1+
#70000
0+
#70500
0%
1"
0-
00
1(
b1 2
11
1&
0!
b0 4
1+
#71000
0+
#71500
b10 2
01
1+
#72000
0+
#72500
b11 2
1+
#73000
0+
#73500
b100 2
1+
#74000
0+
#74500
1-
b101 2
1+
#75000
0+
#75500
0-
b110 2
1+
#76000
0+
#76500
b111 2
1+
#77000
0+
#77500
b1000 2
1+
#78000
0+
#78500
b1001 2
1+
#79000
0+
#79500
b1010 2
1+
#80000
0+
#80500
b1011 2
1+
#81000
0+
#81500
b1100 2
1+
#82000
0+
#82500
b1101 2
1+
#83000
0+
#83500
b1110 2
1+
#84000
0+
#84500
1.
b1111 2
1+
#85000
0+
#85500
0.
b10000 2
1+
#86000
0+
#86500
b10001 2
1+
#87000
0+
#87500
b10010 2
1+
#88000
0+
#88500
b10011 2
1+
#89000
0+
#89500
b10100 2
1+
#90000
0+
#90500
b10101 2
1+
#91000
0+
#91500
b10110 2
1+
#92000
0+
#92500
b10111 2
1+
#93000
0+
#93500
b11000 2
1+
#94000
0+
#94500
b11001 2
1+
#95000
0+
#95500
b11010 2
1+
#96000
0+
#96500
b11011 2
1+
#97000
0+
#97500
b11100 2
1+
#98000
0+
#98500
b11101 2
1+
#99000
0+
#99500
10
b1 3
1/
b11110 2
1+
#100000
0+
#100500
0/
00
b1 2
11
0&
1$
b1 4
1+
#101000
0+
1*
#101500
b10 2
01
1+
#102000
0+
#102500
b11 2
1+
#103000
0+
#103500
b100 2
1+
#104000
0+
#104500
10
b100 3
1-
b101 2
1+
#105000
0+
#105500
0(
0-
1%
00
b1 2
11
0$
1)
b100 4
1+
#106000
0+
#106500
b10 2
01
1+
#107000
0+
#107500
b11 2
1+
#108000
0+
#108500
b100 2
1+
#109000
0+
#109500
1-
b101 2
1+
#110000
0+
#110500
0-
b110 2
1+
#111000
0+
#111500
b111 2
1+
#112000
0+
#112500
b1000 2
1+
#113000
0+
#113500
b1001 2
1+
#114000
0+
#114500
b1010 2
1+
#115000
0+
#115500
b1011 2
1+
#116000
0+
#116500
b1100 2
1+
#117000
0+
#117500
b1101 2
1+
#118000
0+
#118500
b1110 2
1+
#119000
0+
#119500
10
b101 3
1.
b1111 2
1+
#120000
0+
#120500
0.
00
b1 2
11
0)
1'
b101 4
1+
#121000
0+
0*
#121500
b10 2
01
1+
#122000
0+
#122500
b11 2
1+
#123000
0+
#123500
b100 2
1+
#124000
0+
#124500
10
b0 3
1-
b101 2
1+
#125000
0+
#125500
1(
0-
00
0%
1"
b1 2
11
1&
0'
b0 4
1+
#126000
0+
#126500
b10 2
01
1+
#127000
0+
#127500
b11 2
1+
#128000
0+
#128500
b100 2
1+
#129000
0+
#129500
1-
b101 2
1+
#130000
0+
#130500
0-
b110 2
1+
#131000
0+
#131500
b111 2
1+
#132000
0+
#132500
b1000 2
1+
#133000
0+
#133500
b1001 2
1+
#134000
0+
#134500
b1010 2
1+
#135000
0+
#135500
b1011 2
1+
#136000
0+
#136500
b1100 2
1+
#137000
0+
#137500
b1101 2
1+
#138000
0+
#138500
b1110 2
1+
#139000
0+
#139500
1.
b1111 2
1+
#140000
0+
#140500
0.
b10000 2
1+
#141000
0+
#141500
b10001 2
1+
#142000
0+
#142500
b10010 2
1+
#143000
0+
#143500
b10011 2
1+
#144000
0+
#144500
b10100 2
1+
#145000
0+
#145500
b10101 2
1+
#146000
0+
#146500
b10110 2
1+
#147000
0+
#147500
b10111 2
1+
#148000
0+
#148500
b11000 2
1+
#149000
0+
#149500
b11001 2
1+
#150000
0+
#150500
b11010 2
1+
#151000
0+
#151500
b11011 2
1+
#152000
0+
#152500
b11100 2
1+
#153000
0+
#153500
b11101 2
1+
#154000
0+
#154500
10
b1 3
1/
b11110 2
1+
#155000
0+
#155500
0/
00
b1 2
11
0&
1$
b1 4
1+
#156000
0+
#156500
b10 2
01
1+
#157000
0+
#157500
b11 2
1+
#158000
0+
#158500
b100 2
1+
#159000
0+
#159500
10
b10 3
1-
b101 2
1+
#160000
0+
#160500
1%
0"
0-
00
b1 2
11
0$
1#
b10 4
1+
#161000
0+
#161500
b10 2
01
1+
#162000
0+
#162500
b11 2
1+
#163000
0+
#163500
b100 2
1+
#164000
0+
#164500
1-
b101 2
1+
#165000
0+
#165500
0-
b110 2
1+
#166000
0+
#166500
b111 2
1+
#167000
0+
#167500
b1000 2
1+
#168000
0+
#168500
b1001 2
1+
#169000
0+
#169500
b1010 2
1+
#170000
0+
#170500
b1011 2
1+
#171000
0+
#171500
b1100 2
1+
#172000
0+
#172500
b1101 2
1+
#173000
0+
#173500
b1110 2
1+
#174000
0+
#174500
1.
b1111 2
1+
#175000
0+
#175500
0.
b10000 2
1+
#176000
0+
#176500
b10001 2
1+
#177000
0+
#177500
b10010 2
1+
#178000
0+
#178500
b10011 2
1+
#179000
0+
#179500
b10100 2
1+
#180000
0+
#180500
b10101 2
1+
#181000
0+
#181500
b10110 2
1+
#182000
0+
#182500
b10111 2
1+
#183000
0+
#183500
b11000 2
1+
#184000
0+
#184500
b11001 2
1+
#185000
0+
#185500
b11010 2
1+
#186000
0+
#186500
b11011 2
1+
#187000
0+
#187500
b11100 2
1+
#188000
0+
#188500
b11101 2
1+
#189000
0+
#189500
10
b11 3
1/
b11110 2
1+
#190000
0+
#190500
0/
00
b1 2
11
0#
1!
b11 4
1+
#191000
0+
#191500
b10 2
01
1+
#192000
0+
#192500
b11 2
1+
#193000
0+
#193500
b100 2
1+
#194000
0+
#194500
10
b0 3
1-
b101 2
1+
#195000
0+
#195500
0%
1"
0-
00
1(
b1 2
11
1&
0!
b0 4
1+
#196000
0+
#196500
b10 2
01
1+
#197000
0+
#197500
b11 2
1+
#198000
0+
#198500
b100 2
1+
#199000
0+
#199500
1-
b101 2
1+
#200000
0+
#200500
0-
b110 2
1+
#201000
0+
#201500
b111 2
1+
#202000
0+
#202500
b1000 2
1+
#203000
0+
#203500
b1001 2
1+
#204000
0+
#204500
b1010 2
1+
#205000
0+
#205500
b1011 2
1+
#206000
0+
#206500
b1100 2
1+
#207000
0+
#207500
b1101 2
1+
#208000
0+
#208500
b1110 2
1+
#209000
0+
#209500
1.
b1111 2
1+
#210000
0+
#210500
0.
b10000 2
1+
#211000
0+
#211500
b10001 2
1+
#212000
0+
#212500
b10010 2
1+
#213000
0+
#213500
b10011 2
1+
#214000
0+
#214500
b10100 2
1+
#215000
0+
#215500
b10101 2
1+
#216000
0+
#216500
b10110 2
1+
#217000
0+
#217500
b10111 2
1+
#218000
0+
#218500
b11000 2
1+
#219000
0+
#219500
b11001 2
1+
#220000
0+
#220500
b11010 2
1+
#221000
0+
1*
#221500
b11011 2
1+
#222000
0+
#222500
b11100 2
1+
#223000
0+
#223500
b11101 2
1+
#224000
0+
#224500
10
b1 3
1/
b11110 2
1+
#225000
0+
#225500
0/
00
b1 2
11
0&
1$
b1 4
1+
#226000
0+
#226500
b10 2
01
1+
#227000
0+
#227500
b11 2
1+
#228000
0+
#228500
b100 2
1+
#229000
0+
#229500
10
b100 3
1-
b101 2
1+
#230000
0+
#230500
0(
0-
1%
00
b1 2
11
0$
1)
b100 4
1+
