16bit_adder_subtractor/Structure/halfadder.v
module Halfadder(
    carry,
    sum,
    a,
    b
);

input a, b;
output carry, sum;

and (carry, a, b);

xor (sum, a, b);

endmodule

counter/Structure/fulladder.v
`include "./halfadder.v"
module Fulladder(
    cout,
    sum,
    a,
    b,
    cin
);

input a, b, cin;
output cout, sum;

Halfadder H1(.a(a), .b(b), .carry(c1), .sum(s1));
Halfadder H2(.a(cin), .b(s1), .carry(c2), .sum(sum));
or (cout, c1, c2);


endmodule

counter/Structure/5bit_rca.v
`include "./fulladder.v"
`timescale 1ns/10ps

module RCA_5bit(a, b, cin, sum, cout);

input [4:0] a, b;
input cin;
output [4:0] sum;
output cout;





Fulladder F1( .a(a[0]), .b(b[0]), .cin(cin), .sum(sum[0]), .cout(c1) );
Fulladder F2( .a(a[1]), .b(b[1]), .cin(c1), .sum(sum[1]), .cout(c2) );
Fulladder F3( .a(a[2]), .b(b[2]), .cin(c2), .sum(sum[2]), .cout(c3) );
Fulladder F4( .a(a[3]), .b(b[3]), .cin(c3), .sum(sum[3]), .cout(c4) );
Fulladder F5( .a(a[4]), .b(b[4]), .cin(c4), .sum(sum[4]), .cout(cout) );



endmodule

counter/Structure/5bit_subadd.v
`timescale 1ns/10ps
`include "./5bit_rca.v"

module Subadd_5bit(a, b, mode, sum, cout);

input [4:0] a, b;
input mode;
output [4:0] sum;
output cout;

wire [4:0] y;
// do 1's complement
xor x1(y[0], mode, b[0]);
xor x2(y[1], mode, b[1]);
xor x3(y[2], mode, b[2]);
xor x4(y[3], mode, b[3]);
xor x5(y[4], mode, b[4]);

RCA_5bit R1(
    .a(a),
    .b(b),
    .cin(mode),
    .sum(sum),
    .cout(cout)
);


endmodule

counter/Structure/DFF_asyncR.v
`timescale 1ns/10ps
// D type FF with asynchronous reset
// reset is negative edge trigger
module DFF_asyncReset(q, d, clk, rst_n);
input d, clk, rst_n;
output q;


nand n1(o0, o3, o1);
nand n2(o1, o0, clk, rst_n);
nand n3(o2, o1, clk, o3);
nand n4(o3, o2, d, rst_n);
nand n5(q, o1, q_);
nand n6(q_, q, o2, rst_n);




endmodule

counter/Structure/DFF_5bit.v
`include "./DFF_asyncR.v"
`timescale 1ns/10ps

module DFF_5bit(q, d, clk, rst_n);

input [4:0] d;
input clk, rst_n;
output [4:0] q;

DFF_asyncReset D1(
    .q(q[0]),
    .d(d[0]),
    .clk(clk),
    .rst_n(rst_n)
);

DFF_asyncReset D2(
    .q(q[1]),
    .d(d[1]),
    .clk(clk),
    .rst_n(rst_n)
);

DFF_asyncReset D3(
    .q(q[2]),
    .d(d[2]),
    .clk(clk),
    .rst_n(rst_n)
);

DFF_asyncReset D4(
    .q(q[3]),
    .d(d[3]),
    .clk(clk),
    .rst_n(rst_n)
);

DFF_asyncReset D5(
    .q(q[4]),
    .d(d[4]),
    .clk(clk),
    .rst_n(rst_n)
);


endmodule

counter/Structure/Encoder.v
`timescale 1ns/10ps

module Encoder(a, b, c, o);
input a, b, c;
output [4:0] o;

// nor (n1, a, b);
// nor (n2, a, c);
// nor (n2, n1, a);
// nor (o[1], n1, 0);
// nor (o[0], n2, n2);

and (o[4], 0, a);
and (o[3], 0, a);
and (o[2], 0, a);
buf (o[1], b);
buf (o[0], c);



endmodule

counter/Structure/IF.v
`timescale 1ns/10ps

module IF(a, mode, Y);
input [4:0] a;
input mode;
output [1:0] Y;
wire H, L;
wire [4:0] a_;
// if a == 30 (11110)
not (a_[0], a[0]);
not (a_[1], a[1]);
not (a_[2], a[2]);
not (a_[3], a[3]);
not (a_[4], a[4]);
not (mode_, mode);
and (H, a[4], a[3], a[2], a[1], a_[0], mode_);
and (L, a_[4], a_[3], a_[2], a_[1], a_[0], mode);
or (Y[1], H, L);
nor (Y[0], H, L);

// if a == 0 (00000)
// not (b_[0], a[0]);
// not (b_[1], a[1]);
// not (b_[2], a[2]);
// not (b_[3], a[3]);
// not (b_[4], a[4]);
// and (B, b_[4], b_[3], b_[2], b_[1], b_[0]);
// and (m1, B, mode);


// or (T, A, B); // repeat

endmodule

counter/Structure/counter.v
`include "./IF.v"
`include "./Encoder.v"
`include "./DFF_5bit.v"
`include "./5bit_subadd.v"
`timescale 1ns/10ps

module Syncounter(mode, clk, rst_n, counter);
input mode, clk, rst_n; // mode = 0: count 0 -> 30, mode = 1: count 30 -> 0
output [4:0] counter;
wire [4:0] sum, O; 
wire [1:0] W;

IF I1(
    .a(counter),
    .mode(mode),
    .Y(W)
);

Encoder E1(
    .a(1'b0),
    .b(W[1]),
    .c(W[0]),
    .o(O)
);

DFF_5bit D1(
    .q(counter),
    .d(sum),
    .clk(clk),
    .rst_n(rst_n)
);

Subadd_5bit R1(
    .a(counter), 
    .b(O), 
    .mode(mode), 
    .sum(sum), 
    .cout()
);



// Carrylookahead C1(
//     .a(counter),
//     .b(5'b1), // mode = 1: -1, mode = 0: +1
//     .cin(mode),
//     .sum(sum),
//     .cout()
// );


endmodule

counter/Structure/testbench.v
`include "./counter.v"
`timescale 1ns/10ps
`define clkPeriod 20

module testbench();

reg mode, clk, rst_n;
wire [4:0] counter;

Syncounter S1(
    .mode(mode),
    .clk(clk),
    .rst_n(rst_n),
    .counter(counter)
);

// clock generator
always #(`clkPeriod/2) clk = ~clk;

initial begin
    rst_n = 0;
    clk = 0;
    mode = 0;
    # 5   rst_n = 1;
    # 107 rst_n = 0; // check asynchronous reset
    # 23  rst_n = 1;
    # 660 mode = 1; // check counter in mode 1
    # 702 rst_n = 0; // check counter in mode 0
    # 28  rst_n = 1; mode = 0; // check asynchronous reset
    # 600 mode = 1;
    # 600 $finish;

end

// generate waveform
initial begin
    $dumpfile("counter.vcd");
    $dumpvars;
end

// initial begin
//     $fsdbDumpfile("counter.fsdb");
//     $fsdbDumpvars;
// end


endmodule

counter/Structure/counter.vcd
$date
	Fri Oct 23 10:20:37 2020
$end
$version
	Icarus Verilog
$end
$timescale
	10ps
$end
$scope module testbench $end
$var wire 5 ! counter [4:0] $end
$var reg 1 " clk $end
$var reg 1 # mode $end
$var reg 1 $ rst_n $end
$scope module S1 $end
$var wire 1 " clk $end
$var wire 1 # mode $end
$var wire 1 $ rst_n $end
$var wire 5 % sum [4:0] $end
$var wire 5 & counter [4:0] $end
$var wire 2 ' W [1:0] $end
$var wire 5 ( O [4:0] $end
$scope module D1 $end
$var wire 1 " clk $end
$var wire 1 $ rst_n $end
$var wire 5 ) q [4:0] $end
$var wire 5 * d [4:0] $end
$scope module D1 $end
$var wire 1 " clk $end
$var wire 1 + d $end
$var wire 1 , o0 $end
$var wire 1 - o1 $end
$var wire 1 . o2 $end
$var wire 1 / o3 $end
$var wire 1 0 q $end
$var wire 1 1 q_ $end
$var wire 1 $ rst_n $end
$upscope $end
$scope module D2 $end
$var wire 1 " clk $end
$var wire 1 2 d $end
$var wire 1 3 o0 $end
$var wire 1 4 o1 $end
$var wire 1 5 o2 $end
$var wire 1 6 o3 $end
$var wire 1 7 q $end
$var wire 1 8 q_ $end
$var wire 1 $ rst_n $end
$upscope $end
$scope module D3 $end
$var wire 1 " clk $end
$var wire 1 9 d $end
$var wire 1 : o0 $end
$var wire 1 ; o1 $end
$var wire 1 < o2 $end
$var wire 1 = o3 $end
$var wire 1 > q $end
$var wire 1 ? q_ $end
$var wire 1 $ rst_n $end
$upscope $end
$scope module D4 $end
$var wire 1 " clk $end
$var wire 1 @ d $end
$var wire 1 A o0 $end
$var wire 1 B o1 $end
$var wire 1 C o2 $end
$var wire 1 D o3 $end
$var wire 1 E q $end
$var wire 1 F q_ $end
$var wire 1 $ rst_n $end
$upscope $end
$scope module D5 $end
$var wire 1 " clk $end
$var wire 1 G d $end
$var wire 1 H o0 $end
$var wire 1 I o1 $end
$var wire 1 J o2 $end
$var wire 1 K o3 $end
$var wire 1 L q $end
$var wire 1 M q_ $end
$var wire 1 $ rst_n $end
$upscope $end
$upscope $end
$scope module E1 $end
$var wire 1 N a $end
$var wire 1 O b $end
$var wire 1 P c $end
$var wire 5 Q o [4:0] $end
$upscope $end
$scope module I1 $end
$var wire 1 R H $end
$var wire 1 S L $end
$var wire 5 T a [4:0] $end
$var wire 1 # mode $end
$var wire 1 U mode_ $end
$var wire 5 V a_ [4:0] $end
$var wire 2 W Y [1:0] $end
$upscope $end
$scope module R1 $end
$var wire 5 X a [4:0] $end
$var wire 5 Y b [4:0] $end
$var wire 1 # mode $end
$var wire 5 Z y [4:0] $end
$var wire 5 [ sum [4:0] $end
$var wire 1 \ cout $end
$scope module R1 $end
$var wire 5 ] a [4:0] $end
$var wire 5 ^ b [4:0] $end
$var wire 1 # cin $end
$var wire 5 _ sum [4:0] $end
$var wire 1 \ cout $end
$var wire 1 ` c4 $end
$var wire 1 a c3 $end
$var wire 1 b c2 $end
$var wire 1 c c1 $end
$scope module F1 $end
$var wire 1 d a $end
$var wire 1 e b $end
$var wire 1 # cin $end
$var wire 1 c cout $end
$var wire 1 f sum $end
$var wire 1 g s1 $end
$var wire 1 h c2 $end
$var wire 1 i c1 $end
$scope module H1 $end
$var wire 1 d a $end
$var wire 1 e b $end
$var wire 1 i carry $end
$var wire 1 g sum $end
$upscope $end
$scope module H2 $end
$var wire 1 # a $end
$var wire 1 g b $end
$var wire 1 h carry $end
$var wire 1 f sum $end
$upscope $end
$upscope $end
$scope module F2 $end
$var wire 1 j a $end
$var wire 1 k b $end
$var wire 1 c cin $end
$var wire 1 b cout $end
$var wire 1 l sum $end
$var wire 1 m s1 $end
$var wire 1 n c2 $end
$var wire 1 o c1 $end
$scope module H1 $end
$var wire 1 j a $end
$var wire 1 k b $end
$var wire 1 o carry $end
$var wire 1 m sum $end
$upscope $end
$scope module H2 $end
$var wire 1 c a $end
$var wire 1 m b $end
$var wire 1 n carry $end
$var wire 1 l sum $end
$upscope $end
$upscope $end
$scope module F3 $end
$var wire 1 p a $end
$var wire 1 q b $end
$var wire 1 b cin $end
$var wire 1 a cout $end
$var wire 1 r sum $end
$var wire 1 s s1 $end
$var wire 1 t c2 $end
$var wire 1 u c1 $end
$scope module H1 $end
$var wire 1 p a $end
$var wire 1 q b $end
$var wire 1 u carry $end
$var wire 1 s sum $end
$upscope $end
$scope module H2 $end
$var wire 1 b a $end
$var wire 1 s b $end
$var wire 1 t carry $end
$var wire 1 r sum $end
$upscope $end
$upscope $end
$scope module F4 $end
$var wire 1 v a $end
$var wire 1 w b $end
$var wire 1 a cin $end
$var wire 1 ` cout $end
$var wire 1 x sum $end
$var wire 1 y s1 $end
$var wire 1 z c2 $end
$var wire 1 { c1 $end
$scope module H1 $end
$var wire 1 v a $end
$var wire 1 w b $end
$var wire 1 { carry $end
$var wire 1 y sum $end
$upscope $end
$scope module H2 $end
$var wire 1 a a $end
$var wire 1 y b $end
$var wire 1 z carry $end
$var wire 1 x sum $end
$upscope $end
$upscope $end
$scope module F5 $end
$var wire 1 | a $end
$var wire 1 } b $end
$var wire 1 ` cin $end
$var wire 1 \ cout $end
$var wire 1 ~ sum $end
$var wire 1 !" s1 $end
$var wire 1 "" c2 $end
$var wire 1 #" c1 $end
$scope module H1 $end
$var wire 1 | a $end
$var wire 1 } b $end
$var wire 1 #" carry $end
$var wire 1 !" sum $end
$upscope $end
$scope module H2 $end
$var wire 1 ` a $end
$var wire 1 !" b $end
$var wire 1 "" carry $end
$var wire 1 ~ sum $end
$upscope $end
$upscope $end
$upscope $end
$upscope $end
$upscope $end
$upscope $end
$enddefinitions $end
#0
$dumpvars
0#"
0""
0!"
0~
0}
0|
0{
0z
0y
0x
0w
0v
0u
0t
0s
0r
0q
0p
0o
0n
0m
0l
0k
0j
0i
0h
1g
1f
1e
0d
0c
0b
0a
0`
b1 _
b1 ^
b0 ]
0\
b1 [
b1 Z
b1 Y
b0 X
b1 W
b11111 V
1U
b0 T
0S
0R
b1 Q
1P
0O
0N
1M
0L
1K
1J
1I
0H
0G
1F
0E
1D
1C
1B
0A
0@
1?
0>
1=
1<
1;
0:
09
18
07
16
15
14
03
02
11
00
1/
1.
1-
0,
1+
b1 *
b0 )
b1 (
b1 '
b0 &
b1 %
0$
0#
0"
b0 !
$end
#500
1,
0/
1$
#1000
12
1/
1l
0+
1c
b10 %
b10 *
b10 [
b10 _
0f
b11110 V
1i
0g
01
1d
b1 !
b1 &
b1 )
b1 T
b1 X
b1 ]
10
0-
05
0<
0C
0J
1"
#2000
13
0,
06
1-
15
1<
1C
1J
0"
#3000
09
1+
0r
06
0c
1f
0b
12
0i
1g
0n
b11 %
b11 *
b11 [
b11 _
1l
0d
b11101 V
1m
00
08
1j
11
b10 !
b10 &
b10 )
b10 T
b10 X
b10 ]
17
0.
04
0<
0C
0J
1"
#4000
1,
0/
1.
14
1<
1C
1J
0"
#5000
19
1r
16
1b
02
1/
1n
0l
0+
1c
b100 %
b100 *
b100 [
b100 _
0f
b11100 V
1i
0g
01
1d
b11 !
b11 &
b11 )
b11 T
b11 X
b11 ]
10
0-
04
0<
0C
0J
1"
#6000
1:
0,
03
0=
1-
14
1<
1C
1J
0"
#7000
0@
1+
0b
02
0x
0=
0c
1f
0n
0l
0a
19
0i
1g
0m
0t
b101 %
b101 *
b101 [
b101 _
1r
0d
0j
b11011 V
1s
00
07
0?
1p
11
18
b100 !
b100 &
b100 )
b100 T
b100 X
b100 ]
1>
0.
05
0;
0C
0J
1"
#8000
1,
0/
1.
15
1;
1C
1J
0"
#9000
12
1/
1l
0+
1c
b110 %
b110 *
b110 [
b110 _
0f
b11010 V
1i
0g
01
1d
b101 !
b101 &
b101 )
b101 T
b101 X
b101 ]
10
0-
05
0;
0C
0J
1"
#10000
13
0,
06
1-
15
1;
1C
1J
0"
#11000
0@
0x
0=
0a
19
1+
0t
1r
06
0c
1f
0b
12
0i
1g
0n
b111 %
b111 *
b111 [
b111 _
1l
0d
b11001 V
1m
00
08
1j
11
b110 !
b110 &
b110 )
b110 T
b110 X
b110 ]
17
0.
04
0;
0C
0J
1"
#11200
02
09
0l
b1 %
b1 *
b1 [
b1 _
0r
0m
b11111 V
0s
0j
0p
05
03
07
0<
0:
b0 !
b0 &
b0 )
b0 T
b0 X
b0 ]
0>
14
16
18
1;
1=
1?
0$
#12000
1.
15
1<
1C
1J
0"
#13000
0.
05
0<
0C
0J
1"
#13500
1$
#14000
1,
0/
1.
15
1<
1C
1J
0"
#15000
12
1/
1l
0+
1c
b10 %
b10 *
b10 [
b10 _
0f
b11110 V
1i
0g
01
1d
b1 !
b1 &
b1 )
b1 T
b1 X
b1 ]
10
0-
05
0<
0C
0J
1"
#16000
13
0,
06
1-
15
1<
1C
1J
0"
#17000
09
1+
0r
06
0c
1f
0b
12
0i
1g
0n
b11 %
b11 *
b11 [
b11 _
1l
0d
b11101 V
1m
00
08
1j
11
b10 !
b10 &
b10 )
b10 T
b10 X
b10 ]
17
0.
04
0<
0C
0J
1"
#18000
1,
0/
1.
14
1<
1C
1J
0"
#19000
19
1r
16
1b
02
1/
1n
0l
0+
1c
b100 %
b100 *
b100 [
b100 _
0f
b11100 V
1i
0g
01
1d
b11 !
b11 &
b11 )
b11 T
b11 X
b11 ]
10
0-
04
0<
0C
0J
1"
#20000
1:
0,
03
0=
1-
14
1<
1C
1J
0"
#21000
0@
1+
0b
02
0x
0=
0c
1f
0n
0l
0a
19
0i
1g
0m
0t
b101 %
b101 *
b101 [
b101 _
1r
0d
0j
b11011 V
1s
00
07
0?
1p
11
18
b100 !
b100 &
b100 )
b100 T
b100 X
b100 ]
1>
0.
05
0;
0C
0J
1"
#22000
1,
0/
1.
15
1;
1C
1J
0"
#23000
12
1/
1l
0+
1c
b110 %
b110 *
b110 [
b110 _
0f
b11010 V
1i
0g
01
1d
b101 !
b101 &
b101 )
b101 T
b101 X
b101 ]
10
0-
05
0;
0C
0J
1"
#24000
13
0,
06
1-
15
1;
1C
1J
0"
#25000
0@
0x
0=
0a
19
1+
0t
1r
06
0c
1f
0b
12
0i
1g
0n
b111 %
b111 *
b111 [
b111 _
1l
0d
b11001 V
1m
00
08
1j
11
b110 !
b110 &
b110 )
b110 T
b110 X
b110 ]
17
0.
04
0;
0C
0J
1"
#26000
1,
0/
1.
14
1;
1C
1J
0"
#27000
1@
1x
1=
1a
09
1t
0r
16
1b
02
1/
1n
0l
0+
1c
b1000 %
b1000 *
b1000 [
b1000 _
0f
b11000 V
1i
0g
01
1d
b111 !
b111 &
b111 )
b111 T
b111 X
b111 ]
10
0-
04
0;
0C
0J
1"
#28000
1A
0,
03
0:
0D
1-
14
1;
1C
1J
0"
#29000
0G
1+
0b
02
0a
09
0~
0D
0c
1f
0n
0l
0t
0r
0`
1@
0i
1g
0m
0s
0z
b1001 %
b1001 *
b1001 [
b1001 _
1x
0d
0j
0p
b10111 V
1y
00
07
0>
0F
1v
11
18
1?
b1000 !
b1000 &
b1000 )
b1000 T
b1000 X
b1000 ]
1E
0.
05
0<
0B
0J
1"
#30000
1,
0/
1.
15
1<
1B
1J
0"
#31000
12
1/
1l
0+
1c
b1010 %
b1010 *
b1010 [
b1010 _
0f
b10110 V
1i
0g
01
1d
b1001 !
b1001 &
b1001 )
b1001 T
b1001 X
b1001 ]
10
0-
05
0<
0B
0J
1"
#32000
13
0,
06
1-
15
1<
1B
1J
0"
#33000
09
1+
0r
06
0c
1f
0b
12
0i
1g
0n
b1011 %
b1011 *
b1011 [
b1011 _
1l
0d
b10101 V
1m
00
08
1j
11
b1010 !
b1010 &
b1010 )
b1010 T
b1010 X
b1010 ]
17
0.
04
0<
0B
0J
1"
#34000
1,
0/
1.
14
1<
1B
1J
0"
#35000
19
1r
16
1b
02
1/
1n
0l
0+
1c
b1100 %
b1100 *
b1100 [
b1100 _
0f
b10100 V
1i
0g
01
1d
b1011 !
b1011 &
b1011 )
b1011 T
b1011 X
b1011 ]
10
0-
04
0<
0B
0J
1"
#36000
1:
0,
03
0=
1-
14
1<
1B
1J
0"
#37000
0G
0~
0D
0`
1@
1+
0b
02
0z
1x
0=
0c
1f
0n
0l
0a
19
0i
1g
0m
0t
b1101 %
b1101 *
b1101 [
b1101 _
1r
0d
0j
b10011 V
1s
00
07
0?
1p
11
18
b1100 !
b1100 &
b1100 )
b1100 T
b1100 X
b1100 ]
1>
0.
05
0;
0B
0J
1"
#38000
1,
0/
1.
15
1;
1B
1J
0"
#39000
12
1/
1l
0+
1c
b1110 %
b1110 *
b1110 [
b1110 _
0f
b10010 V
1i
0g
01
1d
b1101 !
b1101 &
b1101 )
b1101 T
b1101 X
b1101 ]
10
0-
05
0;
0B
0J
1"
#40000
13
0,
06
1-
15
1;
1B
1J
0"
#41000
0G
0~
0D
0`
1@
0z
1x
0=
0a
19
1+
0t
1r
06
0c
1f
0b
12
0i
1g
0n
b1111 %
b1111 *
b1111 [
b1111 _
1l
0d
b10001 V
1m
00
08
1j
11
b1110 !
b1110 &
b1110 )
b1110 T
b1110 X
b1110 ]
17
0.
04
0;
0B
0J
1"
#42000
1,
0/
1.
14
1;
1B
1J
0"
#43000
1G
1~
1D
1`
0@
1z
0x
1=
1a
09
1t
0r
16
1b
02
1/
1n
0l
0+
1c
b10000 %
b10000 *
b10000 [
b10000 _
0f
b10000 V
1i
0g
01
1d
b1111 !
b1111 &
b1111 )
b1111 T
b1111 X
b1111 ]
10
0-
04
0;
0B
0J
1"
#44000
1H
0,
03
0:
0A
0K
1-
14
1;
1B
1J
0"
#45000
1+
0b
02
0a
09
0`
0@
0K
0c
1f
0n
0l
0t
0r
0z
0x
0\
1G
0i
1g
0m
0s
0y
0""
b10001 %
b10001 *
b10001 [
b10001 _
1~
0d
0j
0p
0v
b1111 V
1!"
00
07
0>
0E
0M
1|
11
18
1?
1F
b10000 !
b10000 &
b10000 )
b10000 T
b10000 X
b10000 ]
1L
0.
05
0<
0C
0I
1"
#46000
1,
0/
1.
15
1<
1C
1I
0"
#47000
12
1/
1l
0+
1c
b10010 %
b10010 *
b10010 [
b10010 _
0f
b1110 V
1i
0g
01
1d
b10001 !
b10001 &
b10001 )
b10001 T
b10001 X
b10001 ]
10
0-
05
0<
0C
0I
1"
#48000
13
0,
06
1-
15
1<
1C
1I
0"
#49000
09
1+
0r
06
0c
1f
0b
12
0i
1g
0n
b10011 %
b10011 *
b10011 [
b10011 _
1l
0d
b1101 V
1m
00
08
1j
11
b10010 !
b10010 &
b10010 )
b10010 T
b10010 X
b10010 ]
17
0.
04
0<
0C
0I
1"
#50000
1,
0/
1.
14
1<
1C
1I
0"
#51000
19
1r
16
1b
02
1/
1n
0l
0+
1c
b10100 %
b10100 *
b10100 [
b10100 _
0f
b1100 V
1i
0g
01
1d
b10011 !
b10011 &
b10011 )
b10011 T
b10011 X
b10011 ]
10
0-
04
0<
0C
0I
1"
#52000
1:
0,
03
0=
1-
14
1<
1C
1I
0"
#53000
0@
1+
0b
02
0x
0=
0c
1f
0n
0l
0a
19
0i
1g
0m
0t
b10101 %
b10101 *
b10101 [
b10101 _
1r
0d
0j
b1011 V
1s
00
07
0?
1p
11
18
b10100 !
b10100 &
b10100 )
b10100 T
b10100 X
b10100 ]
1>
0.
05
0;
0C
0I
1"
#54000
1,
0/
1.
15
1;
1C
1I
0"
#55000
12
1/
1l
0+
1c
b10110 %
b10110 *
b10110 [
b10110 _
0f
b1010 V
1i
0g
01
1d
b10101 !
b10101 &
b10101 )
b10101 T
b10101 X
b10101 ]
10
0-
05
0;
0C
0I
1"
#56000
13
0,
06
1-
15
1;
1C
1I
0"
#57000
0@
0x
0=
0a
19
1+
0t
1r
06
0c
1f
0b
12
0i
1g
0n
b10111 %
b10111 *
b10111 [
b10111 _
1l
0d
b1001 V
1m
00
08
1j
11
b10110 !
b10110 &
b10110 )
b10110 T
b10110 X
b10110 ]
17
0.
04
0;
0C
0I
1"
#58000
1,
0/
1.
14
1;
1C
1I
0"
#59000
1@
1x
1=
1a
09
1t
0r
16
1b
02
1/
1n
0l
0+
1c
b11000 %
b11000 *
b11000 [
b11000 _
0f
b1000 V
1i
0g
01
1d
b10111 !
b10111 &
b10111 )
b10111 T
b10111 X
b10111 ]
10
0-
04
0;
0C
0I
1"
#60000
1A
0,
03
0:
0D
1-
14
1;
1C
1I
0"
#61000
0K
0\
1G
1+
0b
02
0a
09
0""
1~
0D
0c
1f
0n
0l
0t
0r
0`
1@
0i
1g
0m
0s
0z
b11001 %
b11001 *
b11001 [
b11001 _
1x
0d
0j
0p
b111 V
1y
00
07
0>
0F
1v
11
18
1?
b11000 !
b11000 &
b11000 )
b11000 T
b11000 X
b11000 ]
1E
0.
05
0<
0B
0I
1"
#62000
1,
0/
1.
15
1<
1B
1I
0"
#63000
12
1/
1l
0+
1c
b11010 %
b11010 *
b11010 [
b11010 _
0f
b110 V
1i
0g
01
1d
b11001 !
b11001 &
b11001 )
b11001 T
b11001 X
b11001 ]
10
0-
05
0<
0B
0I
1"
#64000
13
0,
06
1-
15
1<
1B
1I
0"
#65000
09
1+
0r
06
0c
1f
0b
12
0i
1g
0n
b11011 %
b11011 *
b11011 [
b11011 _
1l
0d
b101 V
1m
00
08
1j
11
b11010 !
b11010 &
b11010 )
b11010 T
b11010 X
b11010 ]
17
0.
04
0<
0B
0I
1"
#66000
1,
0/
1.
14
1<
1B
1I
0"
#67000
19
1r
16
1b
02
1/
1n
0l
0+
1c
b11100 %
b11100 *
b11100 [
b11100 _
0f
b100 V
1i
0g
01
1d
b11011 !
b11011 &
b11011 )
b11011 T
b11011 X
b11011 ]
10
0-
04
0<
0B
0I
1"
#68000
1:
0,
03
0=
1-
14
1<
1B
1I
0"
#69000
0K
0\
1G
0""
1~
0D
0`
1@
1+
0b
02
0z
1x
0=
0c
1f
0n
0l
0a
19
0i
1g
0m
0t
b11101 %
b11101 *
b11101 [
b11101 _
1r
0d
0j
b11 V
1s
00
07
0?
1p
11
18
b11100 !
b11100 &
b11100 )
b11100 T
b11100 X
b11100 ]
1>
0.
05
0;
0B
0I
1"
#70000
1,
0/
1.
15
1;
1B
1I
0"
#71000
12
1/
1l
0+
1c
b11110 %
b11110 *
b11110 [
b11110 _
0f
b10 V
1i
0g
01
1d
b11101 !
b11101 &
b11101 )
b11101 T
b11101 X
b11101 ]
10
0-
05
0;
0B
0I
1"
#72000
13
0,
06
1-
15
1;
1B
1I
0"
#73000
1o
1k
0e
b10 Z
b10 ^
1K
1\
0G
b10 (
b10 Q
b10 Y
1""
0~
1D
1O
0P
1`
0@
b10 '
b10 W
1z
0x
1=
1R
1a
09
0+
1t
0r
16
0c
0f
1b
02
0i
0g
0n
b0 %
b0 *
b0 [
b0 _
0l
0d
b1 V
0m
00
08
1j
11
b11110 !
b11110 &
b11110 )
b11110 T
b11110 X
b11110 ]
17
0.
04
0;
0B
0I
1"
#74000
03
0:
0A
0H
1.
14
1;
1B
1I
0"
#75000
1+
1f
1g
0k
1e
b1 Z
b1 ^
b1 (
b1 Q
b1 Y
0O
1P
02
0a
09
0`
0@
b1 '
b1 W
0\
0G
0b
0l
0t
0r
0z
0x
0R
0""
b1 %
b1 *
b1 [
b1 _
0~
0o
0m
0s
0y
b11111 V
0!"
0j
0p
0v
0|
07
0>
0E
b0 !
b0 &
b0 )
b0 T
b0 X
b0 ]
0L
18
1?
1F
1M
0.
05
0<
0C
0J
1"
#76000
1,
0/
1.
15
1<
1C
1J
0"
#77000
12
1/
1l
0+
1c
b10 %
b10 *
b10 [
b10 _
0f
b11110 V
1i
0g
01
1d
b1 !
b1 &
b1 )
b1 T
b1 X
b1 ]
10
0-
05
0<
0C
0J
1"
#78000
13
0,
06
1-
15
1<
1C
1J
0"
#79000
09
1+
0r
06
0c
1f
0b
12
0i
1g
0n
b11 %
b11 *
b11 [
b11 _
1l
0d
b11101 V
1m
00
08
1j
11
b10 !
b10 &
b10 )
b10 T
b10 X
b10 ]
17
0.
04
0<
0C
0J
1"
#79500
1\
1""
1`
1z
1a
0@
0G
16
1t
0x
0~
1b
02
0g
1o
0m
1s
1y
1!"
0n
0l
0e
1k
1q
1w
1}
0c
1+
0U
b11110 Z
b11110 ^
0h
b1 %
b1 *
b1 [
b1 _
1f
1#
#80000
1,
0/
03
1.
14
1<
1C
1J
0"
#81000
1\
0G
1""
0~
1`
0@
1z
0x
1a
09
1n
1/
1t
0r
02
1c
0+
1b
0l
1h
b0 %
b0 *
b0 [
b0 _
0f
0o
1m
b11110 V
1g
0j
01
1d
07
b1 !
b1 &
b1 )
b1 T
b1 X
b1 ]
10
18
0-
05
0<
0C
0J
1"
#82000
0,
1-
15
1<
1C
1J
0"
#83000
0m
0\
1G
0k
1e
0""
1~
b11101 Z
b11101 ^
0`
1@
0z
1x
b10 (
b10 Q
b10 Y
0a
19
1O
0P
0t
1r
b10 '
b10 W
0b
12
1S
0n
1l
1c
0+
1h
b11110 %
b11110 *
b11110 [
b11110 _
0f
b11111 V
1g
0d
b0 !
b0 &
b0 )
b0 T
b0 X
b0 ]
00
11
0.
05
0<
0C
0J
1"
#84000
13
1:
1A
1H
06
0=
0D
0K
1.
15
1<
1C
1J
0"
#85000
0c
1+
0h
1f
1o
0g
1k
0e
b11110 Z
b11110 ^
b1 (
b1 Q
b1 Y
0O
1P
b1 '
b1 W
16
0=
0D
0S
0K
1b
02
19
1@
1G
0n
0l
1a
1r
1`
1x
1\
b11101 %
b11101 *
b11101 [
b11101 _
1~
0m
1u
0s
1{
0y
b1 V
1#"
0!"
08
1j
0?
1p
0F
1v
0M
1|
17
1>
1E
b11110 !
b11110 &
b11110 )
b11110 T
b11110 X
b11110 ]
1L
0.
04
0;
0B
0I
1"
#86000
1,
0/
03
1.
14
1;
1B
1I
0"
#87000
0=
19
1n
1/
1r
02
1c
0+
1b
0l
1h
b11100 %
b11100 *
b11100 [
b11100 _
0f
0o
1m
b10 V
1g
0j
01
1d
07
b11101 !
b11101 &
b11101 )
b11101 T
b11101 X
b11101 ]
10
18
0-
05
0;
0B
0I
1"
#88000
0,
1-
15
1;
1B
1I
0"
#89000
1=
09
0r
0b
12
0n
1l
0c
1+
0h
b11011 %
b11011 *
b11011 [
b11011 _
1f
b11 V
0g
0d
b11100 !
b11100 &
b11100 )
b11100 T
b11100 X
b11100 ]
00
11
0.
05
0;
0B
0I
1"
#90000
1,
13
0/
06
0:
1.
15
1;
1B
1I
0"
#91000
1/
06
1c
0+
12
1t
1h
0f
1b
b11010 %
b11010 *
b11010 [
b11010 _
1l
0u
1s
1g
b100 V
1o
0m
0p
01
1d
08
1j
0>
10
b11011 !
b11011 &
b11011 )
b11011 T
b11011 X
b11011 ]
17
1?
0-
04
0<
0B
0I
1"
#92000
0,
1-
14
1<
1B
1I
0"
#93000
16
02
0l
0c
1+
0h
b11001 %
b11001 *
b11001 [
b11001 _
1f
b101 V
0g
0d
b11010 !
b11010 &
b11010 )
b11010 T
b11010 X
b11010 ]
00
11
0.
04
0<
0B
0I
1"
#94000
1,
0/
03
1.
14
1<
1B
1I
0"
#95000
0D
1@
1x
1a
09
1n
1/
1t
0r
02
1c
0+
1b
0l
1h
b11000 %
b11000 *
b11000 [
b11000 _
0f
0o
1m
b110 V
1g
0j
01
1d
07
b11001 !
b11001 &
b11001 )
b11001 T
b11001 X
b11001 ]
10
18
0-
05
0<
0B
0I
1"
#96000
0,
1-
15
1<
1B
1I
0"
#97000
1D
0@
0x
0a
19
0t
1r
0b
12
0n
1l
0c
1+
0h
b10111 %
b10111 *
b10111 [
b10111 _
1f
b111 V
0g
0d
b11000 !
b11000 &
b11000 )
b11000 T
b11000 X
b11000 ]
00
11
0.
05
0<
0B
0I
1"
#98000
1,
13
1:
0/
06
0=
0A
1.
15
1<
1B
1I
0"
