16bit_adder_subtractor/Structure/halfadder.v
module Halfadder(
    carry,
    sum,
    a,
    b
);

input a, b;
output carry, sum;

and (carry, a, b);

xor (sum, a, b);

endmodule

counter/Structure/fulladder.v
`include "./halfadder.v"
module Fulladder(
    cout,
    sum,
    a,
    b,
    cin
);

input a, b, cin;
output cout, sum;

Halfadder H1(.a(a), .b(b), .carry(c1), .sum(s1));
Halfadder H2(.a(cin), .b(s1), .carry(c2), .sum(sum));
or (cout, c1, c2);


endmodule

counter/Structure/5bit_rca.v
`include "./fulladder.v"
`timescale 1ns/10ps

module RCA_5bit(a, b, cin, sum, cout);

input [4:0] a, b;
input cin;
output [4:0] sum;
output cout;





Fulladder F1( .a(a[0]), .b(b[0]), .cin(cin), .sum(sum[0]), .cout(c1) );
Fulladder F2( .a(a[1]), .b(b[1]), .cin(c1), .sum(sum[1]), .cout(c2) );
Fulladder F3( .a(a[2]), .b(b[2]), .cin(c2), .sum(sum[2]), .cout(c3) );
Fulladder F4( .a(a[3]), .b(b[3]), .cin(c3), .sum(sum[3]), .cout(c4) );
Fulladder F5( .a(a[4]), .b(b[4]), .cin(c4), .sum(sum[4]), .cout(cout) );



endmodule

counter/Structure/5bit_subadd.v
`timescale 1ns/10ps
`include "./5bit_rca.v"

module Subadd_5bit(a, b, mode, sum, cout);

input [4:0] a, b;
input mode;
output [4:0] sum;
output cout;

wire [4:0] y;
// do 1's complement
xor x1(y[0], mode, b[0]);
xor x2(y[1], mode, b[1]);
xor x3(y[2], mode, b[2]);
xor x4(y[3], mode, b[3]);
xor x5(y[4], mode, b[4]);

RCA_5bit R1(
    .a(a),
    .b(b),
    .cin(mode),
    .sum(sum),
    .cout(cout)
);


endmodule

counter/Structure/DFF_asyncR.v
`timescale 1ns/10ps
// D type FF with asynchronous reset
// reset is negative edge trigger
module DFF_asyncReset(q, d, clk, rst_n);
input d, clk, rst_n;
output q;


nand n1(o0, o3, o1);
nand n2(o1, o0, clk, rst_n);
nand n3(o2, o1, clk, o3);
nand n4(o3, o2, d, rst_n);
nand n5(q, o1, q_);
nand n6(q_, q, o2, rst_n);




endmodule

counter/Structure/DFF_5bit.v
`include "./DFF_asyncR.v"
`timescale 1ns/10ps

module DFF_5bit(q, d, clk, rst_n);

input [4:0] d;
input clk, rst_n;
output [4:0] q;

DFF_asyncReset D1(
    .q(q[0]),
    .d(d[0]),
    .clk(clk),
    .rst_n(rst_n)
);

DFF_asyncReset D2(
    .q(q[1]),
    .d(d[1]),
    .clk(clk),
    .rst_n(rst_n)
);

DFF_asyncReset D3(
    .q(q[2]),
    .d(d[2]),
    .clk(clk),
    .rst_n(rst_n)
);

DFF_asyncReset D4(
    .q(q[3]),
    .d(d[3]),
    .clk(clk),
    .rst_n(rst_n)
);

DFF_asyncReset D5(
    .q(q[4]),
    .d(d[4]),
    .clk(clk),
    .rst_n(rst_n)
);


endmodule

counter/Structure/counter.v
`include "./DFF_5bit.v"
`include "./5bit_subadd.v"
`timescale 1ns/10ps

module Syncounter(mode, clk, rst_n, counter);
input mode, clk, rst_n; // mode = 0: count 0 -> 30, mode = 1: count 30 -> 0
output [4:0] counter;
wire [4:0] sum; 


DFF_5bit D1(
    .q(counter),
    .d(sum),
    .clk(clk),
    .rst_n(rst_n)
);

Subadd_5bit R1(
    .a(counter), 
    .b(5'b1), 
    .mode(mode), 
    .sum(sum), 
    .cout()
);

// Carrylookahead C1(
//     .a(counter),
//     .b(5'b1), // mode = 1: -1, mode = 0: +1
//     .cin(mode),
//     .sum(sum),
//     .cout()
// );


endmodule

counter/Structure/testbench.v
`include "./counter.v"
`timescale 1ns/10ps
`define clkPeriod 20

module testbench();

reg mode, clk, rst_n;
wire [4:0] counter;

Syncounter S1(
    .mode(mode),
    .clk(clk),
    .rst_n(rst_n),
    .counter(counter)
);

// clock generator
always #(`clkPeriod/2) clk = ~clk;

initial begin
    rst_n = 0;
    clk = 0;
    mode = 0;
    # 5   rst_n = 1;
    # 107 rst_n = 0; // check asynchronous reset
    # 23  rst_n = 1;
    # 660 mode = 1; // check counter in mode 1
    # 702 rst_n = 0; // check counter in mode 0
    # 28  rst_n = 1; mode = 0; // check asynchronous reset
    # 600 mode = 1;
    # 600 $finish;

end

// generate waveform
initial begin
    $dumpfile("counter.vcd");
    $dumpvars;
end

// initial begin
//     $fsdbDumpfile("counter.fsdb");
//     $fsdbDumpvars;
// end


endmodule

counter/Structure/counter.vcd
$date
	Wed Oct 21 16:22:12 2020
$end
$version
	Icarus Verilog
$end
$timescale
	10ps
$end
$scope module testbench $end
$var wire 5 ! counter [4:0] $end
$var reg 1 " clk $end
$var reg 1 # mode $end
$var reg 1 $ rst_n $end
$scope module S1 $end
$var wire 1 " clk $end
$var wire 1 # mode $end
$var wire 1 $ rst_n $end
$var wire 5 % sum [4:0] $end
$var wire 5 & counter [4:0] $end
$scope module D1 $end
$var wire 1 " clk $end
$var wire 1 $ rst_n $end
$var wire 5 ' q [4:0] $end
$var wire 5 ( d [4:0] $end
$scope module D1 $end
$var wire 1 " clk $end
$var wire 1 ) d $end
$var wire 1 * o0 $end
$var wire 1 + o1 $end
$var wire 1 , o2 $end
$var wire 1 - o3 $end
$var wire 1 . q $end
$var wire 1 / q_ $end
$var wire 1 $ rst_n $end
$upscope $end
$scope module D2 $end
$var wire 1 " clk $end
$var wire 1 0 d $end
$var wire 1 1 o0 $end
$var wire 1 2 o1 $end
$var wire 1 3 o2 $end
$var wire 1 4 o3 $end
$var wire 1 5 q $end
$var wire 1 6 q_ $end
$var wire 1 $ rst_n $end
$upscope $end
$scope module D3 $end
$var wire 1 " clk $end
$var wire 1 7 d $end
$var wire 1 8 o0 $end
$var wire 1 9 o1 $end
$var wire 1 : o2 $end
$var wire 1 ; o3 $end
$var wire 1 < q $end
$var wire 1 = q_ $end
$var wire 1 $ rst_n $end
$upscope $end
$scope module D4 $end
$var wire 1 " clk $end
$var wire 1 > d $end
$var wire 1 ? o0 $end
$var wire 1 @ o1 $end
$var wire 1 A o2 $end
$var wire 1 B o3 $end
$var wire 1 C q $end
$var wire 1 D q_ $end
$var wire 1 $ rst_n $end
$upscope $end
$scope module D5 $end
$var wire 1 " clk $end
$var wire 1 E d $end
$var wire 1 F o0 $end
$var wire 1 G o1 $end
$var wire 1 H o2 $end
$var wire 1 I o3 $end
$var wire 1 J q $end
$var wire 1 K q_ $end
$var wire 1 $ rst_n $end
$upscope $end
$upscope $end
$scope module R1 $end
$var wire 5 L a [4:0] $end
$var wire 5 M b [4:0] $end
$var wire 1 # mode $end
$var wire 5 N y [4:0] $end
$var wire 5 O sum [4:0] $end
$var wire 1 P cout $end
$scope module R1 $end
$var wire 5 Q a [4:0] $end
$var wire 5 R b [4:0] $end
$var wire 1 # cin $end
$var wire 5 S sum [4:0] $end
$var wire 1 P cout $end
$var wire 1 T c4 $end
$var wire 1 U c3 $end
$var wire 1 V c2 $end
$var wire 1 W c1 $end
$scope module F1 $end
$var wire 1 X a $end
$var wire 1 Y b $end
$var wire 1 # cin $end
$var wire 1 W cout $end
$var wire 1 Z sum $end
$var wire 1 [ s1 $end
$var wire 1 \ c2 $end
$var wire 1 ] c1 $end
$scope module H1 $end
$var wire 1 X a $end
$var wire 1 Y b $end
$var wire 1 ] carry $end
$var wire 1 [ sum $end
$upscope $end
$scope module H2 $end
$var wire 1 # a $end
$var wire 1 [ b $end
$var wire 1 \ carry $end
$var wire 1 Z sum $end
$upscope $end
$upscope $end
$scope module F2 $end
$var wire 1 ^ a $end
$var wire 1 _ b $end
$var wire 1 W cin $end
$var wire 1 V cout $end
$var wire 1 ` sum $end
$var wire 1 a s1 $end
$var wire 1 b c2 $end
$var wire 1 c c1 $end
$scope module H1 $end
$var wire 1 ^ a $end
$var wire 1 _ b $end
$var wire 1 c carry $end
$var wire 1 a sum $end
$upscope $end
$scope module H2 $end
$var wire 1 W a $end
$var wire 1 a b $end
$var wire 1 b carry $end
$var wire 1 ` sum $end
$upscope $end
$upscope $end
$scope module F3 $end
$var wire 1 d a $end
$var wire 1 e b $end
$var wire 1 V cin $end
$var wire 1 U cout $end
$var wire 1 f sum $end
$var wire 1 g s1 $end
$var wire 1 h c2 $end
$var wire 1 i c1 $end
$scope module H1 $end
$var wire 1 d a $end
$var wire 1 e b $end
$var wire 1 i carry $end
$var wire 1 g sum $end
$upscope $end
$scope module H2 $end
$var wire 1 V a $end
$var wire 1 g b $end
$var wire 1 h carry $end
$var wire 1 f sum $end
$upscope $end
$upscope $end
$scope module F4 $end
$var wire 1 j a $end
$var wire 1 k b $end
$var wire 1 U cin $end
$var wire 1 T cout $end
$var wire 1 l sum $end
$var wire 1 m s1 $end
$var wire 1 n c2 $end
$var wire 1 o c1 $end
$scope module H1 $end
$var wire 1 j a $end
$var wire 1 k b $end
$var wire 1 o carry $end
$var wire 1 m sum $end
$upscope $end
$scope module H2 $end
$var wire 1 U a $end
$var wire 1 m b $end
$var wire 1 n carry $end
$var wire 1 l sum $end
$upscope $end
$upscope $end
$scope module F5 $end
$var wire 1 p a $end
$var wire 1 q b $end
$var wire 1 T cin $end
$var wire 1 P cout $end
$var wire 1 r sum $end
$var wire 1 s s1 $end
$var wire 1 t c2 $end
$var wire 1 u c1 $end
$scope module H1 $end
$var wire 1 p a $end
$var wire 1 q b $end
$var wire 1 u carry $end
$var wire 1 s sum $end
$upscope $end
$scope module H2 $end
$var wire 1 T a $end
$var wire 1 s b $end
$var wire 1 t carry $end
$var wire 1 r sum $end
$upscope $end
$upscope $end
$upscope $end
$upscope $end
$upscope $end
$upscope $end
$enddefinitions $end
#0
$dumpvars
0u
0t
0s
0r
0q
0p
0o
0n
0m
0l
0k
0j
0i
0h
0g
0f
0e
0d
0c
0b
0a
0`
0_
0^
0]
0\
1[
1Z
1Y
0X
0W
0V
0U
0T
b1 S
b1 R
b0 Q
0P
b1 O
b1 N
b1 M
b0 L
1K
0J
1I
1H
1G
0F
0E
1D
0C
1B
1A
1@
0?
0>
1=
0<
1;
1:
19
08
07
16
05
14
13
12
01
00
1/
0.
1-
1,
1+
0*
1)
b1 (
b0 '
b0 &
b1 %
0$
0#
0"
b0 !
$end
#500
1*
0-
1$
#1000
10
1-
1`
0)
1W
b10 %
b10 (
b10 O
b10 S
0Z
1]
0[
0/
1X
b1 !
b1 &
b1 '
b1 L
b1 Q
1.
0+
03
0:
0A
0H
1"
#2000
11
0*
04
1+
13
1:
1A
1H
0"
#3000
07
1)
0f
04
0W
1Z
0V
10
0]
1[
0b
b11 %
b11 (
b11 O
b11 S
1`
0X
1a
0.
06
1^
1/
b10 !
b10 &
b10 '
b10 L
b10 Q
15
0,
02
0:
0A
0H
1"
#4000
1*
0-
1,
12
1:
1A
1H
0"
#5000
17
1f
14
1V
00
1-
1b
0`
0)
1W
b100 %
b100 (
b100 O
b100 S
0Z
1]
0[
0/
1X
b11 !
b11 &
b11 '
b11 L
b11 Q
1.
0+
02
0:
0A
0H
1"
#6000
18
0*
01
0;
1+
12
1:
1A
1H
0"
#7000
0>
1)
0V
00
0l
0;
0W
1Z
0b
0`
0U
17
0]
1[
0a
0h
b101 %
b101 (
b101 O
b101 S
1f
0X
0^
1g
0.
05
0=
1d
1/
16
b100 !
b100 &
b100 '
b100 L
b100 Q
1<
0,
03
09
0A
0H
1"
#8000
1*
0-
1,
13
19
1A
1H
0"
#9000
10
1-
1`
0)
1W
b110 %
b110 (
b110 O
b110 S
0Z
1]
0[
0/
1X
b101 !
b101 &
b101 '
b101 L
b101 Q
1.
0+
03
09
0A
0H
1"
#10000
11
0*
04
1+
13
19
1A
1H
0"
#11000
0>
0l
0;
0U
17
1)
0h
1f
04
0W
1Z
0V
10
0]
1[
0b
b111 %
b111 (
b111 O
b111 S
1`
0X
1a
0.
06
1^
1/
b110 !
b110 &
b110 '
b110 L
b110 Q
15
0,
02
09
0A
0H
1"
#11200
00
07
0`
b1 %
b1 (
b1 O
b1 S
0f
0a
0g
0^
0d
03
01
05
0:
08
b0 !
b0 &
b0 '
b0 L
b0 Q
0<
12
14
16
19
1;
1=
0$
#12000
1,
13
1:
1A
1H
0"
#13000
0,
03
0:
0A
0H
1"
#13500
1$
#14000
1*
0-
1,
13
1:
1A
1H
0"
#15000
10
1-
1`
0)
1W
b10 %
b10 (
b10 O
b10 S
0Z
1]
0[
0/
1X
b1 !
b1 &
b1 '
b1 L
b1 Q
1.
0+
03
0:
0A
0H
1"
#16000
11
0*
04
1+
13
1:
1A
1H
0"
#17000
07
1)
0f
04
0W
1Z
0V
10
0]
1[
0b
b11 %
b11 (
b11 O
b11 S
1`
0X
1a
0.
06
1^
1/
b10 !
b10 &
b10 '
b10 L
b10 Q
15
0,
02
0:
0A
0H
1"
#18000
1*
0-
1,
12
1:
1A
1H
0"
#19000
17
1f
14
1V
00
1-
1b
0`
0)
1W
b100 %
b100 (
b100 O
b100 S
0Z
1]
0[
0/
1X
b11 !
b11 &
b11 '
b11 L
b11 Q
1.
0+
02
0:
0A
0H
1"
#20000
18
0*
01
0;
1+
12
1:
1A
1H
0"
#21000
0>
1)
0V
00
0l
0;
0W
1Z
0b
0`
0U
17
0]
1[
0a
0h
b101 %
b101 (
b101 O
b101 S
1f
0X
0^
1g
0.
05
0=
1d
1/
16
b100 !
b100 &
b100 '
b100 L
b100 Q
1<
0,
03
09
0A
0H
1"
#22000
1*
0-
1,
13
19
1A
1H
0"
#23000
10
1-
1`
0)
1W
b110 %
b110 (
b110 O
b110 S
0Z
1]
0[
0/
1X
b101 !
b101 &
b101 '
b101 L
b101 Q
1.
0+
03
09
0A
0H
1"
#24000
11
0*
04
1+
13
19
1A
1H
0"
#25000
0>
0l
0;
0U
17
1)
0h
1f
04
0W
1Z
0V
10
0]
1[
0b
b111 %
b111 (
b111 O
b111 S
1`
0X
1a
0.
06
1^
1/
b110 !
b110 &
b110 '
b110 L
b110 Q
15
0,
02
09
0A
0H
1"
#26000
1*
0-
1,
12
19
1A
1H
0"
#27000
1>
1l
1;
1U
07
1h
0f
14
1V
00
1-
1b
0`
0)
1W
b1000 %
b1000 (
b1000 O
b1000 S
0Z
1]
0[
0/
1X
b111 !
b111 &
b111 '
b111 L
b111 Q
1.
0+
02
09
0A
0H
1"
#28000
1?
0*
01
08
0B
1+
12
19
1A
1H
0"
#29000
0E
1)
0V
00
0U
07
0r
0B
0W
1Z
0b
0`
0h
0f
0T
1>
0]
1[
0a
0g
0n
b1001 %
b1001 (
b1001 O
b1001 S
1l
0X
0^
0d
1m
0.
05
0<
0D
1j
1/
16
1=
b1000 !
b1000 &
b1000 '
b1000 L
b1000 Q
1C
0,
03
0:
0@
0H
1"
#30000
1*
0-
1,
13
1:
1@
1H
0"
#31000
10
1-
1`
0)
1W
b1010 %
b1010 (
b1010 O
b1010 S
0Z
1]
0[
0/
1X
b1001 !
b1001 &
b1001 '
b1001 L
b1001 Q
1.
0+
03
0:
0@
0H
1"
#32000
11
0*
04
1+
13
1:
1@
1H
0"
#33000
07
1)
0f
04
0W
1Z
0V
10
0]
1[
0b
b1011 %
b1011 (
b1011 O
b1011 S
1`
0X
1a
0.
06
1^
1/
b1010 !
b1010 &
b1010 '
b1010 L
b1010 Q
15
0,
02
0:
0@
0H
1"
#34000
1*
0-
1,
12
1:
1@
1H
0"
#35000
17
1f
14
1V
00
1-
1b
0`
0)
1W
b1100 %
b1100 (
b1100 O
b1100 S
0Z
1]
0[
0/
1X
b1011 !
b1011 &
b1011 '
b1011 L
b1011 Q
1.
0+
02
0:
0@
0H
1"
#36000
18
0*
01
0;
1+
12
1:
1@
1H
0"
#37000
0E
0r
0B
0T
1>
1)
0V
00
0n
1l
0;
0W
1Z
0b
0`
0U
17
0]
1[
0a
0h
b1101 %
b1101 (
b1101 O
b1101 S
1f
0X
0^
1g
0.
05
0=
1d
1/
16
b1100 !
b1100 &
b1100 '
b1100 L
b1100 Q
1<
0,
03
09
0@
0H
1"
#38000
1*
0-
1,
13
19
1@
1H
0"
#39000
10
1-
1`
0)
1W
b1110 %
b1110 (
b1110 O
b1110 S
0Z
1]
0[
0/
1X
b1101 !
b1101 &
b1101 '
b1101 L
b1101 Q
1.
0+
03
09
0@
0H
1"
#40000
11
0*
04
1+
13
19
1@
1H
0"
#41000
0E
0r
0B
0T
1>
0n
1l
0;
0U
17
1)
0h
1f
04
0W
1Z
0V
10
0]
1[
0b
b1111 %
b1111 (
b1111 O
b1111 S
1`
0X
1a
0.
06
1^
1/
b1110 !
b1110 &
b1110 '
b1110 L
b1110 Q
15
0,
02
09
0@
0H
1"
#42000
1*
0-
1,
12
19
1@
1H
0"
#43000
1E
1r
1B
1T
0>
1n
0l
1;
1U
07
1h
0f
14
1V
00
1-
1b
0`
0)
1W
b10000 %
b10000 (
b10000 O
b10000 S
0Z
1]
0[
0/
1X
b1111 !
b1111 &
b1111 '
b1111 L
b1111 Q
1.
0+
02
09
0@
0H
1"
#44000
1F
0*
01
08
0?
0I
1+
12
19
1@
1H
0"
#45000
1)
0V
00
0U
07
0T
0>
0I
0W
1Z
0b
0`
0h
0f
0n
0l
0P
1E
0]
1[
0a
0g
0m
0t
b10001 %
b10001 (
b10001 O
b10001 S
1r
0X
0^
0d
0j
1s
0.
05
0<
0C
0K
1p
1/
16
1=
1D
b10000 !
b10000 &
b10000 '
b10000 L
b10000 Q
1J
0,
03
0:
0A
0G
1"
#46000
1*
0-
1,
13
1:
1A
1G
0"
#47000
10
1-
1`
0)
1W
b10010 %
b10010 (
b10010 O
b10010 S
0Z
1]
0[
0/
1X
b10001 !
b10001 &
b10001 '
b10001 L
b10001 Q
1.
0+
03
0:
0A
0G
1"
#48000
11
0*
04
1+
13
1:
1A
1G
0"
#49000
07
1)
0f
04
0W
1Z
0V
10
0]
1[
0b
b10011 %
b10011 (
b10011 O
b10011 S
1`
0X
1a
0.
06
1^
1/
b10010 !
b10010 &
b10010 '
b10010 L
b10010 Q
15
0,
02
0:
0A
0G
1"
#50000
1*
0-
1,
12
1:
1A
1G
0"
#51000
17
1f
14
1V
00
1-
1b
0`
0)
1W
b10100 %
b10100 (
b10100 O
b10100 S
0Z
1]
0[
0/
1X
b10011 !
b10011 &
b10011 '
b10011 L
b10011 Q
1.
0+
02
0:
0A
0G
1"
#52000
18
0*
01
0;
1+
12
1:
1A
1G
0"
#53000
0>
1)
0V
00
0l
0;
0W
1Z
0b
0`
0U
17
0]
1[
0a
0h
b10101 %
b10101 (
b10101 O
b10101 S
1f
0X
0^
1g
0.
05
0=
1d
1/
16
b10100 !
b10100 &
b10100 '
b10100 L
b10100 Q
1<
0,
03
09
0A
0G
1"
#54000
1*
0-
1,
13
19
1A
1G
0"
#55000
10
1-
1`
0)
1W
b10110 %
b10110 (
b10110 O
b10110 S
0Z
1]
0[
0/
1X
b10101 !
b10101 &
b10101 '
b10101 L
b10101 Q
1.
0+
03
09
0A
0G
1"
#56000
11
0*
04
1+
13
19
1A
1G
0"
#57000
0>
0l
0;
0U
17
1)
0h
1f
04
0W
1Z
0V
10
0]
1[
0b
b10111 %
b10111 (
b10111 O
b10111 S
1`
0X
1a
0.
06
1^
1/
b10110 !
b10110 &
b10110 '
b10110 L
b10110 Q
15
0,
02
09
0A
0G
1"
#58000
1*
0-
1,
12
19
1A
1G
0"
#59000
1>
1l
1;
1U
07
1h
0f
14
1V
00
1-
1b
0`
0)
1W
b11000 %
b11000 (
b11000 O
b11000 S
0Z
1]
0[
0/
1X
b10111 !
b10111 &
b10111 '
b10111 L
b10111 Q
1.
0+
02
09
0A
0G
1"
#60000
1?
0*
01
08
0B
1+
12
19
1A
1G
0"
#61000
0I
0P
1E
1)
0V
00
0U
07
0t
1r
0B
0W
1Z
0b
0`
0h
0f
0T
1>
0]
1[
0a
0g
0n
b11001 %
b11001 (
b11001 O
b11001 S
1l
0X
0^
0d
1m
0.
05
0<
0D
1j
1/
16
1=
b11000 !
b11000 &
b11000 '
b11000 L
b11000 Q
1C
0,
03
0:
0@
0G
1"
#62000
1*
0-
1,
13
1:
1@
1G
0"
#63000
10
1-
1`
0)
1W
b11010 %
b11010 (
b11010 O
b11010 S
0Z
1]
0[
0/
1X
b11001 !
b11001 &
b11001 '
b11001 L
b11001 Q
1.
0+
03
0:
0@
0G
1"
#64000
11
0*
04
1+
13
1:
1@
1G
0"
#65000
07
1)
0f
04
0W
1Z
0V
10
0]
1[
0b
b11011 %
b11011 (
b11011 O
b11011 S
1`
0X
1a
0.
06
1^
1/
b11010 !
b11010 &
b11010 '
b11010 L
b11010 Q
15
0,
02
0:
0@
0G
1"
#66000
1*
0-
1,
12
1:
1@
1G
0"
#67000
17
1f
14
1V
00
1-
1b
0`
0)
1W
b11100 %
b11100 (
b11100 O
b11100 S
0Z
1]
0[
0/
1X
b11011 !
b11011 &
b11011 '
b11011 L
b11011 Q
1.
0+
02
0:
0@
0G
1"
#68000
18
0*
01
0;
1+
12
1:
1@
1G
0"
#69000
0I
0P
1E
0t
1r
0B
0T
1>
1)
0V
00
0n
1l
0;
0W
1Z
0b
0`
0U
17
0]
1[
0a
0h
b11101 %
b11101 (
b11101 O
b11101 S
1f
0X
0^
1g
0.
05
0=
1d
1/
16
b11100 !
b11100 &
b11100 '
b11100 L
b11100 Q
1<
0,
03
09
0@
0G
1"
#70000
1*
0-
1,
13
19
1@
1G
0"
#71000
10
1-
1`
0)
1W
b11110 %
b11110 (
b11110 O
b11110 S
0Z
1]
0[
0/
1X
b11101 !
b11101 &
b11101 '
b11101 L
b11101 Q
1.
0+
03
09
0@
0G
1"
#72000
11
0*
04
1+
13
19
1@
1G
0"
#73000
0I
0P
1E
0t
1r
0B
0T
1>
0n
1l
0;
0U
17
1)
0h
1f
04
0W
1Z
0V
10
0]
1[
0b
b11111 %
b11111 (
b11111 O
b11111 S
1`
0X
1a
0.
06
1^
1/
b11110 !
b11110 &
b11110 '
b11110 L
b11110 Q
15
0,
02
09
0@
0G
1"
#74000
1*
0-
1,
12
19
1@
1G
0"
#75000
1I
1P
0E
1t
0r
1B
1T
0>
1n
0l
1;
1U
07
1h
0f
14
1V
00
1-
1b
0`
0)
1W
b0 %
b0 (
b0 O
b0 S
0Z
1]
0[
0/
1X
b11111 !
b11111 &
b11111 '
b11111 L
b11111 Q
1.
0+
02
09
0@
0G
1"
#76000
0*
01
08
0?
0F
1+
12
19
1@
1G
0"
#77000
1)
0V
00
0U
07
0T
0>
0P
0E
0W
1Z
0b
0`
0h
0f
0n
0l
0t
b1 %
b1 (
b1 O
b1 S
0r
0]
1[
0a
0g
0m
0s
0X
0^
0d
0j
0p
0.
05
0<
0C
b0 !
b0 &
b0 '
b0 L
b0 Q
0J
1/
16
1=
1D
1K
0,
03
0:
0A
0H
1"
#78000
1*
0-
1,
13
1:
1A
1H
0"
#79000
10
1-
1`
0)
1W
b10 %
b10 (
b10 O
b10 S
0Z
1]
0[
0/
1X
b1 !
b1 &
b1 '
b1 L
b1 Q
1.
0+
03
0:
0A
0H
1"
#79500
0-
1)
b11110 N
b11 %
b11 (
b11 O
b11 S
1Z
1#
#80000
11
04
1+
13
1:
1A
1H
0"
#81000
17
1f
14
1V
00
1b
b101 %
b101 (
b101 O
b101 S
0`
1a
06
1^
b11 !
b11 &
b11 '
b11 L
b11 Q
15
0+
02
0:
0A
0H
1"
#82000
18
01
0;
1+
12
1:
1A
1H
0"
#83000
0>
0V
10
0l
0;
0b
1`
0U
17
0a
0h
b111 %
b111 (
b111 O
b111 S
1f
0^
1g
05
0=
1d
16
b101 !
b101 &
b101 '
b101 L
b101 Q
1<
0+
03
09
0A
0H
1"
#84000
11
04
1+
13
19
1A
1H
0"
#85000
1>
1l
1;
1U
07
1h
0f
14
1V
00
1b
b1001 %
b1001 (
b1001 O
b1001 S
0`
1a
06
1^
b111 !
b111 &
b111 '
b111 L
b111 Q
15
0+
02
09
0A
0H
1"
#86000
1?
01
08
0B
1+
12
19
1A
1H
0"
#87000
0E
0V
10
0U
07
0r
0B
0b
1`
0h
0f
0T
1>
0a
0g
0n
b1011 %
b1011 (
b1011 O
b1011 S
1l
0^
0d
1m
05
0<
0D
1j
16
1=
b1001 !
b1001 &
b1001 '
b1001 L
b1001 Q
1C
0+
03
0:
0@
0H
1"
#88000
11
04
1+
13
1:
1@
1H
0"
#89000
17
1f
14
1V
00
1b
b1101 %
b1101 (
b1101 O
b1101 S
0`
1a
06
1^
b1011 !
b1011 &
b1011 '
b1011 L
b1011 Q
15
0+
02
0:
0@
0H
1"
#90000
18
01
0;
1+
12
1:
1@
1H
0"
#91000
0E
0r
0B
0T
1>
0V
10
0n
1l
0;
0b
1`
0U
17
0a
0h
b1111 %
b1111 (
b1111 O
b1111 S
1f
0^
1g
05
0=
1d
16
b1101 !
b1101 &
b1101 '
b1101 L
b1101 Q
1<
0+
03
09
0@
0H
1"
#92000
11
04
1+
13
19
1@
1H
0"
#93000
1E
1r
1B
1T
0>
1n
0l
1;
1U
07
1h
0f
14
1V
00
1b
b10001 %
b10001 (
b10001 O
b10001 S
0`
1a
06
1^
b1111 !
b1111 &
b1111 '
b1111 L
b1111 Q
15
0+
02
09
0@
0H
1"
#94000
1F
01
08
0?
0I
1+
12
19
1@
1H
0"
#95000
0V
10
0U
07
0T
0>
0I
0b
1`
0h
0f
0n
0l
0P
1E
0a
0g
0m
0t
b10011 %
b10011 (
b10011 O
b10011 S
1r
0^
0d
0j
1s
05
0<
0C
0K
1p
16
1=
1D
b10001 !
b10001 &
b10001 '
b10001 L
b10001 Q
1J
0+
03
0:
0A
0G
1"
#96000
11
04
1+
13
1:
1A
1G
0"
#97000
17
1f
14
1V
00
1b
b10101 %
b10101 (
b10101 O
b10101 S
0`
1a
06
1^
b10011 !
b10011 &
b10011 '
b10011 L
b10011 Q
15
0+
02
0:
0A
0G
1"
#98000
18
01
0;
1+
12
1:
1A
1G
0"
#99000
0>
0V
10
0l
0;
0b
1`
0U
17
0a
0h
b10111 %
b10111 (
b10111 O
b10111 S
1f
0^
1g
05
0=
1d
16
b10101 !
b10101 &
b10101 '
b10101 L
b10101 Q
1<
0+
03
09
0A
0G
1"
#100000
11
04
1+
13
19
1A
1G
0"
#101000
1>
1l
1;
1U
07
1h
0f
14
1V
00
1b
b11001 %
b11001 (
b11001 O
b11001 S
0`
1a
06
1^
b10111 !
b10111 &
b10111 '
b10111 L
b10111 Q
15
0+
02
09
0A
0G
1"
#102000
1?
01
08
0B
1+
12
19
1A
1G
0"
#103000
0I
0P
1E
0V
10
0U
07
0t
1r
0B
0b
1`
0h
0f
0T
1>
0a
0g
0n
b11011 %
b11011 (
b11011 O
b11011 S
1l
0^
0d
1m
05
0<
0D
1j
16
1=
b11001 !
b11001 &
b11001 '
b11001 L
b11001 Q
1C
0+
03
0:
0@
0G
1"
#104000
11
04
1+
13
1:
1@
1G
0"
#105000
17
1f
14
1V
00
1b
b11101 %
b11101 (
b11101 O
b11101 S
0`
1a
06
1^
b11011 !
b11011 &
b11011 '
b11011 L
b11011 Q
15
0+
02
0:
0@
0G
1"
#106000
18
01
0;
1+
12
1:
1@
1G
0"
#107000
0I
0P
1E
0t
1r
0B
0T
1>
0V
10
0n
1l
0;
0b
1`
0U
17
0a
0h
b11111 %
b11111 (
b11111 O
b11111 S
1f
0^
1g
05
0=
1d
16
b11101 !
b11101 &
b11101 '
b11101 L
b11101 Q
1<
0+
03
09
0@
0G
1"
#108000
11
04
1+
13
19
1@
1G
0"
#109000
1I
1P
0E
1t
0r
1B
1T
0>
1n
0l
1;
1U
07
1h
0f
14
1V
00
1b
b1 %
b1 (
b1 O
b1 S
0`
1a
06
1^
b11111 !
b11111 &
b11111 '
b11111 L
b11111 Q
15
0+
02
09
0@
0G
1"
#110000
01
08
0?
0F
1+
12
19
1@
1G
0"
#111000
0V
10
0U
07
0T
0>
0P
0E
0b
1`
0h
0f
0n
0l
0t
b11 %
b11 (
b11 O
b11 S
0r
0a
0g
0m
0s
0^
0d
0j
0p
05
0<
0C
b1 !
b1 &
b1 '
b1 L
b1 Q
0J
16
1=
1D
1K
0+
03
0:
0A
0H
1"
#112000
11
04
1+
13
1:
1A
1H
0"
#113000
17
1f
14
1V
00
1b
b101 %
b101 (
b101 O
b101 S
0`
1a
06
1^
b11 !
b11 &
b11 '
b11 L
b11 Q
15
0+
02
0:
0A
0H
1"
#114000
18
01
0;
1+
12
1:
1A
1H
0"
#115000
0>
0V
10
0l
0;
0b
1`
0U
17
0a
0h
b111 %
b111 (
b111 O
b111 S
1f
0^
1g
05
0=
1d
16
b101 !
b101 &
b101 '
b101 L
b101 Q
1<
0+
03
09
0A
0H
1"
#116000
11
04
1+
13
19
1A
1H
0"
#117000
1>
1l
1;
1U
07
1h
0f
14
1V
00
1b
b1001 %
b1001 (
b1001 O
b1001 S
0`
1a
06
1^
b111 !
b111 &
b111 '
b111 L
b111 Q
15
0+
02
09
0A
0H
1"
#118000
1?
01
08
0B
1+
12
19
1A
1H
0"
#119000
0E
0V
10
0U
07
0r
0B
0b
1`
0h
0f
0T
1>
0a
0g
0n
b1011 %
b1011 (
b1011 O
b1011 S
1l
0^
0d
1m
05
0<
0D
1j
16
1=
b1001 !
b1001 &
b1001 '
b1001 L
b1001 Q
1C
0+
03
0:
0@
0H
1"
#120000
11
04
1+
13
1:
1@
1H
0"
#121000
17
1f
14
1V
00
1b
b1101 %
b1101 (
b1101 O
b1101 S
0`
1a
06
1^
b1011 !
b1011 &
b1011 '
b1011 L
b1011 Q
15
0+
02
0:
0@
0H
1"
#122000
18
01
0;
1+
12
1:
1@
1H
0"
